Workbook

Sheet Recuperado_Hoja1 (2)
A1: AUTOLUX S.A.
A2: Subsistema Stock
F3: Stock Por Artículo
F5: Suc.: Casa Central - Jujuy Stock: <> 0 Kits de Repuestos: No
A6: Locación | B6: Seg.Locación | C6: Línea | D6: Artículo | E6: Descripción | F6: Ind. | G6: Stock | H6: Cto.Rep. | I6: Cto.Ult.Comp. | J6: Pcio.Vta. | K6: Habilitado | L6: Vta.Últ. 6 Sem.
A7: ??????????? | C7: TOYOTA | D7: 14986300 | E7: 215 / 60 R17 96V DUELER H/P SPORT | F7: IJ | G7: 4 | H7: 237574.47 | J7: 395957.45 | K7: Si
A8: ??????????? | C8: TOYOTA | D8: 16962001 | E8: 195/50 R16 84V ECOPIA EP150 | F8: IJ | G8: 8 | H8: 185124.88 | I8: 189753 | J8: 308541.46 | K8: Si
A9: ??????????? | C9: TOYOTA | D9: 371000KE8000 | E9: CARDAN CON RODAM. | F9: IJ | G9: 1 | H9: 1722645 | I9: 998419.56 | J9: 2460921.4 | K9: Si
A10: ??????????? | C10: TOYOTA | D10: 521290A15000 | E10: COVER, FR BUMPER, LWR | F10: IJ | G10: 1 | H10: 295459.84 | I10: 279352.66 | J10: 422085.48 | K10: Si
A11: ??????????? | C11: TOYOTA | D11: 887060D88000 | E11: TUBE SUB-ASSY, LIQUID | F11: IJ | G11: -1 | H11: 318944.02 | J11: 455634.31 | K11: Si
A12: ??????????? | C12: TOYOTA | D12: 900911 | E12: 235/65 R16C AGILIS 3 | F12: IJ | G12: 4 | H12: 300017.53 | I12: 300017.53 | J12: 500029.21 | K12: Si
A13: ??????????? | C13: TOYOTA | D13: 903168 | E13: 265/60 R18 FRV PRIMACY SUV+ | F13: IJ | G13: 8 | H13: 218082.79 | I13: 218082.65 | J13: 363471.31 | K13: Si
A14: ??????????? | C14: TOYOTA | D14: 997246 | E14: 265/60 R18 LTX TRAIL 114 H | F14: IJ | G14: 12 | H14: 217699.17 | I14: 217699.17 | J14: 362831.95 | K14: Si
A15: B-CENTRO | C15: TOYOTA | D15: 76870YY02100 | E15: BARRA | F15: IJ | G15: 6 | H15: 2147820.6 | I15: 1622459.7 | J15: 3068315.1 | K15: Si
A16: B-CENTRO | C16: TOYOTA | D16: PH3B00KA17FF | E16: BARRA NEGRA GR-S IV | F16: IJ | G16: 2 | H16: 380219.05 | I16: 295767.02 | J16: 543170.07 | K16: Si
A17: D-00-00-A01 | C17: TOYOTA | D17: 088238014000 | E17: LIQUIDO FRENO TOYOTA GENUINO TIPO 3 X 1L | F17: IJ | G17: 102 | H17: 24210.893 | I17: 23620.38 | J17: 34586.99 | K17: Si
A18: D-00-00-B01 | C18: TOYOTA | D18: 088860280500 | E18: ACEITE ATF WS ATM 4L | F18: IJ | G18: 10 | H18: 67921.378 | I18: 67921.38 | J18: 97030.54 | K18: Si
A19: D-00-00-B01 | C19: TOYOTA | D19: 088860300500 | E19: CVT FLUID FE 4L | F19: IJ | G19: 4 | H19: 70085.008 | I19: 68375.62 | J19: 100121.44 | K19: Si
A20: D-00-00-C01 | C20: TOYOTA | D20: 088860270500 | E20: ACEITE TYPE IV -4LTS | F20: IJ | G20: 5 | H20: 41811.028 | I20: 45244.47 | J20: 59730.04 | K20: Si
A21: D-01-00-A01 | C21: TOYOTA | D21: 178010C01000 | E21: FILTRO AIRE | F21: IJ | G21: 65 | H21: 48363.42 | I21: 47508.27 | J21: 69090.6 | K21: Si | L21: 47
A22: D-01-01-A01 | C22: TOYOTA | D22: 178013113100 | E22: FILTRO DE AIRE | F22: IJ | G22: 2 | H22: 51882.341 | I22: 48739.85 | J22: 74117.63 | K22: Si
A23: D-01-01-A02 | C23: TOYOTA | D23: 178010B02000 | E23: FILTRO DE AIRE | F23: IJ | G23: 1 | H23: 38517.752 | I23: 101.56 | J23: 55025.36 | K23: Si
A24: D-01-01-A03 | C24: TOYOTA | D24: 178016707000 | E24: FILTRO DE AIRE | F24: IJ | G24: 3 | H24: 53836.594 | I24: 46960.67 | J24: 76909.42 | K24: Si
A25: D-01-01-A04 | C25: TOYOTA | D25: 871396003000 | E25: FILTRO AIRE ACOND. | F25: IJ | G25: 1 | H25: 40055.939 | I25: 38738.73 | J25: 57222.77 | K25: Si
A26: D-01-01-A05 | C26: TOYOTA | D26: 178017705000 | E26: FILTRO DE AIRE | F26: IJ | G26: 13 | H26: 40228.041 | I26: 39516.73 | J26: 57468.63 | K26: Si
A27: D-01-01-B02 | C27: TOYOTA | D27: 178010Y02000 | E27: FILTRO AIRE | F27: IJ | G27: 31 | H27: 27769.343 | I27: 26905.71 | J27: 39670.49 | K27: Si | L27: 4
A28: D-01-01-C01 | C28: TOYOTA | D28: 178015408000 | E28: FILTRO DE AIRE | F28: IJ | G28: 1 | H28: 53836.594 | I28: 52853.71 | J28: 76909.42 | K28: Si
A29: D-01-01-C02 | C29: TOYOTA | D29: 178013117000 | E29: FILTRO DE AIRE | F29: IJ | G29: 3 | H29: 45200.043 | I29: 24837.31 | J29: 64571.49 | K29: Si
A30: D-01-01-C04 | C30: TOYOTA | D30: 178012702000 | E30: FILTRO DE AIRE | F30: IJ | G30: 2 | H30: 38517.752 | I30: 563.01 | J30: 55025.36 | K30: Si
A31: D-01-01-C06 | C31: TOYOTA | D31: 178017406000 | E31: FILTRO DE AIRE | F31: IJ | G31: 1 | H31: 44790.284 | I31: 42077.35 | J31: 63986.12 | K31: Si
A32: D-01-01-C07 | C32: TOYOTA | D32: 178013702100 | E32: FILTRO DE AIRE | F32: IJ | G32: 1 | H32: 38328.633 | I32: 30803.45 | J32: 54755.19 | K32: Si
A33: D-01-01-D01 | C33: TOYOTA | D33: 178015102000 | E33: FILTRO DE AIRE | F33: IJ | G33: 4 | H33: 52102.981 | I33: 51181.71 | J33: 74432.83 | K33: Si
A34: D-01-01-D02 | C34: TOYOTA | D34: 17801AZA0800 | E34: FILTRO DE AIRE | F34: IJ | G34: 2 | H34: 35271.166 | I34: 33827.7 | J34: 50387.38 | K34: Si
A35: D-01-01-D03 | C35: TOYOTA | D35: 178017006000 | E35: FILTRO DE AIRE | F35: IJ | G35: 1 | H35: 52292.1 | I35: 41177.63 | J35: 74703 | K35: Si
A36: D-01-01-D04 | C36: TOYOTA | D36: 871393004000 | E36: FILTRO AIRE ACOND. | F36: IJ | G36: 3 | H36: 33190.829 | I36: 31781.43 | J36: 47415.47 | K36: Si
A37: D-01-01-E01 | C37: TOYOTA | D37: 178013116000 | E37: ELEMENT SUB-ASSY, AIR CLEANER FILTER | F37: IJ | G37: 8 | H37: 52292.1 | I37: 51367.49 | J37: 74703 | K37: Si
A38: D-01-01-E03 | C38: TOYOTA | D38: 178012801000 | E38: FILTRO DE AIRE | F38: IJ | G38: 1 | H38: 44790.284 | I38: 1631.13 | J38: 63986.12 | K38: Si
A39: D-01-01-E04 | C39: TOYOTA | D39: 178012106000 | E39: FILTRO DE AIRE | F39: IJ | G39: 7 | H39: 27436.493 | I39: 26951.36 | J39: 39194.99 | K39: Si
... A56: D-01-03-B01 | C56: TOYOTA | D56: 90915YZZM300 | E56: FILTRO ACEITE | F56: IJ | G56: 44 | H56: 11881.247 | I56: 11671.16 | J56: 16973.21 | K56: Si
A57: D-01-03-B02 | C57: TOYOTA | D57: 90915TA00500 | E57: FILTRO DE ACEITE | F57: IJ | G57: 50 | H57: 10365.754 | I57: 10182.46 | J57: 14808.22 | K57: Si | L57: 4
A58: D-01-03-C01 | C58: TOYOTA | D58: 90915YZZD200 | E58: FILTRO ACEITE | F58: IJ | G58: 243 | H58: 11691.652 | I58: 11484.92 | J58: 16702.36 | K58: Si | L58: 210
A59: D-01-04-A02 | C59: TOYOTA | D59: 770244208000 | E59: PLATO BBA COMB. | F59: IJ | G59: 1 | H59: 157558.56 | I59: 130957.33 | J59: 225083.66 | K59: Si
A60: D-01-04-A03 | C60: TOYOTA | D60: 770241239000 | E60: PLATO BBA. COMB. | F60: IJ | G60: 3 | H60: 74895.527 | I60: 48134.82 | J60: 106993.61 | K60: Si
A61: D-01-04-A04 | C61: TOYOTA | D61: 233000L04200 | E61: CONJ. FILTRO COMBUST hx05-09 | F61: IJ | G61: 5 | H61: 122708.35 | I61: 98338.1 | J61: 175297.65 | K61: Si
A62: D-01-04-B01 | C62: TOYOTA | D62: 041523701000 | E62: CONJ.FILTRO ACEITE | F62: IJ | G62: 25 | H62: 17820.383 | I62: 17505.27 | J62: 25457.69 | K62: Si | L62: 9
A63: D-01-04-B02 | C63: TOYOTA | D63: 770241240000 | E63: PLATO BBA. COMB. | F63: IJ | G63: 4 | H63: 74895.527 | I63: 70685.14 | J63: 106993.61 | K63: Si
A64: D-01-04-C01 | C64: TOYOTA | D64: 770241003000 | E64: PLACA SUCCION COMB. | F64: IJ | G64: 1 | H64: 111168.85 | I64: 5723.25 | J64: 158812.64 | K64: Si
A65: D-01-04-C02 | C65: TOYOTA | D65: 770241218000 | E65: PLATO BBA. COMB. | F65: IJ | G65: 2 | H65: 124881.96 | I65: 122623 | J65: 178402.8 | K65: Si | L65: 1
A66: D-01-04-C03 | C66: TOYOTA | D66: 770244211000 | E66: PLATO BBA. COMBUSTIBLE | F66: IJ | G66: 1 | H66: 125922.74 | I66: 109859.02 | J66: 179889.63 | K66: Si
A67: D-01-04-C04 | C67: TOYOTA | D67: 770241224000 | E67: PLATO BOMBA COMB. | F67: IJ | G67: 4 | H67: 171821.26 | I67: 16630.28 | J67: 245458.94 | K67: Si
A68: D-01-04-D01 | C68: TOYOTA | D68: 233900E01100 | E68: FILTRO DE COMBUSTIBLE | F68: IJ | G68: 10 | H68: 138153.27 | I68: 133674.4 | J68: 197361.82 | K68: Si
A69: D-01-04-D02 | C69: TOYOTA | D69: 909153000300 | E69: FILTRO ACEITE | F69: IJ | G69: 3 | H69: 45614.849 | I69: 42879.22 | J69: 65164.07 | K69: Si
A70: D-01-04-D03 | C70: TOYOTA | D70: 770244213100 | E70: PLATE SUB-ASSY, FUEL SUCT | F70: IJ | G70: 1 | H70: 308480.66 | I70: 38300.82 | J70: 440686.66 | K70: Si
A71: D-01-04-D04 | B71: R-01-03-B02 | C71: TOYOTA | D71: 909151000900 | E71: FILTRO ACEITE | F71: IJ | G71: 90 | H71: 18472.132 | I71: 18145.51 | J71: 26388.76 | K71: Si
A72: D-01-04-E01 | C72: TOYOTA | D72: 233000L10100 | E72: PORTA FILTRO COMBUSTIBLE | F72: IJ | G72: 1 | H72: 138123.8 | I72: 133891.26 | J72: 197319.72 | K72: Si
A73: D-01-04-E02 | C73: TOYOTA | D73: 233000L12000 | E73: CONJ. FILT. COMB. 2 Picos ABAJO hx 11-15 | F73: IJ | G73: 4 | H73: 118413.56 | I73: 115889.79 | J73: 169162.23 | K73: Si
A74: D-01-04-E03 | C74: TOYOTA | D74: 233900L04100 | E74: FILTRO COMBUSTIBLE | F74: IJ | G74: 36 | H74: 50733.55 | I74: 47025.11 | J74: 72476.5 | K74: Si | L74: 33
A75: D-01-05-A01 | C75: TOYOTA | D75: 909154000200 | E75: FILTRO DE ACEITE | F75: IJ | G75: 6 | H75: 19748.071 | I75: 18551.93 | J75: 28211.53 | K75: Si
A76: D-01-05-A02 | B76: R-01-03-B03 | C76: TOYOTA | D76: 233900L05000 | E76: FILTRO DE COMBUSTIBLE | F76: IJ | G76: 45 | H76: 55054.853 | I76: 53872.43 | J76: 78649.79 | K76: Si
A77: D-01-05-B01 | B77: R-01-03-B01 | C77: TOYOTA | D77: 233900L10000 | E77: FILTRO DE COMBUSTIBLE | F77: IJ | G77: 95 | H77: 73542.273 | I77: 72241.91 | J77: 105060.39 | K77: Si
A78: D-01-05-C01 | C78: TOYOTA | D78: 233905206000 | E78: FILTRO COMBUSTIBLE | F78: IJ | G78: 1 | H78: 146537.66 | I78: 140415.18 | J78: 209339.52 | K78: Si
A79: D-01-05-C01 | C79: TOYOTA | D79: 233906448000 | E79: FILTRO COMBUSTIBLE | F79: IJ | G79: 2 | H79: 62817.692 | I79: 60166.44 | J79: 89739.56 | K79: Si
A80: D-01-05-C02 | C80: TOYOTA | D80: 233903018000 | E80: FILTRO COMBUSTIBLE | F80: IJ | G80: 4 | H80: 71141.217 | I80: 66802.61 | J80: 101630.31 | K80: Si
A81: D-01-05-C03 | C81: TOYOTA | D81: 156203701000 | E81: PORTA FILTRO ACEITE | F81: IJ | G81: 3 | H81: 58528.477 | I81: 57545.27 | J81: 83612.11 | K81: Si
A82: D-01-05-C04 | C82: TOYOTA | D82: 233901124000 | E82: ELEMENT ASSY, FUEL FILTER | F82: IJ | G82: 5 | H82: 73662.834 | I82: 72329.38 | J82: 105232.62 | K82: Si
A83: D-01-05-C05 | C83: TOYOTA | D83: 233003116000 | E83: FILTRO COMBUSTIBLE | F83: IJ | G83: 3 | H83: 67831.589 | I83: 51815.41 | J83: 96902.27 | K83: Si
A84: D-01-05-D02 | C84: TOYOTA | D84: G92DH4201000 | E84: FILTRO NO.1 | F84: IJ | G84: 6 | H84: 20425.125 | I84: 1009.83 | J84: 29178.75 | K84: Si
A85: D-01-05-D03 | C85: TOYOTA | D85: G92DH1205000 | E85: FILTRO NO.1 | F85: IJ | G85: 1 | H85: 29565.368 | I85: 29047.18 | J85: 42236.24 | K85: Si
A86: D-01-05-D04 | C86: TOYOTA | D86: G92DH4707000 | E86: FILTRO NO.1 | F86: IJ | G86: 3 | H86: 15713.446 | I86: 802.2 | J86: 22447.78 | K86: Si
A87: D-01-05-D05 | C87: TOYOTA | D87: 233007514000 | E87: FILTRO COMBUSTIBLE | F87: IJ | G87: 2 | H87: 73035.585 | I87: 56673.53 | J87: 104336.55 | K87: Si
A88: D-01-05-D06 | C88: TOYOTA | D88: 041523802000 | E88: FILTRO DE ACEITE | F88: IJ | G88: 8 | H88: 21011.088 | I88: 107.4 | J88: 30015.84 | K88: Si
A89: D-01-05-E01 | C89: TOYOTA | D89: 232170y02000 | E89: FILTRO COMBUSTIBLE BBA. | F89: IJ | G89: 4 | H89: 25599.49 | I89: 24714.35 | J89: 36570.7 | K89: Si | L89: 1
A90: D-01-05-E02 | C90: TOYOTA | D90: 232170Y03000 | E90: FILTRO COMBUSTIBLE | F90: IJ | G90: 5 | H90: 16589.454 | I90: 16198.33 | J90: 23699.22 | K90: Si
A91: D-01-05-E03 | C91: TOYOTA | D91: 041523801000 | E91: CONJ.FILTRO ACEITE | F91: IJ | G91: 4 | H91: 18994.262 | I91: 149.05 | J91: 27134.66 | K91: Si
A92: D-01-05-E04 | C92: TOYOTA | D92: 041523109000 | E92: FILTRO DE ACEITE | F92: IJ | G92: 9 | H92: 16531.746 | I92: 16239.43 | J92: 23616.78 | K92: Si
A93: D-01-05-E05 | C93: TOYOTA | D93: 233905107000 | E93: FILTRO COMBUSTIBLE | F93: IJ | G93: 5 | H93: 55507.172 | I93: 53157.82 | J93: 79295.96 | K93: Si
A94: D-01-05-F01 | C94: TOYOTA | D94: 771031216000 | E94: TANQUE COMB SUBCONJ | F94: IJ | G94: 1 | H94: 33010.096 | I94: 32905.84 | J94: 47157.28 | K94: Si
A95: D-01-05-F03 | C95: TOYOTA | D95: 909151000400 | E95: FILTRO ACEITE | F95: IJ | G95: 33 | H95: 18472.132 | I95: 18145.51 | J95: 26388.76 | K95: Si
A96: D-01-05-F04 | C96: TOYOTA | D96: 909152000500 | E96: FILTRO ACEITE | F96: IJ | G96: 21 | H96: 21111.006 | I96: 20766.21 | J96: 30158.58 | K96: Si
A97: D-01-05-F06 | C97: TOYOTA | D97: 233903303000 | E97: FILTRO COMBUSTIBLE | F97: IJ | G97: 2 | H97: 48509.671 | I97: 46947.71 | J97: 69299.53 | K97: Si
A98: D-01-05-G01 | C98: TOYOTA | D98: 233007949500 | E98: FILTRO COMBUSTIBLE | F98: IJ | G98: 1 | H98: 67610.949 | I98: 141.66 | J98: 96587.07 | K98: Si
A99: D-01-05-G02 | C99: TOYOTA | D99: 233007943500 | E99: FILTRO COMBUSTIBLE | F99: IJ | G99: 1 | H99: 57504.734 | I99: 319.68 | J99: 82149.62 | K99: Si
A100: D-01-05-G03 | C100: TOYOTA | D100: 233000D10000 | E100: FILTRO COMBUSTIBLE | F100: IJ | G100: 1 | H100: 69596.723 | I100: 177.26 | J100: 99423.89 | K100: Si
A101: D-01-05-G04 | C101: TOYOTA | D101: 156013302100 | E101: FILTRO ACEITE | F101: IJ | G101: 1 | H101: 16094.239 | J101: 22991.77 | K101: Si
A102: D-01-05-G06 | C102: TOYOTA | D102: 909152000400 | E102: FILTRO ACEITE | F102: IJ | G102: 1 | H102: 22473.941 | I102: 20497.77 | J102: 32105.63 | K102: Si
A103: D-01-05-G07 | C103: TOYOTA | D103: 041523108000 | E103: FILTRO DE ACEITE | F103: IJ | G103: 2 | H103: 18994.262 | I103: 13633.09 | J103: 27134.66 | K103: Si
A104: D-03-00-A01 | C104: TOYOTA | D104: 435120K32000 | E104: DISCO FRENO DEL. | F104: IJ | G104: 6 | H104: 177088.36 | I104: 173927.09 | J104: 252983.37 | K104: Si
A105: D-03-00-A02 | C105: TOYOTA | D105: 435120K08000 | E105: DISCO DE FRENO | F105: IJ | G105: 2 | H105: 158682.42 | I105: 155846.6 | J105: 226689.17 | K105: Si
A106: D-03-00-B01 | C106: TOYOTA | D106: 044652646000 | E106: PASTILLAS DE FRENO DEL. | F106: IJ | G106: 2 | H106: 218024.02 | I106: 167133.91 | J106: 311462.89 | K106: Si
A107: D-03-00-B02 | C107: TOYOTA | D107: 044662013000 | E107: JGO. PASTILLAS FRENO | F107: IJ | G107: 1 | H107: 10466.953 | I107: 326.78 | J107: 14952.79 | K107: Si
A108: D-03-00-B03 | C108: TOYOTA | D108: 044664203000 | E108: JGO. PASTILLAS FRENO | F108: IJ | G108: 5 | H108: 103307.64 | I108: 3587.58 | J108: 147582.34 | K108: Si
A109: D-03-00-B04 | C109: TOYOTA | D109: 044660501000 | E109: JGO. PASTILLAS FRENO | F109: IJ | G109: 1 | H109: 122621.67 | I109: 5327.79 | J109: 175173.82 | K109: Si
A110: D-03-00-B06 | C110: TOYOTA | D110: 044666012000 | E110: JGO. PASTILLAS FRENO | F110: IJ | G110: 2 | H110: 147086.11 | I110: 5664.51 | J110: 210123.02 | K110: Si
A111: D-03-00-B07 | C111: TOYOTA | D111: 044650D10100 | E111: KIT PASTILLA FRENO DEL. | F111: IJ | G111: 4 | H111: 159507.12 | I111: 156713.87 | J111: 227867.31 | K111: Si
A112: D-03-00-B08 | C112: TOYOTA | D112: 044663323000 | E112: JGO. PASTILLAS FRENO | F112: IJ | G112: 1 | H112: 108907.21 | I112: 9529.35 | J112: 155581.73 | K112: Si
A113: D-03-00-B09 | C113: TOYOTA | D113: 044651259300 | E113: JGO. PASTILLAS FRENO | F113: IJ | G113: 1 | H113: 154482.34 | I113: 1962.19 | J113: 220689.06 | K113: Si
A114: D-03-00-C01 | C114: TOYOTA | D114: 044664206000 | E114: JGO. PASTILLAS FRENO | F114: IJ | G114: 5 | H114: 103260.35 | I114: 101434.53 | J114: 147514.79 | K114: Si | L114: 1
A115: D-03-00-C02 | C115: TOYOTA | D115: 044660225000 | E115: JGO.PAST.FRENO TRAS. | F115: IJ | G115: 2 | H115: 132024.17 | I115: 127802.12 | J115: 188605.95 | K115: Si
A116: D-03-00-C04 | C116: TOYOTA | D116: 044656028000 | E116: JGO. PASTILLAS FRENO | F116: IJ | G116: 1 | H116: 189306.87 | I116: 145331.52 | J116: 270438.38 | K116: Si
A117: D-03-00-C05 | C117: TOYOTA | D117: 044666014000 | E117: KIT PASTILLAS FRENO TR. | F117: IJ | G117: 4 | H117: 103654.99 | I117: 101845.72 | J117: 148078.55 | K117: Si | L117: 2
...

Sheet 1,Tranf.Pend. Recep
A1: AUTOLUX S.A.
A2: Subsistema Stock
F3: Transferencias de Stock Pendientes de Recepción
F5: Estado: Pendientes Suc.Origen: Todas Suc.Destino: Casa Central - Jujuy Kits de Repuestos: No Observaciones: No Valorizado: Costo de Compra Formato: Detallado
A6: Fecha | C6: Nro. Cpbte. | D6: Sucursal Origen | E6: Sucursal Destino | G6: Usuario | I6: Cantid. Total | K6: CUMPLIMIENTO | L6: Obs
A7: 46055 | C7: 00000999 | D7: Suc. Las Lajitas | E7: Casa Central - Jujuy | G7: Castillo, Jose | I7: =SUBTOTAL(9,I9:I9) -> 0 | J7: 9493.35 | K7: SC | L7: Antigüedad de 1 dia corrido de la tranferencia en analisis - Sin Obs
C8: Linea | D8: Artículo | E8: Ind. | F8: Denominación | I8: Cantid. | K8: Valoriz.
B9: 1 | C9: 815610K26100 | D9: IJ | E9: ACRILICO FARO TRASERO LH | I9: 1 | J9: 9493.35
A10: 46055 | C10: 00002861 | D10: Suc. Tartagal | E10: Casa Central - Jujuy | G10: Zurita, Roberto | I10: =SUBTOTAL(9,I12:I12) -> 0 | J10: 563.01 | K10: SC | L10: Antigüedad de 1 dia corrido de la tranferencia en analisis - Sin Obs
C11: Linea | D11: Artículo | E11: Ind. | F11: Denominación | I11: Cantid. | K11: Valoriz.
B12: 1 | C12: 178012702000 | D12: IJ | E12: FILTRO DE AIRE | I12: 1 | J12: 563.01
F13: Totales Generales | H13: =SUBTOTAL(9,I7:I12) -> 0 | I13: 10056.36
J14: Fecha y Hora de Emisión: 03/02/2026 10:38 Página: 1/1
K15: 1

Sheet 2.Pend.Creditoo
A1: AUTOLUX S.A.
A2: Subsistema Compras
H3: Pendiente Nota Crédito
H4: Suc.: Casa Central - Jujuy Tipo Ped.: Todos Ordenado: Artículo
M5: Cantid. | O5: Cto.Comp. | Q5: =+COUNTIF(Q17:Q39,"sc")/(COUNTIF(Q17:Q39,"sc")+COUNTIF(Q17:Q39,"nc")) -> 0.8
A6: Artículo | B6: Descripción | F6: Fecha | G6: Cuenta | H6: Tipo | I6: Comprobante | J6: Suc. | K6: Cantid. | L6: Tipo Pedido | M6: N° de Remito | N6: Total | O6: Total | P6: Obs | Q6: Cumplimiento
A7: 52119YP90100 | B7: IJ | C7: PARAGOLPE DEL (con faros antinieblas) | F7: 45027 | G7: 1 | H7: Factura | I7: A-0300-00111430 | J7: 2 | K7: 1 | L7: Normal | M7: R-0033-00793070 | N7: 1 | O7: 418480.31
A8: 961364250100 | B8: IJ | C8: CLIP MANGUERA | F8: 45040 | G8: 1 | H8: Factura | I8: A-0300-00112073 | J8: 2 | K8: 1 | L8: Normal | M8: R-0033-00793905 | N8: 1 | O8: 5008.84
A9: 135683901600 | B9: IJ | C9: CORREA DISTRIBUCION | F9: 45069 | G9: 1 | H9: Factura | I9: A-0300-00116267 | J9: 2 | K9: 4 | L9: Normal | M9: R-0033-00798925 | N9: 4 | O9: 448367.88
A10: 043627114000 | B10: IJ | C10: JGO. JUNTAS CAJA TRANSFER | F10: 45231 | G10: 1 | H10: Factura | I10: A-0300-00134535 | J10: 2 | K10: 1 | L10: Normal | N10: 1 | O10: 24621.76
A11: PZ0680000300 | B11: IJ | C11: 12V AIR COMPRESOR (DIGIT - CAT 3 | F11: 45327 | G11: 1 | H11: Factura | I11: A-0300-00144566 | J11: 2 | K11: 1 | L11: Normal | M11: R-0033-00833757 | N11: 1 | O11: 107430.47
A12: 088860280500 | B12: IJ | C12: ACEITE ATF WS ATM 4L | F12: 45581 | G12: 1 | H12: Factura | I12: A-0300-00176708 | J12: 2 | K12: 2 | L12: Normal | N12: 2 | O12: 135842.76
A13: PZ0680000300 | B13: IJ | C13: 12V AIR COMPRESOR (DIGIT - CAT 3 | F13: 45601 | G13: 1 | H13: Factura | I13: A-0300-00178635 | J13: 2 | K13: 1 | L13: Normal | M13: R-0033-00870179 | N13: 2 | O13: 107430.47
A14: 167110L08000 | B14: IJ | C14: DEFLECTOR RADIADOR | F14: 40998 | G14: 1 | H14: Factura | I14: A-0075-00010632 | J14: 2 | K14: 1 | L14: Normal | M14: R-0033-00383043 | N14: 1 | O14: 101455.99
A15: 138011101200 | B15: IJ | C15: BALANCIN VALVULA | F15: 45618 | G15: 1 | H15: Factura | I15: A-0300-00180976 | J15: 2 | K15: 2 | L15: Normal | M15: R-0033-00873034 | N15: 2 | O15: 132295.64
A16: 424310K12000 | B16: IJ | C16: CAMPANA DE FRENO TRAS. | F16: 44684 | G16: 1 | H16: Factura | I16: A-0300-00076403 | J16: 2 | K16: 1 | L16: Normal | M16: R-0033-00750708 | N16: 1 | O16: 247070.57
A17: 08021LL02000 | B17: IJ | C17: LIQ. LIMPIAPARABRISA | F17: 45688 | G17: 10001 | H17: Factura | I17: A-0300-00148818 | J17: 2 | K17: 12 | L17: Normal | N17: 12 | O17: 37490.04
A18: 426110KR8000 | B18: IJ | C18: LLANTA CHAPA 17X6 | F18: 44819 | G18: 1 | H18: Factura | I18: A-0300-00090003 | J18: 2 | K18: 1 | L18: Normal | M18: R-0033-00767489 | N18: 1 | O18: 195101.88
A19: 454903936500 | B19: IJ | C19: BRAZO AUXILIAR | F19: 37956 | G19: 1 | H19: Factura | I19: A-0023-00022679 | J19: 2 | K19: 1 | L19: Normal | M19: R-0009-00086267 | N19: 1 | O19: 25371.15
A20: 480680K05000 | B20: IJ | C20: PARRILA SUSPENSION RH | F20: 44637 | G20: 1 | H20: Factura | I20: A-0300-00071099 | J20: 2 | K20: 1 | L20: Normal | M20: R-0033-00744074 | N20: 1 | O20: 296702.28
A21: 482023588100 | B21: IJ | C21: HOJA ELASTICO | F21: 37925 | G21: 1 | H21: Factura | I21: A-0023-00021389 | J21: 2 | K21: 1 | L21: Normal | M21: R-0009-00082909 | N21: 1 | O21: 87.73
A22: 482100K72000 | B22: IJ | C22: PAQUETE ELASTICOS | F22: 44585 | G22: 1 | H22: Factura | I22: A-0300-00066353 | J22: 2 | K22: 2 | L22: Normal | M22: R-0033-00738141 | N22: 2 | O22: 911030.12
A23: 485314927500 | B23: IJ | C23: AMORTIG.TRASERO | F23: 38895 | G23: 1 | H23: Factura | I23: A-0023-00066548 | J23: 2 | K23: 2 | L23: Normal | M23: R-0009-00225515 | N23: 2 | O23: 224.3
A24: 088238014000 | B24: IJ | C24: LIQUIDO FRENO TOYOTA GENUINO TIPO 3 X 1L | F24: 45688 | G24: 10001 | H24: Factura | I24: A-0300-00148818 | J24: 2 | K24: 10 | L24: Normal | N24: 10 | O24: 236203.8
A25: 521638910100 | B25: IJ | C25: PLACA PARAGOLPE | F25: 37817 | G25: 1 | H25: Factura | I25: A-0023-00016848 | J25: 2 | K25: 1 | L25: Normal | M25: R-0009-00071822 | N25: 1 | O25: 80.59
A26: 753793508000 | B26: IJ | C26: FRANJA LATERAL | F26: 37741 | G26: 1 | H26: Factura | I26: A-0023-00013708 | J26: 2 | K26: 1 | L26: Normal | M26: R-0009-00064270 | N26: 1 | O26: 40.47
A27: 75998AR01000 | B27: IJ | C27: AUTOADHESIVO 4X4 | F27: 44240 | G27: 1 | H27: Factura | I27: A-0300-00034676 | J27: 2 | K27: 2 | L27: Normal | M27: R-0033-00698059 | N27: 2 | O27: 2202.38
A28: 178010L04000 | B28: IJ | C28: FILTRO DE AIRE | F28: 45688 | G28: 10001 | H28: Factura | I28: A-0300-00148818 | J28: 2 | K28: 10 | L28: Normal | N28: 10 | O28: 392026.7
A29: 901190613700 | B29: IJ | C29: BULON | F29: 41333 | G29: 1 | H29: Factura | I29: A-0075-00032789 | J29: 2 | K29: 1 | L29: Normal | M29: R-0033-00416707 | N29: 1 | O29: 2.99
A30: 902012300300 | B30: IJ | C30: ASIENTO RESORTE VALV | F30: 37705 | G30: 1 | H30: Factura | I30: A-0023-00012348 | J30: 2 | K30: 5 | L30: Normal | M30: R-0009-00060688 | N30: 5 | O30: 10.8
A31: 909170604100 | B31: IJ | C31: JUNTA ESCAPE | F31: 37705 | G31: 1 | H31: Factura | I31: A-0023-00012348 | J31: 2 | K31: 1 | L31: Normal | M31: R-0009-00060687 | N31: 1 | O31: 30.75
A32: PH3B00KA1000 | B32: IJ | C32: BARRA DE TRABAJO DC- CAT 1 | F32: 45688 | G32: 10001 | H32: Factura | I32: A-0300-00148818 | J32: 2 | K32: 2 | L32: Normal | N32: 2 | O32: 721097.56
A33: 9913212050AR | B33: IJ | C33: LAMPARA | F33: 41333 | G33: 1 | H33: Factura | I33: A-0075-00032879 | J33: 2 | K33: 10 | L33: Normal | M33: R-0933-00416862 | N33: 10 | O33: 3506.5
A34: PH3B10KA1100 | B34: IJ | C34: LONA CAJA HX 2016 - CAT 2 | F34: 45688 | G34: 10001 | H34: Factura | I34: A-0300-00148818 | J34: 2 | K34: 1 | L34: Normal | N34: 1 | O34: 167954.58
A35: PH7000KM10DO | B35: IJ | C35: JGO ESTRIBO - CAT 2 | F35: 45688 | G35: 10001 | H35: Factura | I35: A-0300-00148818 | J35: 2 | K35: 1 | L35: Normal | N35: 1 | O35: 239039.89 | Q35: NC
A36: BUTERMOACERO | B36: IJ | C36: TERMO DE ACERO INOX. 1LTS | F36: 45733 | G36: 1 | H36: Factura | I36: A-0300-00193274 | J36: 2 | K36: 2 | L36: Normal | M36: R-0033-00888151 | N36: 2 | O36: 130619.84 | P36: Tasa no aprobo el reclamo de los termos, en conocimento luis. | Q36: SC
A37: 136160E01100 | B37: IJ | C37: ENGRANAJE BBA. ACEITE | F37: 45771 | G37: 1 | H37: Factura | I37: A-0200-00197260 | J37: 2 | K37: 1 | L37: Normal | M37: R-0033-00893210 | N37: 1 | O37: 44419.13 | P37: Pendiente de credito reclamado-Aprobado | Q37: SC
A38: 897455002000 | B38: IJ | C38: BATERIA LLAVE TRANSMISORA CR2032 | F38: 45803 | G38: 1 | H38: Factura | I38: A-0300-00200870 | J38: 2 | K38: 1 | L38: Normal | M38: R-0033-00897568 | N38: 1 | O38: 11089.51 | P38: Pendiente de credito reclamado-Aprobado | Q38: SC
A39: 424310K12000 | B39: IJ | C39: CAMPANA DE FRENO TRAS. | F39: 45814 | G39: 1 | H39: Factura | I39: A-0300-00202404 | J39: 2 | K39: 1 | L39: Normal | M39: R-0033-00899488 | N39: 2 | O39: 247070.57 | P39: Pendiente de credito reclamado-Aprobado | Q39: SC
A40: PZU100601500 | B40: IJ | C40: CUBREALFOMFRA STD SC | F40: 40998 | G40: 1 | H40: Factura | I40: A-0075-00010632 | J40: 2 | K40: 1 | L40: Normal | M40: R-0033-00383043 | N40: 1 | O40: 120.28
A41: EN 600 I | B41: XX | C41: BATERIA 12 X 80 A. IZQ. | F41: 37987 | G41: 844 | H41: Factura | I41: A-0002-00003291 | J41: 2 | K41: 1 | L41: Normal | N41: 1 | O41: 161.98
A42: 36020 | B42: XX | C42: AMORTIGUADOR DELANTERO | F42: 37768 | G42: 12 | H42: Factura | I42: A-0007-00124305 | J42: 2 | K42: 30 | L42: Normal | M42: R-0007-00107594 | N42: 30 | O42: 2221.5
M43: Total | N43: 5391912
F44: Artículos Componentes de Kit de Repuestos
M46: Cantid. | N46: Cto.Comp.
A47: Artículo | B47: Descripción | E47: Fecha | F47: Cuenta | G47: Tipo | J47: Cantid. | K47: Tipo Pedido | M47: Total | N47: Total
O49: Fecha y Hora de Emisión: 03/02/2026 11 Página: 1/1

Sheet 3.Remito Pend Carga
A1: Autolux S.A. - Sucursal Salta
A2: Control Integral de Depósito
A3: Fecha:
A4: Remitos pendientes de carga
G5: 1
A6: Fecha Rec. | B6: Nro. Remito | C6: Fecha Carga Siac. | D6: Fecha Ctrol. | E6: Demora (días) | F6: Observacion | G6: Rdo.
A7: 46050 | B7: R-33-932891 | C7: 46050 | D7: 46056 | E7: =+C7-A7 -> 0 | G7: SC
A8: 46055 | B8: R-33-933524 | C8: 46055 | D8: =+D7 -> 46056 | E8: =+C8-A8 -> 0 | G8: SC
A9: 46051 | B9: R-33-933136 | C9: 46051 | D9: =+D8 -> 46056 | E9: =+C9-A9 -> 0 | G9: SC
A10: 46051 | B10: R-33-933109 | C10: 46051 | D10: =+D9 -> 46056 | E10: =+C10-A10 -> 0 | G10: SC
A12: Esta pendiente de implementar la fecha de recepción en sello.

Sheet 4.Inv Rota
A1: AUTOLUX S.A.
A2: Subsistema Stock
F3: Stock Por Artículo
F5: Suc.: Casa Central - Jujuy Stock: <> 0 Kits de Repuestos: No | K5: 1 | L5: =+COUNTIF(L7:L57,"sc")/(COUNTIF(L7:L57,"sc")+COUNTIF(L7:L57,"nc")) -> 0.94117647
A6: Locación | B6: Seg.Locación | C6: Línea | D6: Artículo | E6: Descripción | F6: Ind. | G6: Stock | H6: Conteo | I6: Dif | J6: Obs | K6: Estado Art | L6: Locacion | M6: Cto.Rep. | N6: Stock Valorizado | O6: Cto.Ult.Comp. | P6: Pcio.Vta. | Q6: Habilitado | R6: Vta.Últ. 6 Sem.
A7: D-01-01-C01 | C7: TOYOTA | D7: 178015408000 | E7: FILTRO DE AIRE | F7: IJ | G7: 1 | H7: 1 | I7: =+H7-G7 -> 0 | K7: SC | L7: SC | M7: 53836.594 | N7: =+M7*G7 -> 53836.594 | O7: 52853.71 | P7: 76909.42 | Q7: Si
A8: D-01-01-C02 | C8: TOYOTA | D8: 178013117000 | E8: FILTRO DE AIRE | F8: IJ | G8: 3 | H8: 3 | I8: =+H8-G8 -> 0 | K8: SC | L8: SC | M8: 45200.043 | N8: =+M8*G8 -> 135600.13 | O8: 24837.31 | P8: 64571.49 | Q8: Si
A9: D-01-01-C04 | C9: TOYOTA | D9: 178012702000 | E9: FILTRO DE AIRE | F9: IJ | G9: 2 | H9: 2 | I9: =+H9-G9 -> 0 | K9: SC | L9: SC | M9: 38517.752 | N9: =+M9*G9 -> 77035.504 | O9: 563.01 | P9: 55025.36 | Q9: Si
A10: D-01-01-C06 | C10: TOYOTA | D10: 178017406000 | E10: FILTRO DE AIRE | F10: IJ | G10: 1 | H10: 1 | I10: =+H10-G10 -> 0 | K10: SC | L10: SC | M10: 44790.284 | N10: =+M10*G10 -> 44790.284 | O10: 42077.35 | P10: 63986.12 | Q10: Si
A11: D-01-01-C07 | C11: TOYOTA | D11: 178013702100 | E11: FILTRO DE AIRE | F11: IJ | G11: 1 | H11: 1 | I11: =+H11-G11 -> 0 | K11: SC | L11: SC | M11: 38328.633 | N11: =+M11*G11 -> 38328.633 | O11: 30803.45 | P11: 54755.19 | Q11: Si
A12: D-01-01-D01 | C12: TOYOTA | D12: 178015102000 | E12: FILTRO DE AIRE | F12: IJ | G12: 4 | H12: 4 | I12: =+H12-G12 -> 0 | K12: SC | L12: SC | M12: 52102.981 | N12: =+M12*G12 -> 208411.92 | O12: 51181.71 | P12: 74432.83 | Q12: Si
A13: D-01-01-D02 | C13: TOYOTA | D13: 17801AZA0800 | E13: FILTRO DE AIRE | F13: IJ | G13: 2 | H13: 2 | I13: =+H13-G13 -> 0 | K13: SC | L13: SC | M13: 35271.166 | N13: =+M13*G13 -> 70542.332 | O13: 33827.7 | P13: 50387.38 | Q13: Si
A14: D-01-01-D03 | C14: TOYOTA | D14: 178017006000 | E14: FILTRO DE AIRE | F14: IJ | G14: 1 | H14: 1 | I14: =+H14-G14 -> 0 | K14: SC | L14: SC | M14: 52292.1 | N14: =+M14*G14 -> 52292.1 | O14: 41177.63 | P14: 74703 | Q14: Si
A15: D-01-01-D04 | C15: TOYOTA | D15: 871393004000 | E15: FILTRO AIRE ACOND. | F15: IJ | G15: 3 | H15: 3 | I15: =+H15-G15 -> 0 | K15: SC | L15: SC | M15: 33190.829 | N15: =+M15*G15 -> 99572.487 | O15: 31781.43 | P15: 47415.47 | Q15: Si
A16: D-01-01-E01 | C16: TOYOTA | D16: 178013116000 | E16: ELEMENT SUB-ASSY, AIR CLEANER FILTER | F16: IJ | G16: 8 | H16: 8 | I16: =+H16-G16 -> 0 | J16: Mal Locado | K16: SC | L16: NC | M16: 52292.1 | N16: =+M16*G16 -> 418336.8 | O16: 51367.49 | P16: 74703 | Q16: Si
A17: D-01-01-E03 | C17: TOYOTA | D17: 178012801000 | E17: FILTRO DE AIRE | F17: IJ | G17: 1 | H17: 1 | I17: =+H17-G17 -> 0 | K17: SC | L17: SC | M17: 44790.284 | N17: =+M17*G17 -> 44790.284 | O17: 1631.13 | P17: 63986.12 | Q17: Si
A18: D-01-01-E04 | C18: TOYOTA | D18: 178012106000 | E18: FILTRO DE AIRE | F18: IJ | G18: 7 | H18: 7 | I18: =+H18-G18 -> 0 | K18: SC | L18: SC | M18: 27436.493 | N18: =+M18*G18 -> 192055.45 | O18: 26951.36 | P18: 39194.99 | Q18: Si
A19: D-01-02-A02 | C19: TOYOTA | D19: 885683702000 | E19: FILTRO ANTIPOLEN | F19: IJ | G19: 2 | H19: 2 | I19: =+H19-G19 -> 0 | K19: SC | L19: SC | M19: 33285.392 | N19: =+M19*G19 -> 66570.784 | O19: 1848.74 | P19: 47550.56 | Q19: Si
A20: D-01-02-A04 | C20: TOYOTA | D20: 888802011000 | E20: FILTRO POLEA A/A | F20: IJ | G20: 1 | H20: 1 | I20: =+H20-G20 -> 0 | K20: SC | L20: SC | M20: 1474.123 | N20: =+M20*G20 -> 1474.123 | O20: 141.07 | P20: 2105.89 | Q20: Si
A21: D-01-02-A05 | C21: TOYOTA | D21: 871393010000 | E21: FILTRO ANTIPOLEN | F21: IJ | G21: 1 | H21: 1 | I21: =+H21-G21 -> 0 | K21: SC | L21: SC | M21: 68485.634 | N21: =+M21*G21 -> 68485.634 | O21: 42675.27 | P21: 97836.62 | Q21: Si
A22: D-01-02-A06 | C22: TOYOTA | D22: 871392802000 | E22: FILTRO AIRE ACOND. | F22: IJ | G22: 4 | H22: 4 | I22: =+H22-G22 -> 0 | K22: SC | L22: SC | M22: 33285.392 | N22: =+M22*G22 -> 133141.57 | O22: 32673.62 | P22: 47550.56 | Q22: Si
A23: D-01-02-A08 | C23: TOYOTA | D23: 871390K04000 | E23: FILTRO AIRE ACOND. | F23: IJ | G23: 1 | H23: 1 | I23: =+H23-G23 -> 0 | K23: SC | L23: SC | M23: 21890.82 | N23: =+M23*G23 -> 21890.82 | O23: 20953.54 | P23: 31272.6 | Q23: Si
A24: D-01-04-B01 | C24: TOYOTA | D24: 41523701000 | E24: CONJ.FILTRO ACEITE | F24: IJ | G24: 25 | H24: 25 | I24: =+H24-G24 -> 0 | J24: Poseia un faltante de -1. Se encontraba 1 art separado, facturado a-48-33367 - Sin obs. | K24: SC | L24: SC | M24: 17820.383 | N24: =+M24*G24 -> 445509.58 | O24: 17505.27 | P24: 25457.69 | Q24: Si | R24: 9
A25: D-01-04-B02 | C25: TOYOTA | D25: 770241240000 | E25: PLATO BBA. COMB. | F25: IJ | G25: 4 | H25: 4 | I25: =+H25-G25 -> 0 | K25: SC | L25: SC | M25: 74895.527 | N25: =+M25*G25 -> 299582.11 | O25: 70685.14 | P25: 106993.61 | Q25: Si
A26: D-01-04-C01 | C26: TOYOTA | D26: 770241003000 | E26: PLACA SUCCION COMB. | F26: IJ | G26: 1 | H26: 1 | I26: =+H26-G26 -> 0 | K26: SC | L26: SC | M26: 111168.85 | N26: =+M26*G26 -> 111168.85 | O26: 5723.25 | P26: 158812.64 | Q26: Si
A27: D-01-04-C02 | C27: TOYOTA | D27: 770241218000 | E27: PLATO BBA. COMB. | F27: IJ | G27: 2 | H27: 2 | I27: =+H27-G27 -> 0 | K27: SC | L27: SC | M27: 124881.96 | N27: =+M27*G27 -> 249763.92 | O27: 122623 | P27: 178402.8 | Q27: Si | R27: 1
A28: D-01-04-C03 | C28: TOYOTA | D28: 770244211000 | E28: PLATO BBA. COMBUSTIBLE | F28: IJ | G28: 1 | H28: 1 | I28: =+H28-G28 -> 0 | K28: SC | L28: SC | M28: 125922.74 | N28: =+M28*G28 -> 125922.74 | O28: 109859.02 | P28: 179889.63 | Q28: Si
A29: D-01-04-C04 | C29: TOYOTA | D29: 770241224000 | E29: PLATO BOMBA COMB. | F29: IJ | G29: 4 | H29: 4 | I29: =+H29-G29 -> 0 | K29: SC | L29: SC | M29: 171821.26 | N29: =+M29*G29 -> 687285.03 | O29: 16630.28 | P29: 245458.94 | Q29: Si
A30: D-01-04-D01 | C30: TOYOTA | D30: 233900E01100 | E30: FILTRO DE COMBUSTIBLE | F30: IJ | G30: 10 | H30: 10 | I30: =+H30-G30 -> 0 | K30: SC | L30: SC | M30: 138153.27 | N30: =+M30*G30 -> 1381532.7 | O30: 133674.4 | P30: 197361.82 | Q30: Si
A31: D-01-04-D02 | C31: TOYOTA | D31: 909153000300 | E31: FILTRO ACEITE | F31: IJ | G31: 3 | H31: 3 | I31: =+H31-G31 -> 0 | K31: SC | L31: SC | M31: 45614.849 | N31: =+M31*G31 -> 136844.55 | O31: 42879.22 | P31: 65164.07 | Q31: Si
A32: D-01-05-G04 | C32: TOYOTA | D32: 156013302100 | E32: FILTRO ACEITE | F32: IJ | G32: 1 | H32: 1 | I32: =+H32-G32 -> 0 | K32: SC | L32: SC | M32: 16094.239 | N32: =+M32*G32 -> 16094.239 | P32: 22991.77 | Q32: Si
A33: D-01-05-G06 | C33: TOYOTA | D33: 909152000400 | E33: FILTRO ACEITE | F33: IJ | G33: 1 | H33: 1 | I33: =+H33-G33 -> 0 | K33: SC | L33: SC | M33: 22473.941 | N33: =+M33*G33 -> 22473.941 | O33: 20497.77 | P33: 32105.63 | Q33: Si
A34: D-01-05-G07 | C34: TOYOTA | D34: 041523108000 | E34: FILTRO DE ACEITE | F34: IJ | G34: 2 | H34: 2 | I34: =+H34-G34 -> 0 | K34: SC | L34: SC | M34: 18994.262 | N34: =+M34*G34 -> 37988.524 | O34: 13633.09 | P34: 27134.66 | Q34: Si
A35: D-03-00-A01 | C35: TOYOTA | D35: 435120K32000 | E35: DISCO FRENO DEL. | F35: IJ | G35: 6 | H35: 6 | I35: =+H35-G35 -> 0 | J35: Mal Locado | K35: SC | L35: NC | M35: 177088.36 | N35: =+M35*G35 -> 1062530.2 | O35: 173927.09 | P35: 252983.37 | Q35: Si
A36: D-03-00-A02 | C36: TOYOTA | D36: 435120K08000 | E36: DISCO DE FRENO | F36: IJ | G36: 2 | H36: 2 | I36: =+H36-G36 -> 0 | J36: Mal Locado | K36: SC | L36: NC | M36: 158682.42 | N36: =+M36*G36 -> 317364.84 | O36: 155846.6 | P36: 226689.17 | Q36: Si
A37: D-03-00-B01 | C37: TOYOTA | D37: 044652646000 | E37: PASTILLAS DE FRENO DEL. | F37: IJ | G37: 2 | H37: 2 | I37: =+H37-G37 -> 0 | K37: SC | L37: SC | M37: 218024.02 | N37: =+M37*G37 -> 436048.05 | O37: 167133.91 | P37: 311462.89 | Q37: Si
A38: D-03-00-B02 | C38: TOYOTA | D38: 044662013000 | E38: JGO. PASTILLAS FRENO | F38: IJ | G38: 1 | H38: 1 | I38: =+H38-G38 -> 0 | K38: SC | L38: SC | M38: 10466.953 | N38: =+M38*G38 -> 10466.953 | O38: 326.78 | P38: 14952.79 | Q38: Si
A39: D-03-00-B03 | C39: TOYOTA | D39: 044664203000 | E39: JGO. PASTILLAS FRENO | F39: IJ | G39: 5 | H39: 5 | I39: =+H39-G39 -> 0 | K39: SC | L39: SC | M39: 103307.64 | N39: =+M39*G39 -> 516538.19 | O39: 3587.58 | P39: 147582.34 | Q39: Si
A40: D-03-00-B04 | C40: TOYOTA | D40: 044660501000 | E40: JGO. PASTILLAS FRENO | F40: IJ | G40: 1 | H40: 1 | I40: =+H40-G40 -> 0 | K40: SC | L40: SC | M40: 122621.67 | N40: =+M40*G40 -> 122621.67 | O40: 5327.79 | P40: 175173.82 | Q40: Si
A41: D-03-00-B06 | C41: TOYOTA | D41: 044666012000 | E41: JGO. PASTILLAS FRENO | F41: IJ | G41: 2 | H41: 2 | I41: =+H41-G41 -> 0 | K41: SC | L41: SC | M41: 147086.11 | N41: =+M41*G41 -> 294172.23 | O41: 5664.51 | P41: 210123.02 | Q41: Si
A42: D-03-00-D08 | C42: TOYOTA | D42: 044664710000 | E42: JGO. PASTILLAS FRENO | F42: IJ | G42: 1 | H42: 1 | I42: =+H42-G42 -> 0 | K42: SC | L42: SC | M42: 77848.218 | N42: =+M42*G42 -> 77848.218 | O42: 871.88 | P42: 111211.74 | Q42: Si
A43: D-03-00-E01 | C43: TOYOTA | D43: 044650K30000 | E43: JGO.PASTILLA FRENO | F43: IJ | G43: 4 | H43: 4 | I43: =+H43-G43 -> 0 | K43: SC | L43: SC | M43: 177100.36 | N43: =+M43*G43 -> 708401.46 | O43: 171372.85 | P43: 253000.52 | Q43: Si
A44: D-03-00-E02 | C44: TOYOTA | D44: 044664710100 | E44: JGO. PASTILLAS FRENO | F44: IJ | G44: 1 | H44: 1 | I44: =+H44-G44 -> 0 | K44: SC | L44: SC | M44: 105763.06 | N44: =+M44*G44 -> 105763.06 | O44: 9233.67 | P44: 151090.09 | Q44: Si
A45: D-03-00-E03 | C45: TOYOTA | D45: 044650527000 | E45: JGO.PASTILLA DE FRENO | F45: IJ | G45: 1 | H45: 1 | I45: =+H45-G45 -> 0 | K45: SC | L45: SC | M45: 189307.5 | N45: =+M45*G45 -> 189307.5 | O45: 45965.68 | P45: 270439.28 | Q45: Si
A46: D-03-00-E04 | C46: TOYOTA | D46: 044663322000 | E46: JGO.PASTILLAS FRENO RR | F46: IJ | G46: 2 | H46: 2 | I46: =+H46-G46 -> 0 | K46: SC | L46: SC | M46: 108907.21 | N46: =+M46*G46 -> 217814.42 | O46: 991.14 | P46: 155581.73 | Q46: Si
A47: D-03-00-E05 | C47: TOYOTA | D47: 044650K60000 | E47: JGO. PASTILLAS FRENO | F47: IJ | G47: 9 | H47: 9 | I47: =+H47-G47 -> 0 | K47: SC | L47: SC | M47: 226473.03 | N47: =+M47*G47 -> 2038257.3 | O47: 222437.63 | P47: 323532.9 | Q47: Si
A48: D-03-00-F01 | C48: TOYOTA | D48: 044653348000 | E48: JGO. PASTILLAS FRENO | F48: IJ | G48: 1 | H48: 1 | I48: =+H48-G48 -> 0 | K48: SC | L48: SC | M48: 157349.43 | N48: =+M48*G48 -> 157349.43 | O48: 130090.59 | P48: 224784.9 | Q48: Si
A49: D-03-05-F01 | C49: TOYOTA | D49: 044950K05000 | E49: JGO. ZAPATAS DE FRENO | F49: IJ | G49: 15 | H49: 15 | I49: =+H49-G49 -> 0 | K49: SC | L49: SC | M49: 313115.66 | N49: =+M49*G49 -> 4696734.8 | O49: 309823.56 | P49: 447308.08 | Q49: Si | R49: 7
A50: D-03-06-C01 | C50: TOYOTA | D50: 485310964100 | E50: AMORTIGUADOR | F50: IJ | G50: 14 | H50: 14 | I50: =+H50-G50 -> 0 | K50: SC | L50: SC | M50: 84663.404 | N50: =+M50*G50 -> 1185287.7 | O50: 83192.72 | P50: 120947.72 | Q50: Si
A51: D-03-06-E03 | C51: TOYOTA | D51: 485318Z01900 | E51: SET AMORTIGUADOR RR RH | F51: IJ | G51: 12 | H51: 12 | I51: =+H51-G51 -> 0 | K51: SC | L51: SC | M51: 83279.035 | N51: =+M51*G51 -> 999348.42 | O51: 80627.44 | P51: 118970.05 | Q51: Si | R51: 1
A52: D-03-06-F02 | C52: TOYOTA | D52: 485300274000 | E52: AMORTIGUADOR TRAS. | F52: IJ | G52: 1 | H52: 1 | I52: =+H52-G52 -> 0 | K52: SC | L52: SC | M52: 184670.87 | N52: =+M52*G52 -> 184670.87 | O52: 7686.63 | P52: 263815.53 | Q52: Si
A53: D-03-06-F05 | C53: TOYOTA | D53: 485410934100 | E53: SET AMORTIGUADOR RR LH | F53: IJ | G53: 15 | H53: 15 | I53: =+H53-G53 -> 0 | K53: SC | L53: SC | M53: 79030.105 | N53: =+M53*G53 -> 1185451.6 | O53: 77661.51 | P53: 112900.15 | Q53: Si
A54: D-05-00-A01 | C54: TOYOTA | D54: 90369T000300 | E54: RODAMIENTO | F54: IJ | G54: 6 | H54: 6 | I54: =+H54-G54 -> 0 | K54: SC | L54: SC | M54: 112529.2 | N54: =+M54*G54 -> 675175.2 | O54: 107767.52 | P54: 160756 | Q54: Si | R54: 4
A55: D-05-00-A02 | C55: TOYOTA | D55: 310010K02000 | E55: CONJ. EMBRAGUE | F55: IJ | G55: 1 | H55: 1 | I55: =+H55-G55 -> 0 | K55: SC | L55: SC | M55: 1300706.6 | N55: =+M55*G55 -> 1300706.6 | O55: 1274563.9 | P55: 1858152.3 | Q55: Si
A56: D-05-00-B02 | C56: TOYOTA | D56: 863000228000 | E56: AMPLIFICADOR ANTENA | F56: IJ | G56: 1 | H56: 1 | I56: =+H56-G56 -> 0 | K56: SC | L56: SC | M56: 472728.17 | N56: =+M56*G56 -> 472728.17 | O56: 134.74 | P56: 675325.96 | Q56: Si
A57: D-06-00-B01 | C57: TOYOTA | D57: 166202702100 | E57: TENSOR CORREA | F57: IJ | G57: 13 | H57: 13 | I57: =+H57-G57 -> 0 | K57: SC | L57: SC | M57: 214082.42 | N57: =+M57*G57 -> 2783071.5 | O57: 9971.47 | P57: 305832.03 | Q57: Si
E61: Cantidad | F61: $ | G61: %
D62: Muestra | E62: =+SUM(G7:G57) -> 213 | F62: =+SUM(N7:N57) -> 24978980 | G62: 1
D63: Faltante | E63: =+SUMIF(I7:I57,"<0") -> 0 | F63: =+I24*M24 -> 0 | G63: =+F63*G$62/F$62 -> 0
D64: Sobrante | E64: =+SUMIF(I7:I57,">0") -> 0 | F64: 0 | G64: =+F64*G$62/F$62 -> 0
D65: Dif.Neta | E65: =+E64+E63 -> 0 | F65: =+F63 -> 0 | G65: =+F65*G$62/F$62 -> 0
D66: Dif.Absoluta | E66: =+E64-E63 -> 0 | F66: =+F65 -> 0 | G66: =+F66*G$62/F$62 -> 0

Sheet 7.Remito Pend de Fact
A1: AUTOLUX S.A.
A2: Subsistema Ventas
F4: Pendiente de Facturar
A6: ( 50105) | F6: Suc.: Casa Central - Jujuy Agrupado: Cliente
A7: Cliente: LEDESMA S.A.A.I. | F7: ( 50105) | M7: 0.5
A8: Fecha | C8: Comprobante | D8: Artículo | E8: Descripción | H8: Suc. | I8: Cantid. | J8: Pcio.Unit. | K8: Total | L8: Justif Control Ant | M8: Cumplimiento
A9: 45485 | C9: R-0005-00003816 | D9: 1 | E9: 90366T006100 | F9: IJ | G9: RODAMIENTO | H9: 2 | I9: 2 | J9: 137030.67 | K9: 274061.34 | L9: REMITO QUE SE HIZO A LEDESMA, NO LLAMO AL REMITO QUE ESTABA // ver mail | M9: SC
A10: 45485 | C10: R-0005-00003816 | D10: 1 | E10: 90916T200600 | F10: IJ | G10: CORREA | H10: 2 | I10: 4 | J10: 53655.18 | K10: 214620.72 | L10: REMITO QUE SE HIZO A LEDESMA, NO LLAMO AL REMITO QUE ESTABA /ver mail | M10: SC
A11: 45987 | C11: R-0005-00004364 | D11: 1 | E11: 443050K03000 | F11: IJ | G11: TAPA RESERVORIO | H11: 2 | I11: 1 | J11: 26908.78 | K11: 26908.78 | L11: Se olvidaron de facturar el remito - | M11: NC
A13: ( 55788)
F14: Artículos Componentes de Kit de Repuestos
G17: Total General
G18: Total Cliente | H18: =SUBTOTAL(9,I9:I13) -> 7 | I18: 515590.84
A20: Cliente: MINA PIRQUITAS S.A
A21: 46050 | C21: R-0005-00004421 | D21: 1 | E21: 903114704100 | F21: IJ | G21: RETEN SEMIEJ. IZQ. | H21: 2 | I21: 1 | J21: 53047.04 | K21: 53047.04 | L21: Se olvidaron de facturar el remito - | M21: NC
A22: 46050 | C22: R-0005-00004421 | D22: 1 | E22: 137500E01000 | F22: IJ | G22: BOTADOR | H22: 2 | I22: 16 | J22: 53914.46 | K22: 862631.36 | L22: Se olvidaron de facturar el remito -
A23: 46050 | C23: R-0005-00004421 | D23: 1 | E23: 270600L16000 | F23: IJ | G23: ALTERNADOR CON REGULADOR (denso) | H23: 2 | I23: 1 | J23: 1264462.8 | K23: 1264462.8 | L23: Se olvidaron de facturar el remito -
A24: 46050 | C24: R-0005-00004421 | D24: 1 | E24: 049420K16000 | F24: IJ | G24: JGO. REP. RESORTES ZAPATA FRENO | H24: 2 | I24: 1 | J24: 35990.33 | K24: 35990.33 | L24: Se olvidaron de facturar el remito -
A25: 46050 | C25: R-0005-00004421 | D25: 1 | E25: 443100K13000 | F25: IJ | G25: BOMBA DIRECCION HIDRAULIC | H25: 2 | I25: 2 | J25: 1680247.9 | K25: 3360495.9 | L25: Se olvidaron de facturar el remito -
A26: 46050 | C26: R-0005-00004421 | D26: 1 | E26: 894817101000 | F26: IJ | G26: SENSOR DIF. PRESION | H26: 2 | I26: 1 | J26: 430030.41 | K26: 430030.41 | L26: Se olvidaron de facturar el remito -
A27: 46050 | C27: R-0005-00004421 | D27: 1 | E27: 894257107000 | F27: IJ | G27: SENSOR TEMPERATURA GAS | H27: 2 | I27: 2 | J27: 723719.01 | K27: 1447438 | L27: Se olvidaron de facturar el remito -
A28: 46050 | C28: R-0005-00004421 | D28: 1 | E28: 281000L20100 | F28: IJ | G28: MOTOR DE ARRANQUE | H28: 2 | I28: 1 | J28: 1576859.5 | K28: 1576859.5 | L28: Se olvidaron de facturar el remito -
A29: 46050 | C29: R-0005-00004421 | D29: 1 | E29: 049490K07000 | F29: IJ | G29: JGO.REPAR.FRENO TRAS | H29: 2 | I29: 1 | J29: 12216.94 | K29: 12216.94 | L29: Se olvidaron de facturar el remito -
A30: 46050 | C30: R-0005-00004421 | D30: 1 | E30: 480680K12100 | F30: IJ | G30: PARRILLA SUSPENSION | H30: 2 | I30: 2 | J30: 389603.31 | K30: 779206.62 | L30: Se olvidaron de facturar el remito -
A31: 46050 | C31: R-0005-00004421 | D31: 1 | E31: 137160E01000 | F31: IJ | G31: TAPON VASTAGO VALV. | H31: 2 | I31: 17 | J31: 1971.07 | K31: 33508.19 | L31: Se olvidaron de facturar el remito -
F33: Artículos Componentes de Kit de Repuestos
G36: Total General
G37: Total Cliente | H37: =SUBTOTAL(9,I21:I32) -> 45 | I37: 9855887.1
G39: Total General | H39: =SUBTOTAL(9,I9:I38) -> 10371530 | I39: 10371478
J41: Fecha y Hora de Emisión: 03/02/2026 11:36 Página: 1/1

Sheet 8.Ventas Internas
A1: AUTOLUX S.A.
A2: Subsistema Ventas
E3: Ventas de Repuestos c/Internas
F5: Suc.: Casa Central - Jujuy Desde: 01/01/2026 Hasta: 31/01/2026 Formato: Resumido
A6: Fecha | B6: Cpbte. | E6: Nro. Cpbte. | F6: Interna | I6: Importe | J6: =+COUNTIF(J12:J83,"sc")/(COUNTIF(J12:J83,"sc")+COUNTIF(J12:J83,"nc")) -> 1
A7: 46030 | B7: Vta. Mostrador | C7: 2 | D7: 15011 | F7: Insumos Varios Taller | I7: 1013209.4 | J7: SC | K7: Firmado por Augusto fasciano
A8: 46024 | B8: Vta. Taller | C8: 2 | D8: 239624 | F8: Cortesias - TMS | I8: 27733.24
A9: 46024 | B9: Vta. Taller | C9: 2 | D9: 239628 | F9: Cortesías - Planes | I9: 67262.85
A10: 46024 | B10: Vta. Taller | C10: 2 | D10: 239629 | F10: Cortesias - TMS | I10: 57173.43
A11: 46024 | B11: Dev. Taller | C11: 2 | D11: 194954 | F11: Cortesías - Planes | I11: -67262.85
A12: 46027 | B12: Vta. Taller | C12: 2 | D12: 239638 | F12: Reparación Usadas | I12: 807220.01 | J12: SC
A13: 46027 | B13: Vta. Taller | C13: 2 | D13: 239670 | F13: Reparación Usadas | I13: 819328.3 | J13: SC
A14: 46027 | B14: Vta. Taller | C14: 2 | D14: 239679 | F14: Cortesías - Planes | I14: 52271.75
A15: 46027 | B15: Dev. Taller | C15: 2 | D15: 194957 | F15: Reparación Usadas | I15: -807220.01
A16: 46034 | B16: Vta. Mostrador | C16: 2 | D16: 15013 | F16: Reparación Usadas | I16: 451498.45 | J16: SC | K16: Firmado por Esteban Toril
A17: 46045 | B17: Vta. Mostrador | C17: 2 | D17: 15019 | F17: Preparación Pre-Entrega | I17: 230804.5 | J17: SC | K17: Firmado por Jorge Jijena
A18: 46028 | B18: Vta. Mostrador | C18: 2 | D18: 15007 | F18: Reparación Usadas | I18: 189038.88 | J18: SC | K18: Firmado por Martin Diaz
A19: 46038 | B19: Vta. Mostrador | C19: 2 | D19: 15017 | F19: Preparación Pre-Entrega | I19: 186193.82 | J19: SC | K19: Firmado por Jorge Jijena
A20: 46045 | B20: Vta. Mostrador | C20: 2 | D20: 15020 | F20: Reparación Usadas | I20: 158751.21 | J20: SC | K20: Firmado por Martin Diaz
A21: 46028 | B21: Vta. Mostrador | C21: 2 | D21: 15004 | F21: Reparación Usadas | I21: 151892.85 | J21: SC | K21: Firmado por Esteban Toril
A22: 46034 | B22: Vta. Mostrador | C22: 2 | D22: 15012 | F22: Cortesías - 0km | I22: 91874.82
A23: 46028 | B23: Vta. Taller | C23: 2 | D23: 239717 | F23: Cortesías - Planes | I23: 52271.75
A24: 46028 | B24: Vta. Taller | C24: 2 | D24: 239727 | F24: Cortesias - TMS | I24: 167560.42
A25: 46028 | B25: Vta. Taller | C25: 2 | D25: 239729 | F25: Cortesias - TMS | I25: 24538.51
A26: 46028 | B26: Vta. Taller | C26: 2 | D26: 239732 | F26: Cortesias - TMS | I26: 244038.15
A27: 46037 | B27: Vta. Mostrador | C27: 2 | D27: 15016 | F27: Cortesías - 0km | I27: 91874.82
A28: 46024 | B28: Vta. Mostrador | C28: 2 | D28: 15001 | F28: Cortesias - Repuestos | I28: 45030
A29: 46029 | B29: Vta. Taller | C29: 2 | D29: 239775 | F29: Cortesías - Planes | I29: 27733.24
A30: 46029 | B30: Vta. Taller | C30: 2 | D30: 239776 | F30: Cortesía Ventas - Taller | I30: 276223.02 | J30: SC
A31: 46029 | B31: Vta. Taller | C31: 2 | D31: 239791 | F31: Cortesías - Planes | I31: 474362.73
A32: 46029 | B32: Vta. Taller | C32: 2 | D32: 239801 | F32: Cortesías - Planes | I32: 474362.73
A33: 46029 | B33: Vta. Taller | C33: 2 | D33: 239811 | F33: Cortesías - Planes | I33: 203944.84
A34: 46029 | B34: Vta. Taller | C34: 2 | D34: 239815 | F34: Cortesías - Planes | I34: 265073.02
A35: 46029 | B35: Vta. Taller | C35: 2 | D35: 239817 | F35: Cortesías - 0km | I35: 652555.43
A36: 46029 | B36: Dev. Mostrador | C36: 2 | D36: 854 | F36: Cortesía Ventas - Taller | I36: -20208.18
A37: 46029 | B37: Dev. Taller | C37: 2 | D37: 194963 | F37: Cortesías - Planes | I37: -203944.84
A38: 46028 | B38: Vta. Mostrador | C38: 2 | D38: 15003 | F38: Reparación Usadas | I38: 28605.51
A39: 46030 | B39: Vta. Taller | C39: 2 | D39: 239833 | F39: Cortesías - Planes | I39: 45910.99
A40: 46030 | B40: Vta. Taller | C40: 2 | D40: 239841 | F40: Cortesías - 0km | I40: 295819.66
A41: 46030 | B41: Vta. Taller | C41: 2 | D41: 239871 | F41: Cortesías - Planes | I41: 47638.09
A42: 46030 | B42: Vta. Taller | C42: 2 | D42: 239879 | F42: Reparación Usadas | I42: 190371.83
... A44: 46030 | B44: Vta. Taller | C44: 2 | D44: 239888 | F44: Reparación Usadas | I44: 189038.88
A45: 46030 | B45: Vta. Taller | C45: 2 | D45: 239891 | F45: Cortesías - 0km | I45: 873592.96 | J45: SC | K45: Control de Accesorios a traves de la operación
A46: 46031 | B46: Vta. Taller | C46: 2 | D46: 239924 | F46: Reparación Usadas | I46: 13465.84
A47: 46031 | B47: Dev. Mostrador | C47: 2 | D47: 855 | F47: Insumos Varios Taller | I47: -1013209.4
A48: 46031 | B48: Dev. Taller | C48: 2 | D48: 194968 | F48: Cortesía Ventas - Taller | I48: -832148.36
A49: 46029 | B49: Vta. Mostrador | C49: 2 | D49: 15010 | F49: Cortesía Ventas - Taller | I49: 26951.37
A50: 46048 | B50: Vta. Mostrador | C50: 2 | D50: 15021 | F50: Reparación Usadas | I50: 24392.84
A51: 46028 | B51: Vta. Mostrador | C51: 2 | D51: 15002 | F51: Reparación Usadas | I51: 20705.53
A52: 46034 | B52: Vta. Taller | C52: 2 | D52: 240005 | F52: Reparación Usadas | I52: 72590.25
A53: 46029 | B53: Vta. Mostrador | C53: 2 | D53: 15009 | F53: Cortesía Ventas - Taller | I53: 20208.18
A54: 46035 | B54: Vta. Taller | C54: 2 | D54: 240017 | F54: Reparación Usadas | I54: 137267.69
A55: 46035 | B55: Vta. Taller | C55: 2 | D55: 240054 | F55: Cortesías - 0km | I55: 873592.96 | J55: SC | K55: Control de Accesorios a traves de la operación
A56: 46036 | B56: Vta. Taller | C56: 2 | D56: 240074 | F56: Cortesía Ventas - Taller | I56: 48438.5 | J56: SC
A57: 46036 | B57: Vta. Taller | C57: 2 | D57: 240110 | F57: Cortesías - Planes | I57: 47582.02
A58: 46036 | B58: Vta. Taller | C58: 2 | D58: 240125 | F58: Cortesías - Planes | I58: 379385.4
A59: 46036 | B59: Vta. Taller | C59: 2 | D59: 240128 | F59: Cortesías - Planes | I59: 51890.04
A60: 46044 | B60: Vta. Mostrador | C60: 2 | D60: 15018 | F60: Cortesías - 0km | I60: 14481.39
A61: 46037 | B61: Vta. Taller | C61: 2 | D61: 240140 | F61: Cortesías - 0km | I61: 669648.12 | J61: SC | K61: Control de Accesorios a traves de la operación
A62: 46037 | B62: Vta. Taller | C62: 2 | D62: 240158 | F62: Cortesías - 0km | I62: 7173.66
A63: 46037 | B63: Vta. Taller | C63: 2 | D63: 240172 | F63: Cortesías - 0km | I63: 473399
A64: 46037 | B64: Vta. Taller | C64: 2 | D64: 240184 | F64: Cortesías - Planes | I64: 167504.35
A65: 46037 | B65: Vta. Taller | C65: 2 | D65: 240186 | F65: Cortesías - 0km | I65: 290262.72
A66: 46037 | B66: Vta. Taller | C66: 2 | D66: 240196 | F66: Reparación Usadas | I66: 23162.16
A67: 46037 | B67: Dev. Mostrador | C67: 2 | D67: 856 | F67: Cortesías - 0km | I67: -91874.82
A68: 46051 | B68: Vta. Mostrador | C68: 2 | D68: 15022 | F68: Cortesías - 0km | I68: 14481.39
A69: 46038 | B69: Vta. Taller | C69: 2 | D69: 240228 | F69: Reparación Usadas | I69: 284706.12
A70: 46041 | B70: Vta. Taller | C70: 2 | D70: 240259 | F70: Cortesías - 0km | I70: 344594.79
A71: 46042 | B71: Vta. Taller | C71: 2 | D71: 272407 | F71: Cortesías - Planes | I71: 27351.53
A72: 46042 | B72: Vta. Taller | C72: 2 | D72: 272433 | F72: Cortesías - Planes | I72: 21316.41
A73: 46042 | B73: Vta. Taller | C73: 2 | D73: 272434 | F73: Cortesías - Planes | I73: 1727.1
... A75: 46042 | B75: Vta. Taller | C75: 2 | D75: 272446 | F75: Reparación Usadas | I75: 251043.37
A76: 46042 | B76: Vta. Taller | C76: 2 | D76: 272448 | F76: Reparación Usadas | I76: 2191081.5 | J76: SC
A77: 46028 | B77: Vta. Mostrador | C77: 2 | D77: 15005 | F77: Reparación Usadas | I77: 13465.84
A78: 46044 | B78: Vta. Taller | C78: 2 | D78: 272561 | F78: Cortesías - 0km | I78: 367768.39
A79: 46028 | B79: Vta. Mostrador | C79: 2 | D79: 15006 | F79: Reparación Usadas | I79: 13465.84
A80: 46028 | B80: Vta. Mostrador | C80: 2 | D80: 15008 | F80: Reparación Usadas | I80: 12196.42
A81: 46045 | B81: Vta. Taller | C81: 2 | D81: 272582 | F81: Cortesías - Planes | I81: 165777.25
A82: 46045 | B82: Vta. Taller | C82: 2 | D82: 272589 | F82: Cortesías - Planes | I82: 474362.73 | J82: SC | K82: Control de Accesorios a traves de la operación
A83: 46045 | B83: Vta. Taller | C83: 2 | D83: 272617 | F83: Cortesías - 0km | I83: 270417.89 | J83: SC | K83: Control de Accesorios a traves de la operación
A84: 46034 | B84: Vta. Mostrador | C84: 2 | D84: 15014 | F84: Reparación Usadas | I84: 11111.92
A85: 46048 | B85: Vta. Taller | C85: 2 | D85: 272658 | F85: Cortesías - Planes | I85: 515964.25
A86: 46050 | B86: Vta. Taller | C86: 2 | D86: 272778 | F86: Cortesías - Planes | I86: 45854.92
A87: 46035 | B87: Vta. Mostrador | C87: 2 | D87: 15015 | F87: Cortesias - Repuestos | I87: 8130.99
A88: 46051 | B88: Vta. Taller | C88: 2 | D88: 272812 | F88: Cortesías - Planes | I88: 27351.53
A89: 46051 | B89: Vta. Taller | C89: 2 | D89: 272834 | F89: Cortesías - 0km | I89: 474362.73
A90: 46051 | B90: Dev. Taller | C90: 2 | D90: 195006 | F90: Cortesía Ventas - Taller | I90: -1542710.6
H91: Total | I91: 13366668
J92: Fecha y Hora de Emisión: 03/02/2026 11:49 Página: 1/1

Sheet 9.Transf.Pend. Entrega
A1: AUTOLUX S.A.
A2: Subsistema Stock
F3: Transferencias de Stock Pendientes de Recepción
F5: Estado: Pendientes Suc.Origen: Casa Central - Jujuy Suc.Destino: Todas Kits de Repuestos: No Observaciones: No Valorizado: Costo de Compra Formato: Detallado
A6: Fecha | C6: Nro. Cpbte. | D6: Sucursal Origen | E6: Sucursal Destino | G6: Usuario | I6: Cantid. Total | K6: Cumplimiento | L6: Obs
A7: 46056 | C7: 00005217 | D7: Casa Central - Jujuy | E7: Suc. Tartagal | G7: Chauque, Hugo | I7: =SUBTOTAL(9,I9:I11) -> 0 | J7: 1079596.2 | K7: SC | L7: Transferencias pendientes de recepcionar con fecha igual a la ejecucion del control
C8: Linea | D8: Artículo | E8: Ind. | F8: Denominación | I8: Cantid. | K8: Valoriz.
B9: 1 | C9: 14881001 | D9: IJ | E9: 265/65/17 DUELER A/T REVO 2 | I9: 3 | J9: 657189.36
B10: 1 | C10: GRARRANCADOR | D10: IJ | E10: ARRANCADOR DE BATERIA GR | I10: 1 | J10: 97537.85
B11: 1 | C11: 18909001 | D11: IJ | E11: 225/45 R17 94W TURANZA ER300 | I11: 2 | J11: 324868.98
F12: Totales Generales | H12: =SUBTOTAL(9,I7:I11) -> 0 | I12: 1079596.2
J13: Fecha y Hora de Emisión: 03/02/2026 10:5 Página: 1/1
K14: 1

Sheet KPI'S
B2: INDICADORES
B4: CONTROL DE DEPÓSITO
B5: Categoría | C5: Características
B6: Periódo: Actual | C6: Corresponde al momento en el que realizamos el control en depósito
B7: Alcance: Muestreo | C7: Tanto el control de documentación como el inventario físico de mercaderías se basará en una muestra elegida, previo análisis del stock y corte de documentación.
B9: Referencias
B10: SC | C10: Si Cumple
B11: PC | C11: Parcialmente Cumple
B12: NC | C12: No Cumple
B14: PARÁMETROS A CONSIDERAR
B17: ENTRADA DE MERCADERÍAS
B19: Transferencias Pendientes de Recepción | C19: Evaluar la antigüedad de la transferencia pendiente, en función de la distancia existente entre sucursales.
B20: SC | C20: Transferencias que no superen el plazo previsto de antigüedad, definido por distancia entre sucursales.
B21: PC | C21: Transferencias que superan el plazo previsto de antigüedad, autorizadas o con una gestíon especial.
B22: NC | C22: Transferencias que superan el plazo previsto de antigüedad.
B24: Distancias | C24: Plazo- Hasta:
B25: Entre sucursales de una misma locaclidad | C25: 2 días
B26: Entre sucursales de Salta - Jujuy | C26: 2 días
B27: Viajes al interior | C27: 3 días
B29: Pendientes de Crédito | C29: Analizar que los repuestos pendientes de crédito cuenten con sus reclamos respectivos.
B30: SC | C30: Todos los pendientes de crédito cuentan con sus respectivos reclamos
B31: PC
B32: NC | C32: Al menos un repuesto pendiente de crédito no cuenta con reclamo.
B34: Remitos de proveedores | C34: Verificar los remitos recepcionados no superen el plazo de 48 hs, de forma tal que la mercaderia recibida se convierta en inventario registrado.
B35: SC | C35: Remitos recepcionados e ingresados en sistema en un plazo de 48 horas.
B36: PC | C36: Remitos pendientes de recepción que superan el plazo previsto de 48 horas, autorizados.
B37: NC | C37: Remitos pendientes de recepción que superan el plazo previsto de 48 horas.
B40: STOCK DE MERCADERÍAS
B42: Rdo. Inv. Rotativo | C42: Calificar la diferencia absoluta del resultado final del inventario rotativo, que refleja la correcta gestión en el manejo del stock.
B43: SC | C43: Diferencia absoluta < 1%
B44: PC | C44: Diferencia absoluta > 1% y < 2%
B45: NC | C45: Diferencia absoluta > 2%
B47: Locación | C47: Verificar que la locación prevista en sistema coincida con la ubicación física de los artículos.
B48: SC | C48: Desvíos en la señalización y localización de los artículos de hasta el 1% del total de la muestra- Ejemplo: 2 artículos mal locados sobre un total de 200
B49: PC | C49: Desvíos en la señalización y localización de los artículos de hasta el 3% del total de la muestra- Ejemplo: 6 artículos mal locados sobre un total de 200
B50: NC | C50: Desvíos en la señalización y localización de los artículos mayor al 3% del total de la muestra
B52: Estado de Art. | C52: Verificar que los artículos no se encuentren en calidad defectuosa que le impidan su comercialización.
B53: SC | C53: Desvíos en la calidad de los artículos de hasta el 0% del total de la muestra- Ejemplo: 0 artículos defecuosos sobre un total de 200.
B54: PC | C54: Desvíos en la calidad de los artículos de hasta el 1% del total de la muestra- Ejemplo: 2 artículos defecuosos sobre un total de 200.
B55: NC | C55: Desvíos en la calidad de los artículos mayor al 1% del total de la muestra
B58: SALIDAS DE MERCADERÍAS
B60: Remitos Pend. De Facturación | C60: Verificar que las salidas de artículos estén autorizadas. (no más de 48hs,)
B61: SC | C61: Remito pendiente de facturación, autorizado.
B62: PC | C62: -
B63: NC | C63: Remito pendiente de facturación, sin autorización.
B65: Ventas Internas Directas | C65: Verificar el esquema de autorizaciones sobre cortesías y ventas de insumos a taller, tanto de quien los recibe los artículos y el jefe de Área que autoriza las salidas (puede ser por email).
B66: SC | C66: Vales firmados, autorizados.
B67: PC | C67: -
B68: NC | C68: Vales sin firma, no autorizados.
B70: Tipo de Ventas Internas Directas | C70: Analizar una muestra sobre las Ventas Internas Directas emitidas en la última semana
B71: Ventas por mostrador- Internas directas | C71: No se vincula con una ORA- Cargo interno- Imputado a cualquier sector- Cortesías por lo general- Contablemente se imputa : Resultado a Repuestos
B72: Vales a Taller | C72: Si se vincula a una ORA- Cargos: Interno- Garantía- Mixtos- Son de repuestos- Contablemente se imputa: Repuestos en proceso a Repuestos
B74: Transf. Pend. De Entrega | C74: Evaluar la antigüedad de la transferencia pendiente, en función de la distancia existente entre sucursales.
... B77: NC | C77: Transferencias realizadas en sistema y no enviadas físicamente, o viceversa.
B81: ARQUEO DE CAJA
B82: CATEGORIA | C82: CARACTERÍSTICAS
B83: Billeteo | C83: Condiciones: Planilla de billeteo coincida con el saldo según legajo de caja.
B84: SC | C84: Planilla de billeteo coincide con el saldo de caja o la diferencia es menor a $ 1.000
B85: PC
B86: NC | C86: Planilla de billeteo no coincide con el saldo de caja o la diferencia es mayor a $ 1.000
B88: Cheques | C88: Verificar la existencia de los cheques en cartera.
B89: SC | C89: Se observa la totalidad de cheques en cartera fisicos o los cheques electronicos por sistema.
B90: PC
B91: NC | C91: Falta algun cheque que figura en cartera.
B93: Vales a rendir | C93: Verificar la existencia de los comprobantes de vales firmados por los empleados y que los mismos respeten los plazos de acuerdo al procedimiento.
B94: SC | C94: Se visualiza la totalidad de los vales a rendir firmados y los mismos no se encuentran vencidos.
B95: PC | C95: Existe algun vale con plazo vencido autorizado por el jefe administrativo por alguna razon excepcional.
B96: NC | C96: No se encuentra la totalidad de vales a rendir, o los mismos no estan firmados, o se encuentran vencidos y sin el traslado a anticipos al personal.
B98: Cupones de trajetas. | C98: Verificar la existencia de los cupones en cartera.
B99: SC | C99: Se encuentran todos los cupones de tarjeta en caja.
B100: PC
B101: NC | C101: Falta algun cupón que figura en cartera.
B103: Transferencias pendientes de recepcion. | C103: Verificar que las transferencias entre cajas esten firmadas por quien emite y recibe la transferencia.
B104: SC | C104: No existen transferencias pendientes o de existir se encuentran firmadas o con mail de concentimiento por quien emitio y quien debe recibir la transferencia.
B105: PC
B106: NC | C106: Existen transferencias pendientes de recepcion sin el comprobante firmado por quien emite y debe recibir la transferencia.
B108: Contado Pendiente. | C108: Bonificaciones y descuentos con mail de autorizacion
B109: SC | C109: No existen facturas en contado pendiente, y de existir las mismas cuentan con un plazo de emision menor a 48 horas.
B110: PC
B111: NC | C111: Existen facturas en contado pendiente con un plazo de emision mayor a 48 horas.

Sheet Salta-Jujuy
B2: Control Integral de Depósito
B3: Tablero de Resultados
B23: Tablero de Resultados - Control Integral de Depósito
B24: Sucursal: | C24: Casa Central Jujuy | F24: Fecha de realización: | G24: 46056
B25: Auditor: | C25: Gustavo Zambrano | F25: Codigo Auditoria: | G25: PROG - 858
B26: Etapas | C26: Parámetros | E26: Ponderación | F26: % Cumplimiento | G26: Resultado final
B27: Entradas | C27: 1. Transf. Pend. de Recepción | E27: 0.1 | F27: =+F48 -> 1 | G27: =+E27*F27 -> 0.1
C28: 2. Pendientes de Crédito | E28: 0.075 | F28: =+F69 -> 1 | G28: =+E28*F28 -> 0.075
C29: 3. Remito de Compras | E29: 0.025 | F29: =+F81 -> 1 | G29: =+E29*F29 -> 0.025
B30: Stock | C30: 4. Rdo. Inv. Rotativo | E30: 0.5 | F30: =+F94 -> 1 | G30: =+E30*F30 -> 0.5
C31: 5. Locación | E31: 0.1 | F31: =+'4.Inv Rota'!L5 -> 0.94117647 | G31: =+E31*F31 -> 0.094117647
C32: 6. Estado de Art. | E32: 0.025 | F32: =+'4.Inv Rota'!K5 -> 1 | G32: =+E32*F32 -> 0.025
B33: Salidas | C33: 7. Remitos Pend. de Facturación | E33: 0.025 | F33: =+F135 -> 0.5 | G33: =+E33*F33 -> 0.0125
C34: 8. Ventas Internas Directas | E34: 0.05 | F34: =+F148 -> 1 | G34: =+E34*F34 -> 0.05
C35: 9. Transf. Pend. De Entrega | E35: 0.1 | F35: =+F154 -> 1 | G35: =+E35*F35 -> 0.1
E36: =SUM(E27:E35) -> 1 | G36: =SUM(G27:G35) -> 0.98161765
B38: Detalle de Desvíos:
A39: Entradas
A40: 1. Transf. Pend. de Recepción
B41: Cantidad total de transferencias, según SIAC: | E41: 3
B42: Transferencias con observaciones: | E42: 0
B44: Fecha | C44: Nro. Cpbte. | D44: Sucursal Origen | E44: Valoriz. Total | F44: Cant. días demora
B46: Plazo promedio en días de recepción de Transferencias con Desvío | F46: =AVERAGE(F45:F45) -> #DIV/0!
B47: (*) Se puede agregar más detalle con referencia a la fila. | I47: ← Se puede agregar más comentarios aquí
B48: Grado de cumplimiento para Transf. Pend. De Recepción: | F48: =+'1,Tranf.Pend. Recep'!K15 -> 1
A50: 2. Pendientes de Crédito
B51: Cantidad total de Artículos Pendientes de Crédito, según SIAC: | E51: 5
B52: Pendientes de Crédito con observaciones: | E52: 5
B54: Únicamente a modo informativo, y sin impacto en el resultado del control, se detalla a continuación el siguiente crédito pendiente:
B56: Artículo | C56: Fecha | D56: Comprobante | E56: Cantidad | F56: Observacion
B57: 08021LL02000 | C57: =+VLOOKUP(B57,'2.Pend.Creditoo'!A$17:N$35,6,0) -> 45688 | D57: =+VLOOKUP(B57,'2.Pend.Creditoo'!A$17:N$35,9,0) -> A-0300-00148818 | E57: =+VLOOKUP(B57,'2.Pend.Creditoo'!A$17:N$35,14,0) -> 12 | F57: Se detecto que el comprobante observado fue registrado contablemente en el ejercicio 2025, pese a haber sido emitida por el proveedor en febrero de 2024. Los remitos asociados a dicha operación fueron correctamente cargados en el sistema durante el ejercicio 2024, sin generar diferencias de stock, pero no fueron oportunamente vinculados a la factura correspondiente. Como consecuencia, la factura quedó registrada en un ejercicio posterior sin cancelación contra remitos, manteniéndose en estado pendiente de crédito para evitar impacto en inventarios.
B58: 088238014000 | C58: =+VLOOKUP(B58,'2.Pend.Creditoo'!A$17:N$35,6,0) -> 45688 | D58: =+VLOOKUP(B58,'2.Pend.Creditoo'!A$17:N$35,9,0) -> A-0300-00148818 | E58: =+VLOOKUP(B58,'2.Pend.Creditoo'!A$17:N$35,14,0) -> 10
B59: 178010L04000 | C59: =+VLOOKUP(B59,'2.Pend.Creditoo'!A$17:N$35,6,0) -> 45688 | D59: =+VLOOKUP(B59,'2.Pend.Creditoo'!A$17:N$35,9,0) -> A-0300-00148818 | E59: =+VLOOKUP(B59,'2.Pend.Creditoo'!A$17:N$35,14,0) -> 10
B60: PH3B00KA1000 | C60: =+VLOOKUP(B60,'2.Pend.Creditoo'!A$17:N$35,6,0) -> 45688 | D60: =+VLOOKUP(B60,'2.Pend.Creditoo'!A$17:N$35,9,0) -> A-0300-00148818 | E60: =+VLOOKUP(B60,'2.Pend.Creditoo'!A$17:N$35,14,0) -> 2
B61: PH3B10KA1100 | C61: =+VLOOKUP(B61,'2.Pend.Creditoo'!A$17:N$35,6,0) -> 45688 | D61: =+VLOOKUP(B61,'2.Pend.Creditoo'!A$17:N$35,9,0) -> A-0300-00148818 | E61: =+VLOOKUP(B61,'2.Pend.Creditoo'!A$17:N$35,14,0) -> 1
B62: PH7000KM10DO | C62: =+VLOOKUP(B62,'2.Pend.Creditoo'!A$17:N$35,6,0) -> 45688 | D62: =+VLOOKUP(B62,'2.Pend.Creditoo'!A$17:N$35,9,0) -> A-0300-00148818 | E62: =+VLOOKUP(B62,'2.Pend.Creditoo'!A$17:N$35,14,0) -> 1
B64: Fecha | C64: Artículo | D64: N° de Remito | E64: Total | F64: Observaciones
B65: 45469 | C65: 561010K41000 | D65: R-0033-00852594 | E65: 152617.67 | F65: Rechazado por envío erroneo de doc.
B66: 45469 | C66: 644610D07000 | D66: R-0033-00852594 | E66: 42796.48 | F66: Rechazado por envío erroneo de doc.
B67: Importe Total de Artículos con Desvío Pend. De Crédito | E67: =SUM(E65:E66) -> 195414.15
B68: (*) Se puede agregar más detalle con referencia a la fila. | I68: ← Se puede agregar más comentarios aquí
B69: Grado de cumplimiento para Artículos Pendiente de Crédito: | F69: =+E51/E52 -> 1
A71: 3. Remito de Compras
B72: Cantidad total de Remitos de Compras Pendientes: | E72: 2
B73: Remitos con Demoras: | E73: 0
B75: Fecha Rec. | C75: Nro. Remito | D75: Cant. días demora
D76: =NETWORKDAYS(B76,$G$24) -> 32897
D77: =NETWORKDAYS(B77,$G$24) -> 32897
D78: =NETWORKDAYS(B78,$G$24) -> 32897
B79: Plazo promedio de demora | D79: =AVERAGE(D76:D78) -> 32897
B80: (*) Se puede agregar más detalle con referencia a la fila. | I80: ← Se puede agregar más comentarios aquí
B81: Grado de cumplimiento para Remitos de Compras: | F81: =+'3.Remito Pend Carga'!G5 -> 1
A84: Stock
A85: 4. Resultado Inventario Rotativo
B86: El resultado del inventario rotativo es el siguiente:
B87: Detalle | D87: Cant. de Art. | E87: $ | F87: %
B88: Muestra | D88: =+'4.Inv Rota'!E62 -> 213 | E88: =+'4.Inv Rota'!F62 -> 24978980 | F88: =+'4.Inv Rota'!G62 -> 1
B89: Faltantes | D89: =+'4.Inv Rota'!E63 -> 0 | E89: =+'4.Inv Rota'!F63 -> 0 | F89: =+'4.Inv Rota'!G63 -> 0
B90: Sobrantes | D90: =+'4.Inv Rota'!E64 -> 0 | E90: =+'4.Inv Rota'!F64 -> 0 | F90: =+'4.Inv Rota'!G64 -> 0
B91: Diferencia Neta | D91: =+'4.Inv Rota'!E65 -> 0 | E91: =+'4.Inv Rota'!F65 -> 0 | F91: =+'4.Inv Rota'!G65 -> 0
B92: Diferencia Absoluta | D92: =+'4.Inv Rota'!E66 -> 0 | E92: =+'4.Inv Rota'!F66 -> 0 | F92: =+'4.Inv Rota'!G66 -> 0
B94: Del cual, según la siguiente escala, el grado de cumplimiento del billeteo es de: | F94: =VLOOKUP(ABS(F92),D97:E102,2,1) -> 1
D96: Dif. Abs. desde | E96: Grado de cumplim.
D97: 0 | E97: 1
D98: 0.001 | E98: 0.94
D99: 0.008 | E99: 0.82
D100: 0.016 | E100: 0.65
D101: 0.024 | E101: 0.35
D102: 0.033 | E102: 0
A104: 5. Locación
B105: Muestra: | E105: 51
B106: Artículos mal locados: | E106: 3
B108: Locación | C108: Artículo | D108: Descripción
B109: =+'4.Inv Rota'!A16 -> D-01-01-E01 | C109: =+'4.Inv Rota'!D16 -> 178013116000 | D109: =+'4.Inv Rota'!E16 -> ELEMENT SUB-ASSY, AIR CLEANER FILTER
B110: =+'4.Inv Rota'!A35 -> D-03-00-A01 | C110: =+'4.Inv Rota'!D35 -> 435120K32000 | D110: =+'4.Inv Rota'!E35 -> DISCO FRENO DEL.
B111: =+'4.Inv Rota'!A36 -> D-03-00-A02 | C111: =+'4.Inv Rota'!D36 -> 435120K08000 | D111: =+'4.Inv Rota'!E36 -> DISCO DE FRENO
B113: Grado de cumplimiento con respecto a la locación de los artículos: | F113: =+'4.Inv Rota'!L5 -> 0.94117647
A115: 6. Estado de Art.
B116: Muestra | E116: 51
B117: Artículos con Estado observado: | E117: 0
B119: Locación | C119: Artículo | D119: Observación | F119: Cantidad
B121: Grado de cumplimiento con respecto al Estado de los Artículos: | F121: =+'4.Inv Rota'!K5 -> 1
A123: Salidas
A124: 7. Remitos Pend. De Facturación
B125: Cantidad total de Remitos Pend. de Facturación, según SIAC: | E125: 4
B126: Remitos con observaciones: | E126: 2
B128: Cliente | C128: Fecha | D128: Nro. Cpbte. | E128: $ | F128: Observacion
B129: LEDESMA S.A.A.I. | C129: =+'7.Remito Pend de Fact'!A11 -> 45987 | D129: =+'7.Remito Pend de Fact'!C11 -> R-0005-00004364 | E129: =+'7.Remito Pend de Fact'!K11 -> 26908.78 | F129: Los mencionados remitos, al momento del control, se encontraban pendientes de facturación, sin que exista una justificación al respecto. Al dia de la fecha, la situacion fue subsanada.
B130: MINA PIRQUITAS S.A | C130: =+'7.Remito Pend de Fact'!A21 -> 46050 | D130: =+'7.Remito Pend de Fact'!C21 -> R-0005-00004421 | E130: =+SUM('7.Remito Pend de Fact'!K21:K31) -> 9855887.1
B132: Fecha | C132: Nro. de Cbte. | D132: Observación
F133: (*)
B134: (*) Se puede agregar más detalle con referencia a la fila. | I134: ← Se puede agregar más comentarios aquí
B135: Grado de cumplimiento para Remitos Pend. de Facturación: | F135: =+'7.Remito Pend de Fact'!M7 -> 0.5
A137: 8. Ventas Internas Directas
B138: Cantidad total de vales por internas directas: | E138: 17
B139: Vales con observaciones: | E139: 0
B141: Fecha | C141: Cpbte. | D141: Nro. Cpbte. | E141: Interna | F141: Observacion
B142: - | C142: - | D142: - | E142: - | F142: -
B144: Fecha | C144: Nro. Cpbte. | D144: Interna | E144: Importe
B145: 45484 | C145: 20552 | D145: Cortesía Ventas - Taller | E145: 4150783.2 | F145: (*)
...

Sheet Config S-J
A1: NO MODIFICAR, TIENE FORMULAS
A2: CONFIGURACIÓN PARA HOJA DE: "TESORERÍAS Y TARTAGAL"
A3: CONFIGURACIÓN DEL GRÁFICO:
A4: ** Calificación para los rangos del gráfico:
A5: 35 | B5: SAT | C5: Satisfactorio
A6: 30 | B6: ADE | C6: Adecuado
A7: 17 | B7: SUJ | C7: Sujeto a mejora
A8: 12 | B8: NAD | C8: No adecuado
A9: 6 | B9: INS | C9: Insatisfactorio
A10: =SUM(A5:A9) -> 100 | B10: TOTAL
A12: ** Valor para la aguja del velocimetro:
A13: Valor | C13: =+'Salta-Jujuy'!G36*100 -> 98.161765
A15: ** Parametros para el tamaño de la aguja:
A16: Antes | C16: =C13-C17/2 -> 97.161765
A17: Puntero | C17: 2
A18: Después | C18: =SUM(A5:A10)-C16-C17 -> 100.83824
A20: CONFIGURACIÓN DEL TEXTO DE LA CALIFICACIÓN:
A21: ** Parametros para la calificación textual:
A22: Min | B22: Abrev. | C22: Calificación | D22: Definición
A23: 0.94 | B23: SAT | C23: Satisfactorio | D23: No existen desvíos, o si existen estos son escasos y no significativos.
A24: 0.82 | B24: ADE | C24: Adecuado | D24: Los desvíos requieren de seguimiento por parte del sector para evitar su reincidencia.
A25: 0.65 | B25: SUJ | C25: Sujeto a mejora | D25: Suficiente cantidad de desvíos significativos que requieren de acciones correctivas.
A26: 0.35 | B26: NAD | C26: No adecuado | D26: Numerosos e importantes devíos que requieren de acción inmediata.
A27: 0 | B27: INS | C27: Insatisfactorio | D27: Numerosos e importantes devíos que requieren de medidas.
A29: Detalle de la calificación: | C29: =+C13/100 -> 0.98161765
A31: → | B31: =IF(C29<A26,C27,IF(C29<A25,C26,IF(C29<A24,C25,IF(C29<A23,C24,C23)))) -> Satisfactorio
A32: → | B32: =VLOOKUP(B31,C23:D27,2,FALSE) -> No existen desvíos, o si existen estos son escasos y no significativos.
A34: CONFIGURACIÓN PARA LAS TARJETAS QUE CONTIENEN TEXTO:
A35: ** Tarjeta 1: Lugar | D35: =+'Salta-Jujuy'!C24 -> Casa Central Jujuy
A36: → Lista desplegable para las sucursales: | D36: Casa Central Jujuy
D37: Sucursal Salta
A39: ** Tarjeta 2: Muestra de Art. | D39: =+'Salta-Jujuy'!D88 -> 213
A42: ** Tarjeta 3: Fecha de realización arqueo | D42: =+'Salta-Jujuy'!G24 -> 46056

Sheet Rotativo
A1: Autolux S.A. - Sucursal Salta
A2: Control Integral de Depósito | C2: 815610K31000 | D2: =+D59/D58 -> 1.0701884
A3: Fecha: | B3: 45604 | E3: Inventario Rotativo | I3: =1-(COUNTIFS($I$5:$I$90,"NC")/COUNTA($D$5:$D$90)) -> 0.98837209 | J3: =1-(COUNTIFS($J$5:$J$90,"NC")/COUNTA($D$5:$D$90)) -> 1 | L3: Pendientes | Q3: Recuento | V3: Ajuste | Y3: =SUM(Y5:Y90) -> -1240272.4 | Z3: =SUM(Z5:Z90) -> 1.8368988e+08
A4: Locación | B4: Artículo | C4: Descripción | D4: Cto.Rep. | E4: Stock | F4: Conteo | G4: Dif. | H4: x Dif.Final | I4: Locación | J4: Estado | K4: Justificaciones | L4: 7924 | M4: Dev. Transf. | N4: TOTAL remitos | O4: Dif. Parcial | P4: Acción | Q4: Stock | R4: Recuento | S4: Dif. | T4: Dif. Final | U4: Ajuste | V4: Faltante | W4: Sobrante | X4: Canje | Y4: Dif.Valorizada | Z4: Stock Valorizado | AA4: % | AB4: % Acumulado
A5: A-01-A01 | B5: 10594001 | C5: 205/55 R16 91V Turanza ER300 | D5: 138147.13 | E5: -3 | F5: 1 | G5: =+F5-E5 -> 4 | H5: =+D5*G5 -> 552588.51 | I5: SC | J5: SC | K5: INGRESO DE TRANSFERENCIA X4 n°7924 SE RECEPCIONA LA TRANSFERENCIA EL DIA DE LA FECHA. STOCK OK. | L5: 4 | N5: =+SUM(L5:M5) -> 4 | O5: =-E5-N5+F5 -> 0 | P5: Recontar | Q5: 21 | R5: 22 | S5: =+R5-Q5 -> 1 | T5: =IF(G5=0,0,IF(P5="Recontar",S5,IF(P5="Ajustar",O5,IF(P5="Canje",G5)))) -> 1 | U5: Sin Ajuste | V5: =IF(U5=$V$4,T5,"0") -> 0 | W5: =IF(U5=$W$4,T5,"0") -> 0 | X5: =IF(U5=$V$4,0,IF(U5=$W$4,0,IF(U5="-",0,IF(U5="Sin Ajuste",0,T5)))) -> 0 | Y5: =+V5*D5+W5*D5 -> 0 | Z5: =+E5*D5 -> -414441.38 | AA5: =+Z5/$Z$3 -> -0.0022562015 | AB5: =+AA5 -> -0.0022562015
A6: A-01-A03 | B6: 14199001 | C6: 265/60R18 110H - DUELER HT 684 II | D6: 217804.45 | E6: 15 | F6: 14 | G6: =+F6-E6 -> -1 | H6: =+D6*G6 -> -217804.45 | I6: SC | J6: SC | K6: ARTICULO CRUZADO CON 15175001 15175001 (FISICO 2//VIRTUAL 1) SOBRANTE X1 | L6: Una de las cubiertas no tiene el mismo cód es por ello que sólo se conto /14) | N6: =+SUM(L6:M6) -> 0 | O6: =-E6-N6+F6 -> -1 | P6: Recontar | Q6: 31 | R6: 30 | S6: =+R6-Q6 -> -1 | T6: =IF(G6=0,0,IF(P6="Recontar",S6,IF(P6="Ajustar",O6,IF(P6="Canje",G6)))) -> -1 | U6: Canje A | V6: =IF(U6=$V$4,T6,"0") -> 0 | W6: =IF(U6=$W$4,T6,"0") -> 0 | X6: =IF(U6=$V$4,0,IF(U6=$W$4,0,IF(U6="-",0,IF(U6="Sin Ajuste",0,T6)))) -> -1 | Y6: =+V6*D6+W6*D6 -> 0 | Z6: =+E6*D6 -> 3267066.7 | AA6: =+Z6/$Z$3 -> 0.017785774 | AB6: =+AB5+AA6 -> 0.015529573
A7: B-02-05-C01 | B7: 15175001 | C7: 265/60R18 110T DUELER HT 684 II | D7: 219662.03 | E7: 1 | F7: 2 | G7: =+F7-E7 -> 1 | H7: =+D7*G7 -> 219662.03 | I7: SC | J7: SC | K7: ARTICULO CRUZADO CON 15175001 15175001 (FISICO 2//VIRTUAL 1) SOBRANTE X1 | N7: =+SUM(L7:M7) -> 0 | O7: =-E7-N7+F7 -> 1 | P7: Recontar | Q7: 1 | R7: 2 | S7: =+R7-Q7 -> 1 | T7: =IF(G7=0,0,IF(P7="Recontar",S7,IF(P7="Ajustar",O7,IF(P7="Canje",G7)))) -> 1 | U7: Canje A | V7: =IF(U7=$V$4,T7,"0") -> 0 | W7: =IF(U7=$W$4,T7,"0") -> 0 | X7: =IF(U7=$V$4,0,IF(U7=$W$4,0,IF(U7="-",0,IF(U7="Sin Ajuste",0,T7)))) -> 1 | Y7: =+V7*D7+W7*D7 -> 0 | Z7: =+E7*D7 -> 219662.03 | AA7: =+Z7/$Z$3 -> 0.0011958309 | AB7: =+AB6+AA7 -> 0.016725404
A8: A-02-02-B02 | B8: PH4020KM1000 | C8: PROTECTOR PARAG.HILUX`19 - CAT 2 | D8: 94407.061 | E8: 4 | F8: 4 | G8: =+F8-E8 -> 0 | H8: =+D8*G8 -> 0 | I8: SC | J8: SC | K8: - | L8: - | N8: =+SUM(L8:M8) -> 0 | O8: =-E8-N8+F8 -> 0 | P8: - | S8: =+R8-Q8 -> 0 | T8: =IF(G8=0,0,IF(P8="Recontar",S8,IF(P8="Ajustar",O8,IF(P8="Canje",G8)))) -> 0 | U8: - | V8: =IF(U8=$V$4,T8,"0") -> 0 | W8: =IF(U8=$W$4,T8,"0") -> 0 | X8: =IF(U8=$V$4,0,IF(U8=$W$4,0,IF(U8="-",0,IF(U8="Sin Ajuste",0,T8)))) -> 0 | Y8: =+V8*D8+W8*D8 -> 0 | Z8: =+E8*D8 -> 377628.24 | AA8: =+Z8/$Z$3 -> 0.0020557923 | AB8: =+AB7+AA8 -> 0.018781196
A9: A-02-03-B02 | B9: PH4010KM1000 | C9: PROTECTOR FRONTAL HX 2016 | D9: 85459.983 | E9: 3 | F9: 3 | G9: =+F9-E9 -> 0 | H9: =+D9*G9 -> 0 | I9: SC | J9: SC | K9: - | L9: - | N9: =+SUM(L9:M9) -> 0 | O9: =-E9-N9+F9 -> 0 | P9: - | S9: =+R9-Q9 -> 0 | T9: =IF(G9=0,0,IF(P9="Recontar",S9,IF(P9="Ajustar",O9,IF(P9="Canje",G9)))) -> 0 | U9: - | V9: =IF(U9=$V$4,T9,"0") -> 0 | W9: =IF(U9=$W$4,T9,"0") -> 0 | X9: =IF(U9=$V$4,0,IF(U9=$W$4,0,IF(U9="-",0,IF(U9="Sin Ajuste",0,T9)))) -> 0 | Y9: =+V9*D9+W9*D9 -> 0 | Z9: =+E9*D9 -> 256379.95 | AA9: =+Z9/$Z$3 -> 0.0013957217 | AB9: =+AB8+AA9 -> 0.020176918
A10: ABI-02-A01 | B10: 0400720171C0 | C10: CENTRO VOLANTE (BLACK) | D10: 117012.5 | E10: 9 | F10: 14 | G10: =+F10-E10 -> 5 | H10: =+D10*G10 -> 585062.48 | I10: SC | J10: SC | K10: Variacion en la operativa de campañas STOCK OK | L10: - | N10: =+SUM(L10:M10) -> 0 | O10: =-E10-N10+F10 -> 5 | P10: Recontar | Q10: 19 | R10: 19 | S10: =+R10-Q10 -> 0 | T10: =IF(G10=0,0,IF(P10="Recontar",S10,IF(P10="Ajustar",O10,IF(P10="Canje",G10)))) -> 0 | U10: Sin Ajuste | V10: =IF(U10=$V$4,T10,"0") -> 0 | W10: =IF(U10=$W$4,T10,"0") -> 0 | X10: =IF(U10=$V$4,0,IF(U10=$W$4,0,IF(U10="-",0,IF(U10="Sin Ajuste",0,T10)))) -> 0 | Y10: =+V10*D10+W10*D10 -> 0 | Z10: =+E10*D10 -> 1053112.5 | AA10: =+Z10/$Z$3 -> 0.0057331001 | AB10: =+AB9+AA10 -> 0.025910018
A11: ABI-02-B01 | B11: 0400720171B0 | C11: CENTRO VOLANTE (DK.GRAY) | D11: 117012.5 | E11: 7 | F11: 18 | G11: =+F11-E11 -> 11 | H11: =+D11*G11 -> 1287137.5 | I11: SC | J11: SC | K11: Variacion en la operativa de campañas STOCK OK | L11: - | N11: =+SUM(L11:M11) -> 0 | O11: =-E11-N11+F11 -> 11 | P11: Recontar | Q11: 15 | R11: 15 | S11: =+R11-Q11 -> 0 | T11: =IF(G11=0,0,IF(P11="Recontar",S11,IF(P11="Ajustar",O11,IF(P11="Canje",G11)))) -> 0 | U11: Sin Ajuste | V11: =IF(U11=$V$4,T11,"0") -> 0 | W11: =IF(U11=$W$4,T11,"0") -> 0 | X11: =IF(U11=$V$4,0,IF(U11=$W$4,0,IF(U11="-",0,IF(U11="Sin Ajuste",0,T11)))) -> 0 | Y11: =+V11*D11+W11*D11 -> 0 | Z11: =+E11*D11 -> 819087.48 | AA11: =+Z11/$Z$3 -> 0.0044590779 | AB11: =+AB10+AA11 -> 0.030369096
A12: ABI-03-C01 | B12: 040040712200 | C12: KIT FFX CABLE ESPIRAL | D12: 148788.51 | E12: 4 | F12: 11 | G12: =+F12-E12 -> 7 | H12: =+D12*G12 -> 1041519.6 | I12: SC | J12: SC | K12: Variacion en la operativa de campañas STOCK OK | L12: - | N12: =+SUM(L12:M12) -> 0 | O12: =-E12-N12+F12 -> 7 | P12: Recontar | Q12: 18 | R12: 18 | S12: =+R12-Q12 -> 0 | T12: =IF(G12=0,0,IF(P12="Recontar",S12,IF(P12="Ajustar",O12,IF(P12="Canje",G12)))) -> 0 | U12: Sin Ajuste | V12: =IF(U12=$V$4,T12,"0") -> 0 | W12: =IF(U12=$W$4,T12,"0") -> 0 | X12: =IF(U12=$V$4,0,IF(U12=$W$4,0,IF(U12="-",0,IF(U12="Sin Ajuste",0,T12)))) -> 0 | Y12: =+V12*D12+W12*D12 -> 0 | Z12: =+E12*D12 -> 595154.06 | AA12: =+Z12/$Z$3 -> 0.0032399937 | AB12: =+AB11+AA12 -> 0.033609089
A13: ABI-03-D01 | B13: 040050591200 | C13: KIT PLACA SUCCION COMB. | D13: 59893.631 | E13: 11 | F13: 6 | G13: =+F13-E13 -> -5 | H13: =+D13*G13 -> -299468.15 | I13: SC | J13: SC | K13: Variacion en la operativa de campañas STOCK OK | L13: - | N13: =+SUM(L13:M13) -> 0 | O13: =-E13-N13+F13 -> -5 | P13: Recontar | Q13: 12 | R13: 12 | S13: =+R13-Q13 -> 0 | T13: =IF(G13=0,0,IF(P13="Recontar",S13,IF(P13="Ajustar",O13,IF(P13="Canje",G13)))) -> 0 | U13: Sin Ajuste | V13: =IF(U13=$V$4,T13,"0") -> 0 | W13: =IF(U13=$W$4,T13,"0") -> 0 | X13: =IF(U13=$V$4,0,IF(U13=$W$4,0,IF(U13="-",0,IF(U13="Sin Ajuste",0,T13)))) -> 0 | Y13: =+V13*D13+W13*D13 -> 0 | Z13: =+E13*D13 -> 658829.94 | AA13: =+Z13/$Z$3 -> 0.0035866426 | AB13: =+AB12+AA13 -> 0.037195732
A14: B-04-03-D06 | B14: PH9600KM10PT | C14: KIT PERNOS TH PU ARG HX 2016 - CAT 3 | D14: 51692.48 | E14: 7 | F14: 7 | G14: =+F14-E14 -> 0 | H14: =+D14*G14 -> 0 | I14: SC | J14: SC | K14: - | L14: - | N14: =+SUM(L14:M14) -> 0 | O14: =-E14-N14+F14 -> 0 | P14: - | S14: =+R14-Q14 -> 0 | T14: =IF(G14=0,0,IF(P14="Recontar",S14,IF(P14="Ajustar",O14,IF(P14="Canje",G14)))) -> 0 | U14: - | V14: =IF(U14=$V$4,T14,"0") -> 0 | W14: =IF(U14=$W$4,T14,"0") -> 0 | X14: =IF(U14=$V$4,0,IF(U14=$W$4,0,IF(U14="-",0,IF(U14="Sin Ajuste",0,T14)))) -> 0 | Y14: =+V14*D14+W14*D14 -> 0 | Z14: =+E14*D14 -> 361847.36 | AA14: =+Z14/$Z$3 -> 0.0019698819 | AB14: =+AB13+AA14 -> 0.039165614
A15: B-04-07-B07 | B15: 811500K73000 | C15: OPTICA IZQUIERDA | D15: 691006.13 | E15: 2 | F15: 2 | G15: =+F15-E15 -> 0 | H15: =+D15*G15 -> 0 | I15: SC | J15: SC | K15: - | L15: - | N15: =+SUM(L15:M15) -> 0 | O15: =-E15-N15+F15 -> 0 | P15: - | S15: =+R15-Q15 -> 0 | T15: 0 | U15: - | V15: =IF(U15=$V$4,T15,"0") -> 0 | W15: =IF(U15=$W$4,T15,"0") -> 0 | X15: =IF(U15=$V$4,0,IF(U15=$W$4,0,IF(U15="-",0,IF(U15="Sin Ajuste",0,T15)))) -> 0 | Y15: =+V15*D15+W15*D15 -> 0 | Z15: =+E15*D15 -> 1382012.3 | AA15: =+Z15/$Z$3 -> 0.0075236168 | AB15: =+AB14+AA15 -> 0.04668923
A16: B-06-03-A03 | B16: 426110K77100 | C16: LLANTA CHAPA 16" DX 2011-2015 | D16: 188580.68 | E16: 1 | F16: 1 | G16: =+F16-E16 -> 0 | H16: =+D16*G16 -> 0 | I16: SC | J16: SC | K16: - | L16: - | N16: =+SUM(L16:M16) -> 0 | O16: =-E16-N16+F16 -> 0 | P16: - | S16: =+R16-Q16 -> 0 | T16: =+O16 -> 0 | U16: - | V16: =IF(U16=$V$4,T16,"0") -> 0 | W16: =IF(U16=$W$4,T16,"0") -> 0 | X16: =IF(U16=$V$4,0,IF(U16=$W$4,0,IF(U16="-",0,IF(U16="Sin Ajuste",0,T16)))) -> 0 | Y16: =+V16*D16+W16*D16 -> 0 | Z16: =+E16*D16 -> 188580.68 | AA16: =+Z16/$Z$3 -> 0.0010266253 | AB16: =+AB15+AA16 -> 0.047715856
A17: B-06-11-A01 | B17: 426110KF7200 | C17: LLANTA 17 CHAPA 17X7.5 | D17: 151958.66 | E17: 18 | F17: 17 | G17: =+F17-E17 -> -1 | H17: =+D17*G17 -> -151958.66 | I17: SC | J17: SC | K17: CRUZADA CON 426110KR80 426110KR80 SE ENCUENTRA SOBRANTE X1 | L17: - | N17: =+SUM(L17:M17) -> 0 | O17: =-E17-N17+F17 -> -1 | P17: Recontar | Q17: 15 | R17: 14 | S17: =+R17-Q17 -> -1 | T17: =IF(G17=0,0,IF(P17="Recontar",S17,IF(P17="Ajustar",O17,IF(P17="Canje",G17)))) -> -1 | U17: Canje B | V17: =IF(U17=$V$4,T17,"0") -> 0 | W17: =IF(U17=$W$4,T17,"0") -> 0 | X17: =IF(U17=$V$4,0,IF(U17=$W$4,0,IF(U17="-",0,IF(U17="Sin Ajuste",0,T17)))) -> -1 | Y17: =+V17*D17+W17*D17 -> 0 | Z17: =+E17*D17 -> 2735255.9 | AA17: =+Z17/$Z$3 -> 0.014890618 | AB17: =+AB16+AA17 -> 0.062606474
A18: B-06-11-A02 | B18: 426110KR8000 | C18: LLANTA CHAPA 17X6 | D18: 142247.43 | E18: 0 | F18: 1 | G18: =+F18-E18 -> 1 | H18: =+D18*G18 -> 142247.43 | I18: SC | J18: SC | K18: CRUZADA CON 426110KR80 426110KR80 SE ENCUENTRA SOBRANTE X1 | L18: - | N18: =+SUM(L18:M18) -> 0 | O18: =-E18-N18+F18 -> 1 | P18: Recontar | Q18: 15 | R18: 16 | S18: =+R18-Q18 -> 1 | T18: =IF(G18=0,0,IF(P18="Recontar",S18,IF(P18="Ajustar",O18,IF(P18="Canje",G18)))) -> 1 | U18: Canje B | V18: =IF(U18=$V$4,T18,"0") -> 0 | W18: =IF(U18=$W$4,T18,"0") -> 0 | X18: =IF(U18=$V$4,0,IF(U18=$W$4,0,IF(U18="-",0,IF(U18="Sin Ajuste",0,T18)))) -> 1 | Y18: =+V18*D18+W18*D18 -> 0 | Z18: =+E18*D18 -> 0 | AA18: =+Z18/$Z$3 -> 0 | AB18: =+AB17+AA18 -> 0.062606474
A19: D-01-02-A01 | B19: 871390K08000 | C19: FILTRO A/A | D19: 14403.347 | E19: 302 | F19: 300 | G19: =+F19-E19 -> -2 | H19: =+D19*G19 -> -28806.694 | I19: SC | J19: SC | K19: Variacion en la operativa de taller de ese dia STOCK OK.(RECONTAR) | L19: - | N19: =+SUM(L19:M19) -> 0 | O19: =-E19-N19+F19 -> -2 | P19: Recontar | Q19: 336 | R19: 336 | S19: =+R19-Q19 -> 0 | T19: =IF(G19=0,0,IF(P19="Recontar",S19,IF(P19="Ajustar",O19,IF(P19="Canje",G19)))) -> 0 | U19: Sin Ajuste | V19: =IF(U19=$V$4,T19,"0") -> 0 | W19: =IF(U19=$W$4,T19,"0") -> 0 | X19: =IF(U19=$V$4,0,IF(U19=$W$4,0,IF(U19="-",0,IF(U19="Sin Ajuste",0,T19)))) -> 0 | Y19: =+V19*D19+W19*D19 -> 0 | Z19: =+E19*D19 -> 4349810.8 | AA19: =+Z19/$Z$3 -> 0.023680188 | AB19: =+AB18+AA19 -> 0.086286662
A20: D-01-02-B01 | B20: 871390K01000 | C20: FILTRO AIRE ACOND. | D20: 19677.231 | E20: 247 | F20: 246 | G20: =+F20-E20 -> -1 | H20: =+D20*G20 -> -19677.231 | I20: SC | J20: SC | K20: Variacion en la operativa de taller de ese dia STOCK OK.(RECONTAR) | L20: - | N20: =+SUM(L20:M20) -> 0 | O20: =-E20-N20+F20 -> -1 | P20: Recontar | Q20: 243 | R20: 243 | S20: =+R20-Q20 -> 0 | T20: =IF(G20=0,0,IF(P20="Recontar",S20,IF(P20="Ajustar",O20,IF(P20="Canje",G20)))) -> 0 | U20: Sin Ajuste | V20: =IF(U20=$V$4,T20,"0") -> 0 | W20: =IF(U20=$W$4,T20,"0") -> 0 | X20: =IF(U20=$V$4,0,IF(U20=$W$4,0,IF(U20="-",0,IF(U20="Sin Ajuste",0,T20)))) -> 0 | Y20: =+V20*D20+W20*D20 -> 0 | Z20: =+E20*D20 -> 4860276.1 | AA20: =+Z20/$Z$3 -> 0.026459139 | AB20: =+AB19+AA20 -> 0.1127458
A21: D-01-03-A01 | B21: 233900L07000 | C21: FILTRO COMBUSTIBLE | D21: 6541.969 | E21: -1 | F21: 0 | G21: =+F21-E21 -> 1 | H21: =+D21*G21 -> 6541.969 | I21: SC | J21: SC | K21: ARTICULO CRUZADO CON 233900L050 233900L050 SE ENCUENTRA FALTANTE X1 | L21: - | N21: =+SUM(L21:M21) -> 0 | O21: =-E21-N21+F21 -> 1 | P21: Recontar | Q21: -1 | R21: 0 | S21: =+R21-Q21 -> 1 | T21: =IF(G21=0,0,IF(P21="Recontar",S21,IF(P21="Ajustar",O21,IF(P21="Canje",G21)))) -> 1 | U21: Sobrante | V21: =IF(U21=$V$4,T21,"0") -> 0 | W21: =IF(U21=$W$4,T21,"0") -> 1 | X21: =IF(U21=$V$4,0,IF(U21=$W$4,0,IF(U21="-",0,IF(U21="Sin Ajuste",0,T21)))) -> 0 | Y21: =+V21*D21+W21*D21 -> 6541.969 | Z21: =+E21*D21 -> -6541.969 | AA21: =+Z21/$Z$3 -> -3.5614205e-05 | AB21: =+AB20+AA21 -> 0.11271019 | AC21: No se puede ajustar.Ajuste realizado el 28/11/2024 se encontraba inhabilitado.
A22: D-01-05-A01 | B22: 233900L05000 | C22: FILTRO DE COMBUSTIBLE | D22: 40100.144 | E22: 1 | F22: 0 | G22: =+F22-E22 -> -1 | H22: =+D22*G22 -> -40100.144 | I22: SC | J22: SC | K22: ARTICULO CRUZADO CON 233900L050 233900L050 SE ENCUENTRA FALTANTE X1 | L22: - | N22: =+SUM(L22:M22) -> 0 | O22: =-E22-N22+F22 -> -1 | P22: Recontar | Q22: 154 | R22: =152+1 -> 153 | S22: =+R22-Q22 -> -1 | T22: =IF(G22=0,0,IF(P22="Recontar",S22,IF(P22="Ajustar",O22,IF(P22="Canje",G22)))) -> -1 | U22: Faltante | V22: =IF(U22=$V$4,T22,"0") -> -1 | W22: =IF(U22=$W$4,T22,"0") -> 0 | X22: =IF(U22=$V$4,0,IF(U22=$W$4,0,IF(U22="-",0,IF(U22="Sin Ajuste",0,T22)))) -> 0 | Y22: =+V22*D22+W22*D22 -> -40100.144 | Z22: =+E22*D22 -> 40100.144 | AA22: =+Z22/$Z$3 -> 0.0002183035 | AB22: =+AB21+AA22 -> 0.11292849
A23: D-01-04-B01 | B23: 90915YZZD200 | C23: FILTRO ACEITE | D23: 8285.928 | E23: 424 | F23: =503-50-60 -> 393 | G23: =+F23-E23 -> -31 | H23: =+D23*G23 -> -256863.77 | I23: SC | J23: SC | K23: Variacion en la operativa de taller de ese dia (SE ENCUENTRA SOBRANTE X1) CRUZADO CON 0415237010 QUE SE ENCUENTRA FALTANTE X1 | L23: - | N23: =+SUM(L23:M23) -> 0 | O23: =-E23-N23+F23 -> -31 | P23: Recontar | Q23: 504 | R23: =176+39+260+29+1 -> 505 | S23: =+R23-Q23 -> 1 | T23: =IF(G23=0,0,IF(P23="Recontar",S23,IF(P23="Ajustar",O23,IF(P23="Canje",G23)))) -> 1 | U23: Sobrante | V23: =IF(U23=$V$4,T23,"0") -> 0 | W23: =IF(U23=$W$4,T23,"0") -> 1 | X23: =IF(U23=$V$4,0,IF(U23=$W$4,0,IF(U23="-",0,IF(U23="Sin Ajuste",0,T23)))) -> 0 | Y23: =+V23*D23+W23*D23 -> 8285.928 | Z23: =+E23*D23 -> 3513233.5 | AA23: =+Z23/$Z$3 -> 0.019125896 | AB23: =+AB22+AA23 -> 0.13205439
A24: D-01-04-C01 | B24: 178012105000 | C24: FILTRO DE AIRE | D24: 18412.912 | E24: 51 | F24: 51 | G24: =+F24-E24 -> 0 | H24: =+D24*G24 -> 0 | I24: SC | J24: SC | K24: - | L24: - | N24: =+SUM(L24:M24) -> 0 | O24: =-E24-N24+F24 -> 0 | P24: - | S24: =+R24-Q24 -> 0 | T24: =IF(G24=0,0,IF(P24="Recontar",S24,IF(P24="Ajustar",O24,IF(P24="Canje",G24)))) -> 0 | U24: - | V24: =IF(U24=$V$4,T24,"0") -> 0 | W24: =IF(U24=$W$4,T24,"0") -> 0 | X24: =IF(U24=$V$4,0,IF(U24=$W$4,0,IF(U24="-",0,IF(U24="Sin Ajuste",0,T24)))) -> 0 | Y24: =+V24*D24+W24*D24 -> 0 | Z24: =+E24*D24 -> 939058.51 | AA24: =+Z24/$Z$3 -> 0.0051121952 | AB24: =+AB23+AA24 -> 0.13716658
A25: D-01-05-C04 | B25: 041523701000 | C25: CONJ.FILTRO ACEITE | D25: 12765.606 | E25: 183 | F25: 178 | G25: =+F25-E25 -> -5 | H25: =+D25*G25 -> -63828.03 | I25: SC | J25: SC | K25: Variacion en la operativa de taller de ese dia (SE ENCUENTRA FALTANTE X1) CRUZADO CON 90915YZZD2 QUE SE ENCUENTRA SOBRANTE X1 | L25: - | N25: =+SUM(L25:M25) -> 0 | O25: =-E25-N25+F25 -> -5 | P25: Recontar | Q25: 208 | R25: =175+7+10+15 -> 207 | S25: =+R25-Q25 -> -1 | T25: =IF(G25=0,0,IF(P25="Recontar",S25,IF(P25="Ajustar",O25,IF(P25="Canje",G25)))) -> -1 | U25: Faltante | V25: =IF(U25=$V$4,T25,"0") -> -1 | W25: =IF(U25=$W$4,T25,"0") -> 0 | X25: =IF(U25=$V$4,0,IF(U25=$W$4,0,IF(U25="-",0,IF(U25="Sin Ajuste",0,T25)))) -> 0 | Y25: =+V25*D25+W25*D25 -> -12765.606 | Z25: =+E25*D25 -> 2336105.9 | AA25: =+Z25/$Z$3 -> 0.012717663 | AB25: =+AB24+AA25 -> 0.14988424
A26: D-01-06-C03 | B26: 233905107000 | C26: FILTRO COMBUSTIBLE | D26: 39055.632 | E26: 4 | F26: 4 | G26: =+F26-E26 -> 0 | H26: =+D26*G26 -> 0 | I26: SC | J26: SC | K26: - | L26: - | N26: =+SUM(L26:M26) -> 0 | O26: =-E26-N26+F26 -> 0 | P26: - | S26: =+R26-Q26 -> 0 | T26: =IF(G26=0,0,IF(P26="Recontar",S26,IF(P26="Ajustar",O26,IF(P26="Canje",G26)))) -> 0 | U26: - | V26: =IF(U26=$V$4,T26,"0") -> 0 | W26: =IF(U26=$W$4,T26,"0") -> 0 | X26: =IF(U26=$V$4,0,IF(U26=$W$4,0,IF(U26="-",0,IF(U26="Sin Ajuste",0,T26)))) -> 0 | Y26: =+V26*D26+W26*D26 -> 0 | Z26: =+E26*D26 -> 156222.53 | AA26: =+Z26/$Z$3 -> 0.00085046889 | AB26: =+AB25+AA26 -> 0.15073471
A27: D-01-07-C03 | B27: 178013112000 | C27: FILTRO DE AIRE RAV4 | D27: 36648.717 | E27: 11 | F27: 11 | G27: =+F27-E27 -> 0 | H27: =+D27*G27 -> 0 | I27: SC | J27: SC | K27: - | L27: - | N27: =+SUM(L27:M27) -> 0 | O27: =-E27-N27+F27 -> 0 | P27: - | S27: =+R27-Q27 -> 0 | T27: =IF(G27=0,0,IF(P27="Recontar",S27,IF(P27="Ajustar",O27,IF(P27="Canje",G27)))) -> 0 | U27: - | V27: =IF(U27=$V$4,T27,"0") -> 0 | W27: =IF(U27=$W$4,T27,"0") -> 0 | X27: =IF(U27=$V$4,0,IF(U27=$W$4,0,IF(U27="-",0,IF(U27="Sin Ajuste",0,T27)))) -> 0 | Y27: =+V27*D27+W27*D27 -> 0 | Z27: =+E27*D27 -> 403135.89 | AA27: =+Z27/$Z$3 -> 0.0021946549 | AB27: =+AB26+AA27 -> 0.15292937
A28: D-01-10-A01 | B28: 815610K27100 | C28: ACRILICO.FARO.KOITO | D28: 120562.7 | E28: 10 | F28: 11 | G28: =+F28-E28 -> 1 | H28: =+D28*G28 -> 120562.7 | I28: SC | J28: SC | K28: CRUZADO CON 815610K31000 - | L28: - | N28: =+SUM(L28:M28) -> 0 | O28: =-E28-N28+F28 -> 1 | P28: Recontar | Q28: 13 | R28: =5+9 -> 14 | S28: =+R28-Q28 -> 1 | T28: =IF(G28=0,0,IF(P28="Recontar",S28,IF(P28="Ajustar",O28,IF(P28="Canje",G28)))) -> 1 | U28: Sobrante | V28: =IF(U28=$V$4,T28,"0") -> 0 | W28: =IF(U28=$W$4,T28,"0") -> 1 | X28: =IF(U28=$V$4,0,IF(U28=$W$4,0,IF(U28="-",0,IF(U28="Sin Ajuste",0,T28)))) -> 0 | Y28: =+V28*D28+W28*D28 -> 120562.7 | Z28: =+E28*D28 -> 1205627 | AA28: =+Z28/$Z$3 -> 0.0065633829 | AB28: =+AB27+AA28 -> 0.15949275
A29: D-02-03-C02 | B29: 043710K13000 | C29: CRUCETA CARDAN | D29: 95837.308 | E29: 31 | F29: =35-3 -> 32 | G29: =+F29-E29 -> 1 | H29: =+D29*G29 -> 95837.308 | I29: SC | J29: SC | K29: CRUZADA CON 043710K170 043710K170 SE ENCUENTRA FALTANTE X1 | L29: - | N29: =+SUM(L29:M29) -> 0 | O29: =-E29-N29+F29 -> 1 | P29: Recontar | Q29: 37 | R29: 38 | S29: =+R29-Q29 -> 1 | T29: =IF(G29=0,0,IF(P29="Recontar",S29,IF(P29="Ajustar",O29,IF(P29="Canje",G29)))) -> 1 | U29: Sobrante | V29: =IF(U29=$V$4,T29,"0") -> 0 | W29: =IF(U29=$W$4,T29,"0") -> 1 | X29: =IF(U29=$V$4,0,IF(U29=$W$4,0,IF(U29="-",0,IF(U29="Sin Ajuste",0,T29)))) -> 0 | Y29: =+V29*D29+W29*D29 -> 95837.308 | Z29: =+E29*D29 -> 2970956.5 | AA29: =+Z29/$Z$3 -> 0.016173763 | AB29: =+AB28+AA29 -> 0.17566651
A30: D-04-08-C02 | B30: 043710K17000 | C30: CRUCETA CARDAN | D30: 107733.38 | E30: 1 | F30: 0 | G30: =+F30-E30 -> -1 | H30: =+D30*G30 -> -107733.38 | I30: SC | J30: SC | K30: CRUZADA CON 043710K170 043710K170 SE ENCUENTRA FALTANTE X1 | L30: - | N30: =+SUM(L30:M30) -> 0 | O30: =-E30-N30+F30 -> -1 | P30: Recontar | Q30: 8 | R30: 7 | S30: =+R30-Q30 -> -1 | T30: =IF(G30=0,0,IF(P30="Recontar",S30,IF(P30="Ajustar",O30,IF(P30="Canje",G30)))) -> -1 | U30: Faltante | V30: =IF(U30=$V$4,T30,"0") -> -1 | W30: =IF(U30=$W$4,T30,"0") -> 0 | X30: =IF(U30=$V$4,0,IF(U30=$W$4,0,IF(U30="-",0,IF(U30="Sin Ajuste",0,T30)))) -> 0 | Y30: =+V30*D30+W30*D30 -> -107733.38 | Z30: =+E30*D30 -> 107733.38 | AA30: =+Z30/$Z$3 -> 0.00058649601 | AB30: =+AB29+AA30 -> 0.17625301
A31: D-02-04-D02 | B31: PZV831121000 | C31: TUERCAS SEG LLANT. ALEAC COROLLA -CAT 3 | D31: 59066.896 | E31: 44 | F31: 43 | G31: =+F31-E31 -> -1 | H31: =+D31*G31 -> -59066.896 | I31: SC | J31: SC | K31: MAL CONTADO (X1 MAL UBICADO) STOCK OK (RECONTAR) | L31: - | N31: =+SUM(L31:M31) -> 0 | O31: =-E31-N31+F31 -> -1 | P31: Recontar | Q31: 42 | R31: 42 | S31: =+R31-Q31 -> 0 | T31: =IF(G31=0,0,IF(P31="Recontar",S31,IF(P31="Ajustar",O31,IF(P31="Canje",G31)))) -> 0 | U31: Sin Ajuste | V31: =IF(U31=$V$4,T31,"0") -> 0 | W31: =IF(U31=$W$4,T31,"0") -> 0 | X31: =IF(U31=$V$4,0,IF(U31=$W$4,0,IF(U31="-",0,IF(U31="Sin Ajuste",0,T31)))) -> 0 | Y31: =+V31*D31+W31*D31 -> 0 | Z31: =+E31*D31 -> 2598943.4 | AA31: =+Z31/$Z$3 -> 0.014148539 | AB31: =+AB30+AA31 -> 0.19040155
A32: D-02-05-B02 | B32: PC4580K00200 | C32: CANDADO SEGURIDAD AUX. HX 2016 - CAT 3 | D32: 97355.979 | E32: 37 | F32: 37 | G32: =+F32-E32 -> 0 | H32: =+D32*G32 -> 0 | I32: SC | J32: SC | K32: - | L32: - | N32: =+SUM(L32:M32) -> 0 | O32: =-E32-N32+F32 -> 0 | P32: - | S32: =+R32-Q32 -> 0 | T32: =IF(G32=0,0,IF(P32="Recontar",S32,IF(P32="Ajustar",O32,IF(P32="Canje",G32)))) -> 0 | U32: - | V32: =IF(U32=$V$4,T32,"0") -> 0 | W32: =IF(U32=$W$4,T32,"0") -> 0 | X32: =IF(U32=$V$4,0,IF(U32=$W$4,0,IF(U32="-",0,IF(U32="Sin Ajuste",0,T32)))) -> 0 | Y32: =+V32*D32+W32*D32 -> 0 | Z32: =+E32*D32 -> 3602171.2 | AA32: =+Z32/$Z$3 -> 0.019610069 | AB32: =+AB31+AA32 -> 0.21001162
A33: D-03-01-E01 | B33: 815510K30000 | C33: ACRILICO FARO DER. VALEO | D33: 94946.488 | E33: 9 | F33: 8 | G33: =+F33-E33 -> -1 | H33: =+D33*G33 -> -94946.488 | I33: SC | J33: SC | K33: CRUZADO CON 815510K261 - | L33: - | N33: =+SUM(L33:M33) -> 0 | O33: =-E33-N33+F33 -> -1 | P33: Recontar | Q33: 11 | R33: =5+3+2 -> 10 | S33: =+R33-Q33 -> -1 | T33: =IF(G33=0,0,IF(P33="Recontar",S33,IF(P33="Ajustar",O33,IF(P33="Canje",G33)))) -> -1 | U33: Faltante | V33: =IF(U33=$V$4,T33,"0") -> -1 | W33: =IF(U33=$W$4,T33,"0") -> 0 | X33: =IF(U33=$V$4,0,IF(U33=$W$4,0,IF(U33="-",0,IF(U33="Sin Ajuste",0,T33)))) -> 0 | Y33: =+V33*D33+W33*D33 -> -94946.488 | Z33: =+E33*D33 -> 854518.39 | AA33: =+Z33/$Z$3 -> 0.0046519623 | AB33: =+AB32+AA33 -> 0.21466358
A34: D-03-02-B01 | B34: 435120229000 | C34: DISCO DE FRENO | D34: 112959.8 | E34: 4 | F34: 4 | G34: =+F34-E34 -> 0 | H34: =+D34*G34 -> 0 | I34: SC | J34: SC | K34: - | L34: - | N34: =+SUM(L34:M34) -> 0 | O34: =-E34-N34+F34 -> 0 | P34: - | S34: =+R34-Q34 -> 0 | T34: =IF(G34=0,0,IF(P34="Recontar",S34,IF(P34="Ajustar",O34,IF(P34="Canje",G34)))) -> 0 | U34: - | V34: =IF(U34=$V$4,T34,"0") -> 0 | W34: =IF(U34=$W$4,T34,"0") -> 0 | X34: =IF(U34=$V$4,0,IF(U34=$W$4,0,IF(U34="-",0,IF(U34="Sin Ajuste",0,T34)))) -> 0 | Y34: =+V34*D34+W34*D34 -> 0 | Z34: =+E34*D34 -> 451839.19 | AA34: =+Z34/$Z$3 -> 0.0024597936 | AB34: =+AB33+AA34 -> 0.21712337
A35: D-03-03-A01 | B35: 424310227000 | C35: DISCOS TRASEROS COROLLA | D35: 107041.5 | E35: 9 | F35: 8 | G35: =+F35-E35 -> -1 | H35: =+D35*G35 -> -107041.5 | I35: SC | J35: SC | K35: VALE TALLER N°59142890 VALE CARGADO CANTIDAD X1 Y EL VEHICULO SE LLEVO X2 | L35: - | N35: =+SUM(L35:M35) -> 0 | O35: =-E35-N35+F35 -> -1 | P35: Recontar | Q35: 11 | R35: 10 | S35: =+R35-Q35 -> -1 | T35: =IF(G35=0,0,IF(P35="Recontar",S35,IF(P35="Ajustar",O35,IF(P35="Canje",G35)))) -> -1 | U35: Faltante | V35: =IF(U35=$V$4,T35,"0") -> -1 | W35: =IF(U35=$W$4,T35,"0") -> 0 | X35: =IF(U35=$V$4,0,IF(U35=$W$4,0,IF(U35="-",0,IF(U35="Sin Ajuste",0,T35)))) -> 0 | Y35: =+V35*D35+W35*D35 -> -107041.5 | Z35: =+E35*D35 -> 963373.51 | AA35: =+Z35/$Z$3 -> 0.005244565 | AB35: =+AB34+AA35 -> 0.22236794
A36: D-03-03-D01 | B36: 843060K05100 | C36: CABLE ESPIRAL C/CONTROL VOLANTE | D36: 155295.16 | E36: 9 | F36: =10-1 -> 9 | G36: =+F36-E36 -> 0 | H36: =+D36*G36 -> 0 | I36: SC | J36: SC | K36: - | L36: - | N36: =+SUM(L36:M36) -> 0 | O36: =-E36-N36+F36 -> 0 | P36: - | S36: =+R36-Q36 -> 0 | T36: =IF(G36=0,0,IF(P36="Recontar",S36,IF(P36="Ajustar",O36,IF(P36="Canje",G36)))) -> 0 | U36: - | V36: =IF(U36=$V$4,T36,"0") -> 0 | W36: =IF(U36=$W$4,T36,"0") -> 0 | X36: =IF(U36=$V$4,0,IF(U36=$W$4,0,IF(U36="-",0,IF(U36="Sin Ajuste",0,T36)))) -> 0 | Y36: =+V36*D36+W36*D36 -> 0 | Z36: =+E36*D36 -> 1397656.4 | AA36: =+Z36/$Z$3 -> 0.0076087831 | AB36: =+AB35+AA36 -> 0.22997672
A37: D-03-03-E02 | B37: 843060K02100 | C37: CABLE ESPIRAL | D37: 161658.02 | E37: 4 | F37: 4 | G37: =+F37-E37 -> 0 | H37: =+D37*G37 -> 0 | I37: SC | J37: SC | K37: - | L37: - | N37: =+SUM(L37:M37) -> 0 | O37: =-E37-N37+F37 -> 0 | P37: - | S37: =+R37-Q37 -> 0 | T37: =IF(G37=0,0,IF(P37="Recontar",S37,IF(P37="Ajustar",O37,IF(P37="Canje",G37)))) -> 0 | U37: - | V37: =IF(U37=$V$4,T37,"0") -> 0 | W37: =IF(U37=$W$4,T37,"0") -> 0 | X37: =IF(U37=$V$4,0,IF(U37=$W$4,0,IF(U37="-",0,IF(U37="Sin Ajuste",0,T37)))) -> 0 | Y37: =+V37*D37+W37*D37 -> 0 | Z37: =+E37*D37 -> 646632.08 | AA37: =+Z37/$Z$3 -> 0.003520238 | AB37: =+AB36+AA37 -> 0.23349696
A38: D-03-04-A01 | B38: 312100K28100 | C38: PLACA EMBRAGUE | D38: 426421.68 | E38: 23 | F38: 22 | G38: =+F38-E38 -> -1 | H38: =+D38*G38 -> -426421.68 | I38: SC | J38: SC | K38: CRUZADA CON 312100K090 312100K090 SE ENCUENTRA SOBRANTE X1 | L38: - | N38: =+SUM(L38:M38) -> 0 | O38: =-E38-N38+F38 -> -1 | P38: Recontar | Q38: 21 | R38: =11+9 -> 20 | S38: =+R38-Q38 -> -1 | T38: =IF(G38=0,0,IF(P38="Recontar",S38,IF(P38="Ajustar",O38,IF(P38="Canje",G38)))) -> -1 | U38: Canje C | V38: =IF(U38=$V$4,T38,"0") -> 0 | W38: =IF(U38=$W$4,T38,"0") -> 0 | X38: =IF(U38=$V$4,0,IF(U38=$W$4,0,IF(U38="-",0,IF(U38="Sin Ajuste",0,T38)))) -> -1 | Y38: =+V38*D38+W38*D38 -> 0 | Z38: =+E38*D38 -> 9807698.7 | AA38: =+Z38/$Z$3 -> 0.0533927 | AB38: =+AB37+AA38 -> 0.28688966
A39: D-02-02-A01 | B39: 312100K09000 | C39: PLACA EMBRAGUE | D39: 402642.53 | E39: 0 | F39: 1 | G39: =+F39-E39 -> 1 | H39: =+D39*G39 -> 402642.53 | I39: SC | J39: SC | K39: CRUZADA CON 312100K090 312100K090 SE ENCUENTRA SOBRANTE X1 | L39: - | N39: =+SUM(L39:M39) -> 0 | O39: =-E39-N39+F39 -> 1 | P39: Recontar | Q39: 10 | R39: =7+4 -> 11 | S39: =+R39-Q39 -> 1 | T39: =IF(G39=0,0,IF(P39="Recontar",S39,IF(P39="Ajustar",O39,IF(P39="Canje",G39)))) -> 1 | U39: Canje C | V39: =IF(U39=$V$4,T39,"0") -> 0 | W39: =IF(U39=$W$4,T39,"0") -> 0 | X39: =IF(U39=$V$4,0,IF(U39=$W$4,0,IF(U39="-",0,IF(U39="Sin Ajuste",0,T39)))) -> 1 | Y39: =+V39*D39+W39*D39 -> 0 | Z39: =+E39*D39 -> 0 | AA39: =+Z39/$Z$3 -> 0 | AB39: =+AB38+AA39 -> 0.28688966
A40: D-03-05-C03 | B40: 455030934000 | C40: PRECAP DE DIRECC. | D40: 189483.41 | E40: 13 | F40: 13 | G40: =+F40-E40 -> 0 | H40: =+D40*G40 -> 0 | I40: SC | J40: SC | K40: - | L40: - | N40: =+SUM(L40:M40) -> 0 | O40: =-E40-N40+F40 -> 0 | P40: - | S40: =+R40-Q40 -> 0 | T40: =IF(G40=0,0,IF(P40="Recontar",S40,IF(P40="Ajustar",O40,IF(P40="Canje",G40)))) -> 0 | U40: - | V40: =IF(U40=$V$4,T40,"0") -> 0 | W40: =IF(U40=$W$4,T40,"0") -> 0 | X40: =IF(U40=$V$4,0,IF(U40=$W$4,0,IF(U40="-",0,IF(U40="Sin Ajuste",0,T40)))) -> 0 | Y40: =+V40*D40+W40*D40 -> 0 | Z40: =+E40*D40 -> 2463284.3 | AA40: =+Z40/$Z$3 -> 0.013410016 | AB40: =+AB39+AA40 -> 0.30029968
A41: D-03-06-D02 | B41: 043750K01200 | C41: CRUCETA CARDAN | D41: 106043.99 | E41: 8 | F41: =9-1 -> 8 | G41: =+F41-E41 -> 0 | H41: =+D41*G41 -> 0 | I41: SC | J41: SC | K41: - | L41: - | N41: =+SUM(L41:M41) -> 0 | O41: =-E41-N41+F41 -> 0 | P41: - | S41: =+R41-Q41 -> 0 | T41: =IF(G41=0,0,IF(P41="Recontar",S41,IF(P41="Ajustar",O41,IF(P41="Canje",G41)))) -> 0 | U41: - | V41: =IF(U41=$V$4,T41,"0") -> 0 | W41: =IF(U41=$W$4,T41,"0") -> 0 | X41: =IF(U41=$V$4,0,IF(U41=$W$4,0,IF(U41="-",0,IF(U41="Sin Ajuste",0,T41)))) -> 0 | Y41: =+V41*D41+W41*D41 -> 0 | Z41: =+E41*D41 -> 848351.95 | AA41: =+Z41/$Z$3 -> 0.0046183925 | AB41: =+AB40+AA41 -> 0.30491807
A42: D-03-06-E01 | B42: 135056704200 | C42: TENSOR | D42: 131526.66 | E42: 36 | F42: =38-3 -> 35 | G42: =+F42-E42 -> -1 | H42: =+D42*G42 -> -131526.66 | I42: SC | J42: SC | K42: NO SE ENCUENTRA EL DESVIO AJUSTAR | L42: - | N42: =+SUM(L42:M42) -> 0 | O42: =-E42-N42+F42 -> -1 | P42: Ajustar | S42: =+R42-Q42 -> 0 | T42: =IF(G42=0,0,IF(P42="Recontar",S42,IF(P42="Ajustar",O42,IF(P42="Canje",G42)))) -> -1 | U42: Faltante | V42: =IF(U42=$V$4,T42,"0") -> -1 | W42: =IF(U42=$W$4,T42,"0") -> 0 | X42: =IF(U42=$V$4,0,IF(U42=$W$4,0,IF(U42="-",0,IF(U42="Sin Ajuste",0,T42)))) -> 0 | Y42: =+V42*D42+W42*D42 -> -131526.66 | Z42: =+E42*D42 -> 4734959.8 | AA42: =+Z42/$Z$3 -> 0.025776923 | AB42: =+AB41+AA42 -> 0.33069499
A43: D-04-02-E05 | B43: 904671018300 | C43: CLIP PLASTICO | D43: 1181.698 | E43: 118 | F43: 118 | G43: =+F43-E43 -> 0 | H43: =+D43*G43 -> 0 | I43: SC | J43: SC | K43: - | L43: - | N43: =+SUM(L43:M43) -> 0 | O43: =-E43-N43+F43 -> 0 | P43: - | S43: =+R43-Q43 -> 0 | T43: =IF(G43=0,0,IF(P43="Recontar",S43,IF(P43="Ajustar",O43,IF(P43="Canje",G43)))) -> 0 | U43: - | V43: =IF(U43=$V$4,T43,"0") -> 0 | W43: =IF(U43=$W$4,T43,"0") -> 0 | X43: =IF(U43=$V$4,0,IF(U43=$W$4,0,IF(U43="-",0,IF(U43="Sin Ajuste",0,T43)))) -> 0 | Y43: =+V43*D43+W43*D43 -> 0 | Z43: =+E43*D43 -> 139440.36 | AA43: =+Z43/$Z$3 -> 0.00075910749 | AB43: =+AB42+AA43 -> 0.3314541
A44: D-04-03-F03 | B44: 455030K14000 | C44: PRECAP DIRECCION HX 16> | D44: 256186.8 | E44: 45 | F44: =49-4 -> 45 | G44: =+F44-E44 -> 0 | H44: =+D44*G44 -> 0 | I44: SC | J44: SC | K44: - | L44: - | N44: =+SUM(L44:M44) -> 0 | O44: =-E44-N44+F44 -> 0 | P44: - | S44: =+R44-Q44 -> 0 | T44: =IF(G44=0,0,IF(P44="Recontar",S44,IF(P44="Ajustar",O44,IF(P44="Canje",G44)))) -> 0 | U44: - | V44: =IF(U44=$V$4,T44,"0") -> 0 | W44: =IF(U44=$W$4,T44,"0") -> 0 | X44: =IF(U44=$V$4,0,IF(U44=$W$4,0,IF(U44="-",0,IF(U44="Sin Ajuste",0,T44)))) -> 0 | Y44: =+V44*D44+W44*D44 -> 0 | Z44: =+E44*D44 -> 11528406 | AA44: =+Z44/$Z$3 -> 0.062760158 | AB44: =+AB43+AA44 -> 0.39421426
A45: D-04-05-F02 | B45: 521611601000 | C45: CLIP PLASTICO | D45: 2229.983 | E45: 123 | F45: 115 | G45: =+F45-E45 -> -8 | H45: =+D45*G45 -> -17839.864 | I45: SC | J45: SC | K45: NO SE ENCUENTRA EL DESVIO AJUSTAR | L45: - | N45: =+SUM(L45:M45) -> 0 | O45: =-E45-N45+F45 -> -8 | P45: Ajustar | S45: =+R45-Q45 -> 0 | T45: =IF(G45=0,0,IF(P45="Recontar",S45,IF(P45="Ajustar",O45,IF(P45="Canje",G45)))) -> -8 | U45: Faltante | V45: =IF(U45=$V$4,T45,"0") -> -8 | W45: =IF(U45=$W$4,T45,"0") -> 0 | X45: =IF(U45=$V$4,0,IF(U45=$W$4,0,IF(U45="-",0,IF(U45="Sin Ajuste",0,T45)))) -> 0 | Y45: =+V45*D45+W45*D45 -> -17839.864 | Z45: =+E45*D45 -> 274287.91 | AA45: =+Z45/$Z$3 -> 0.0014932119 | AB45: =+AB44+AA45 -> 0.39570747
A46: D-04-05-F06 | B46: 450460931000 | C46: EXTREMO DIRECCION | D46: 94520.013 | E46: 2 | F46: =5-3 -> 2 | G46: =+F46-E46 -> 0 | H46: =+D46*G46 -> 0 | I46: SC | J46: SC | K46: - | L46: - | N46: =+SUM(L46:M46) -> 0 | O46: =-E46-N46+F46 -> 0 | P46: - | S46: =+R46-Q46 -> 0 | T46: =IF(G46=0,0,IF(P46="Recontar",S46,IF(P46="Ajustar",O46,IF(P46="Canje",G46)))) -> 0 | U46: - | V46: =IF(U46=$V$4,T46,"0") -> 0 | W46: =IF(U46=$W$4,T46,"0") -> 0 | X46: =IF(U46=$V$4,0,IF(U46=$W$4,0,IF(U46="-",0,IF(U46="Sin Ajuste",0,T46)))) -> 0 | Y46: =+V46*D46+W46*D46 -> 0 | Z46: =+E46*D46 -> 189040.03 | AA46: =+Z46/$Z$3 -> 0.001029126 | AB46: =+AB45+AA46 -> 0.39673659
A47: D-04-06-A03 | B47: 90366T006100 | C47: RODAMIENTO | D47: 111974.99 | E47: 31 | F47: 30 | G47: =+F47-E47 -> -1 | H47: =+D47*G47 -> -111974.99 | I47: SC | J47: SC | K47: NO SE ENCUENTRA EL DESVIO AJUSTAR | L47: - | N47: =+SUM(L47:M47) -> 0 | O47: =-E47-N47+F47 -> -1 | P47: Ajustar | S47: =+R47-Q47 -> 0 | T47: =IF(G47=0,0,IF(P47="Recontar",S47,IF(P47="Ajustar",O47,IF(P47="Canje",G47)))) -> -1 | U47: Faltante | V47: =IF(U47=$V$4,T47,"0") -> -1 | W47: =IF(U47=$W$4,T47,"0") -> 0 | X47: =IF(U47=$V$4,0,IF(U47=$W$4,0,IF(U47="-",0,IF(U47="Sin Ajuste",0,T47)))) -> 0 | Y47: =+V47*D47+W47*D47 -> -111974.99 | Z47: =+E47*D47 -> 3471224.7 | AA47: =+Z47/$Z$3 -> 0.018897201 | AB47: =+AB46+AA47 -> 0.4156338
A48: D-04-06-B02 | B48: 909420205200 | C48: BULON | D48: 4300.926 | E48: 119 | F48: =158-40 -> 118 | G48: =+F48-E48 -> -1 | H48: =+D48*G48 -> -4300.926 | I48: SC | J48: SC | K48: NO SE ENCUENTRA EL DESVIO AJUSTAR | L48: - | N48: =+SUM(L48:M48) -> 0 | O48: =-E48-N48+F48 -> -1 | P48: Ajustar | S48: =+R48-Q48 -> 0 | T48: =IF(G48=0,0,IF(P48="Recontar",S48,IF(P48="Ajustar",O48,IF(P48="Canje",G48)))) -> -1 | U48: Faltante | V48: =IF(U48=$V$4,T48,"0") -> -1 | W48: =IF(U48=$W$4,T48,"0") -> 0 | X48: =IF(U48=$V$4,0,IF(U48=$W$4,0,IF(U48="-",0,IF(U48="Sin Ajuste",0,T48)))) -> 0 | Y48: =+V48*D48+W48*D48 -> -4300.926 | Z48: =+E48*D48 -> 511810.19 | AA48: =+Z48/$Z$3 -> 0.0027862732 | AB48: =+AB47+AA48 -> 0.41842007
A49: D-04-06-E01 | B49: 488200K04000 | C49: BIELETA BARR. ESTABIL.DER. | D49: 144483.14 | E49: 56 | F49: 55 | G49: =+F49-E49 -> -1 | H49: =+D49*G49 -> -144483.14 | I49: SC | J49: SC | K49: NO SE ENCUENTRA EL DESVIO AJUSTAR | L49: - | N49: =+SUM(L49:M49) -> 0 | O49: =-E49-N49+F49 -> -1 | P49: Ajustar | S49: =+R49-Q49 -> 0 | T49: =IF(G49=0,0,IF(P49="Recontar",S49,IF(P49="Ajustar",O49,IF(P49="Canje",G49)))) -> -1 | U49: Faltante | V49: =IF(U49=$V$4,T49,"0") -> -1 | W49: =IF(U49=$W$4,T49,"0") -> 0 | X49: =IF(U49=$V$4,0,IF(U49=$W$4,0,IF(U49="-",0,IF(U49="Sin Ajuste",0,T49)))) -> 0 | Y49: =+V49*D49+W49*D49 -> -144483.14 | Z49: =+E49*D49 -> 8091056 | AA49: =+Z49/$Z$3 -> 0.04404737 | AB49: =+AB48+AA49 -> 0.46246744
A50: D-04-06-E02 | B50: 488100K02000 | C50: BIELETA BARRA ESTABILIZ. IZQ | D50: 144483.14 | E50: 30 | F50: 30 | G50: =+F50-E50 -> 0 | H50: =+D50*G50 -> 0 | I50: SC | J50: SC | K50: - | L50: - | N50: =+SUM(L50:M50) -> 0 | O50: =-E50-N50+F50 -> 0 | P50: - | S50: =+R50-Q50 -> 0 | T50: =IF(G50=0,0,IF(P50="Recontar",S50,IF(P50="Ajustar",O50,IF(P50="Canje",G50)))) -> 0 | U50: - | V50: =IF(U50=$V$4,T50,"0") -> 0 | W50: =IF(U50=$W$4,T50,"0") -> 0 | X50: =IF(U50=$V$4,0,IF(U50=$W$4,0,IF(U50="-",0,IF(U50="Sin Ajuste",0,T50)))) -> 0 | Y50: =+V50*D50+W50*D50 -> 0 | Z50: =+E50*D50 -> 4334494.3 | AA50: =+Z50/$Z$3 -> 0.023596805 | AB50: =+AB49+AA50 -> 0.48606424
A51: D-04-07-A01 | B51: 486090K08000 | C51: SOPORTE SUSPENSION FR. | D51: 80272.955 | E51: 66 | F51: =69-6 -> 63 | G51: =+F51-E51 -> -3 | H51: =+D51*G51 -> -240818.86 | I51: SC | J51: SC | K51: NO SE ENCUENTRA EL DESVIO AJUSTAR | L51: - | N51: =+SUM(L51:M51) -> 0 | O51: =-E51-N51+F51 -> -3 | P51: Ajustar | S51: =+R51-Q51 -> 0 | T51: =IF(G51=0,0,IF(P51="Recontar",S51,IF(P51="Ajustar",O51,IF(P51="Canje",G51)))) -> -3 | U51: Faltante | V51: =IF(U51=$V$4,T51,"0") -> -3 | W51: =IF(U51=$W$4,T51,"0") -> 0 | X51: =IF(U51=$V$4,0,IF(U51=$W$4,0,IF(U51="-",0,IF(U51="Sin Ajuste",0,T51)))) -> 0 | Y51: =+V51*D51+W51*D51 -> -240818.86 | Z51: =+E51*D51 -> 5298015 | AA51: =+Z51/$Z$3 -> 0.028842172 | AB51: =+AB50+AA51 -> 0.51490642
A52: D-04-07-F04 | B52: 4260B0K27000 | C52: TAZA DE RUEDA | D52: 69053.285 | E52: 13 | F52: =12+1 -> 13 | G52: =+F52-E52 -> 0 | H52: =+D52*G52 -> 0 | I52: SC | J52: SC | K52: - | L52: - | N52: =+SUM(L52:M52) -> 0 | O52: =-E52-N52+F52 -> 0 | P52: - | S52: =+R52-Q52 -> 0 | T52: =IF(G52=0,0,IF(P52="Recontar",S52,IF(P52="Ajustar",O52,IF(P52="Canje",G52)))) -> 0 | U52: - | V52: =IF(U52=$V$4,T52,"0") -> 0 | W52: =IF(U52=$W$4,T52,"0") -> 0 | X52: =IF(U52=$V$4,0,IF(U52=$W$4,0,IF(U52="-",0,IF(U52="Sin Ajuste",0,T52)))) -> 0 | Y52: =+V52*D52+W52*D52 -> 0 | Z52: =+E52*D52 -> 897692.71 | AA52: =+Z52/$Z$3 -> 0.0048870014 | AB52: =+AB51+AA52 -> 0.51979342
A53: D-04-08-E02 | B53: 4260B0K23000 | C53: TAZA DE RUEDA GRIS | D53: 31570.35 | E53: 18 | F53: 18 | G53: =+F53-E53 -> 0 | H53: =+D53*G53 -> 0 | I53: SC | J53: SC | K53: - | L53: - | N53: =+SUM(L53:M53) -> 0 | O53: =-E53-N53+F53 -> 0 | P53: - | S53: =+R53-Q53 -> 0 | T53: =IF(G53=0,0,IF(P53="Recontar",S53,IF(P53="Ajustar",O53,IF(P53="Canje",G53)))) -> 0 | U53: - | V53: =IF(U53=$V$4,T53,"0") -> 0 | W53: =IF(U53=$W$4,T53,"0") -> 0 | X53: =IF(U53=$V$4,0,IF(U53=$W$4,0,IF(U53="-",0,IF(U53="Sin Ajuste",0,T53)))) -> 0 | Y53: =+V53*D53+W53*D53 -> 0 | Z53: =+E53*D53 -> 568266.3 | AA53: =+Z53/$Z$3 -> 0.0030936179 | AB53: =+AB52+AA53 -> 0.52288704
A54: D-04-08-F03 | B54: 043710K08200 | C54: CRUCETA CARDAN | D54: 107733.38 | E54: 29 | F54: 29 | G54: =+F54-E54 -> 0 | H54: =+D54*G54 -> 0 | I54: SC | J54: SC | K54: - | L54: - | N54: =+SUM(L54:M54) -> 0 | O54: =-E54-N54+F54 -> 0 | P54: - | S54: =+R54-Q54 -> 0 | T54: =IF(G54=0,0,IF(P54="Recontar",S54,IF(P54="Ajustar",O54,IF(P54="Canje",G54)))) -> 0 | U54: - | V54: =IF(U54=$V$4,T54,"0") -> 0 | W54: =IF(U54=$W$4,T54,"0") -> 0 | X54: =IF(U54=$V$4,0,IF(U54=$W$4,0,IF(U54="-",0,IF(U54="Sin Ajuste",0,T54)))) -> 0 | Y54: =+V54*D54+W54*D54 -> 0 | Z54: =+E54*D54 -> 3124268 | AA54: =+Z54/$Z$3 -> 0.017008384 | AB54: =+AB53+AA54 -> 0.53989542
A55: D-04-09-A02 | B55: 364107102000 | C55: ACTUADOR CAJA TRANSF. liso (1610- ) | D55: 796230.86 | E55: 5 | F55: =6-1 -> 5 | G55: =+F55-E55 -> 0 | H55: =+D55*G55 -> 0 | I55: SC | J55: SC | K55: - | L55: - | N55: =+SUM(L55:M55) -> 0 | O55: =-E55-N55+F55 -> 0 | P55: - | S55: =+R55-Q55 -> 0 | T55: =IF(G55=0,0,IF(P55="Recontar",S55,IF(P55="Ajustar",O55,IF(P55="Canje",G55)))) -> 0 | U55: - | V55: =IF(U55=$V$4,T55,"0") -> 0 | W55: =IF(U55=$W$4,T55,"0") -> 0 | X55: =IF(U55=$V$4,0,IF(U55=$W$4,0,IF(U55="-",0,IF(U55="Sin Ajuste",0,T55)))) -> 0 | Y55: =+V55*D55+W55*D55 -> 0 | Z55: =+E55*D55 -> 3981154.3 | AA55: =+Z55/$Z$3 -> 0.021673237 | AB55: =+AB54+AA55 -> 0.56156866
A56: D-05-05-E01 | B56: 903665300400 | C56: RODAMIENTO | D56: 44959.565 | E56: 2 | F56: 2 | G56: =+F56-E56 -> 0 | H56: =+D56*G56 -> 0 | I56: SC | J56: SC | K56: - | L56: - | N56: =+SUM(L56:M56) -> 0 | O56: =-E56-N56+F56 -> 0 | P56: - | S56: =+R56-Q56 -> 0 | T56: =IF(G56=0,0,IF(P56="Recontar",S56,IF(P56="Ajustar",O56,IF(P56="Canje",G56)))) -> 0 | U56: - | V56: =IF(U56=$V$4,T56,"0") -> 0 | W56: =IF(U56=$W$4,T56,"0") -> 0 | X56: =IF(U56=$V$4,0,IF(U56=$W$4,0,IF(U56="-",0,IF(U56="Sin Ajuste",0,T56)))) -> 0 | Y56: =+V56*D56+W56*D56 -> 0 | Z56: =+E56*D56 -> 89919.13 | AA56: =+Z56/$Z$3 -> 0.00048951597 | AB56: =+AB55+AA56 -> 0.56205817
A57: D-06-05-D02 | B57: 853302101000 | C57: MOTOR LAVAPARABRISAS | D57: 119584.82 | E57: 1 | F57: 1 | G57: =+F57-E57 -> 0 | H57: =+D57*G57 -> 0 | I57: SC | J57: SC | K57: - | L57: - | N57: =+SUM(L57:M57) -> 0 | O57: =-E57-N57+F57 -> 0 | P57: - | S57: =+R57-Q57 -> 0 | T57: =IF(G57=0,0,IF(P57="Recontar",S57,IF(P57="Ajustar",O57,IF(P57="Canje",G57)))) -> 0 | U57: - | V57: =IF(U57=$V$4,T57,"0") -> 0 | W57: =IF(U57=$W$4,T57,"0") -> 0 | X57: =IF(U57=$V$4,0,IF(U57=$W$4,0,IF(U57="-",0,IF(U57="Sin Ajuste",0,T57)))) -> 0 | Y57: =+V57*D57+W57*D57 -> 0 | Z57: =+E57*D57 -> 119584.82 | AA57: =+Z57/$Z$3 -> 0.00065101472 | AB57: =+AB56+AA57 -> 0.56270919
A58: D-07-01-A01 | B58: 435120K22000 | C58: DISCO FRENO DEL. | D58: 118017.05 | E58: 6 | F58: 8 | G58: =+F58-E58 -> 2 | H58: =+D58*G58 -> 236034.09 | I58: SC | J58: SC | K58: CRUZADO CON 435120K320 435120K320 SE ENCUENTRA FALTANTE X2 | L58: - | N58: =+SUM(L58:M58) -> 0 | O58: =-E58-N58+F58 -> 2 | P58: Recontar | Q58: 6 | R58: 8 | S58: =+R58-Q58 -> 2 | T58: =IF(G58=0,0,IF(P58="Recontar",S58,IF(P58="Ajustar",O58,IF(P58="Canje",G58)))) -> 2 | U58: Canje D | V58: =IF(U58=$V$4,T58,"0") -> 0 | W58: =IF(U58=$W$4,T58,"0") -> 0 | X58: =IF(U58=$V$4,0,IF(U58=$W$4,0,IF(U58="-",0,IF(U58="Sin Ajuste",0,T58)))) -> 2 | Y58: =+V58*D58+W58*D58 -> 0 | Z58: =+E58*D58 -> 708102.28 | AA58: =+Z58/$Z$3 -> 0.0038548791 | AB58: =+AB57+AA58 -> 0.56656407
A59: D-02-04-A01 | B59: 435120K32000 | C59: DISCO FRENO DEL. | D59: 126300.48 | E59: 2 | F59: 0 | G59: =+F59-E59 -> -2 | H59: =+D59*G59 -> -252600.95 | I59: SC | J59: SC | K59: CRUZADO CON 435120K320 435120K320 SE ENCUENTRA FALTANTE X2 | L59: - | N59: =+SUM(L59:M59) -> 0 | O59: =-E59-N59+F59 -> -2 | P59: Recontar | Q59: 20 | R59: =12+6 -> 18 | S59: =+R59-Q59 -> -2 | T59: =IF(G59=0,0,IF(P59="Recontar",S59,IF(P59="Ajustar",O59,IF(P59="Canje",G59)))) -> -2 | U59: Canje D | V59: =IF(U59=$V$4,T59,"0") -> 0 | W59: =IF(U59=$W$4,T59,"0") -> 0 | X59: =IF(U59=$V$4,0,IF(U59=$W$4,0,IF(U59="-",0,IF(U59="Sin Ajuste",0,T59)))) -> -2 | Y59: =+V59*D59+W59*D59 -> 0 | Z59: =+E59*D59 -> 252600.95 | AA59: =+Z59/$Z$3 -> 0.001375149 | AB59: =+AB58+AA59 -> 0.56793922
A60: D-07-01-B03 | B60: 166203003100 | C60: TENSOR | D60: 154143.74 | E60: 7 | F60: 7 | G60: =+F60-E60 -> 0 | H60: =+D60*G60 -> 0 | I60: SC | J60: SC | K60: - | L60: - | N60: =+SUM(L60:M60) -> 0 | O60: =-E60-N60+F60 -> 0 | P60: - | S60: =+R60-Q60 -> 0 | T60: =IF(G60=0,0,IF(P60="Recontar",S60,IF(P60="Ajustar",O60,IF(P60="Canje",G60)))) -> 0 | U60: - | V60: =IF(U60=$V$4,T60,"0") -> 0 | W60: =IF(U60=$W$4,T60,"0") -> 0 | X60: =IF(U60=$V$4,0,IF(U60=$W$4,0,IF(U60="-",0,IF(U60="Sin Ajuste",0,T60)))) -> 0 | Y60: =+V60*D60+W60*D60 -> 0 | Z60: =+E60*D60 -> 1079006.2 | AA60: =+Z60/$Z$3 -> 0.0058740643 | AB60: =+AB59+AA60 -> 0.57381328
A61: D-07-01-C01 | B61: 815610K31000 | C61: ACRILICO FARO IZQ.VALEO | D61: 96845.42 | E61: 7 | F61: 6 | G61: =+F61-E61 -> -1 | H61: =+D61*G61 -> -96845.42 | I61: SC | J61: SC | K61: CRUZADO CON 815610K271 - | L61: - | N61: =+SUM(L61:M61) -> 0 | O61: =-E61-N61+F61 -> -1 | P61: Recontar | Q61: 8 | R61: 7 | S61: =+R61-Q61 -> -1 | T61: =IF(G61=0,0,IF(P61="Recontar",S61,IF(P61="Ajustar",O61,IF(P61="Canje",G61)))) -> -1 | U61: Faltante | V61: =IF(U61=$V$4,T61,"0") -> -1 | W61: =IF(U61=$W$4,T61,"0") -> 0 | X61: =IF(U61=$V$4,0,IF(U61=$W$4,0,IF(U61="-",0,IF(U61="Sin Ajuste",0,T61)))) -> 0 | Y61: =+V61*D61+W61*D61 -> -96845.42 | Z61: =+E61*D61 -> 677917.94 | AA61: =+Z61/$Z$3 -> 0.0036905568 | AB61: =+AB60+AA61 -> 0.57750384
A62: D-07-02-A01 | B62: 435120K11000 | C62: DISCO DE FRENO | D62: 117864.45 | E62: 18 | F62: =10+8+2 -> 20 | G62: =+F62-E62 -> 2 | H62: =+D62*G62 -> 235728.91 | I62: SC | J62: SC | K62: MAL CONTEO. EL ARTICULO SE ENCUENTRA SOBRANTE X1 RECONTAR | L62: - | N62: =+SUM(L62:M62) -> 0 | O62: =-E62-N62+F62 -> 2 | P62: Recontar | Q62: 18 | R62: 19 | S62: =+R62-Q62 -> 1 | T62: =IF(G62=0,0,IF(P62="Recontar",S62,IF(P62="Ajustar",O62,IF(P62="Canje",G62)))) -> 1 | U62: Sobrante | V62: =IF(U62=$V$4,T62,"0") -> 0 | W62: =IF(U62=$W$4,T62,"0") -> 1 | X62: =IF(U62=$V$4,0,IF(U62=$W$4,0,IF(U62="-",0,IF(U62="Sin Ajuste",0,T62)))) -> 0 | Y62: =+V62*D62+W62*D62 -> 117864.45 | Z62: =+E62*D62 -> 2121560.2 | AA62: =+Z62/$Z$3 -> 0.011549685 | AB62: =+AB61+AA62 -> 0.58905352
A63: D-07-05-A01 | B63: 044270K01100 | C63: JUNTA | D63: 114421.66 | E63: 12 | F63: 12 | G63: =+F63-E63 -> 0 | H63: =+D63*G63 -> 0 | I63: SC | J63: SC | K63: - | L63: - | N63: =+SUM(L63:M63) -> 0 | O63: =-E63-N63+F63 -> 0 | P63: - | S63: =+R63-Q63 -> 0 | T63: =IF(G63=0,0,IF(P63="Recontar",S63,IF(P63="Ajustar",O63,IF(P63="Canje",G63)))) -> 0 | U63: - | V63: =IF(U63=$V$4,T63,"0") -> 0 | W63: =IF(U63=$W$4,T63,"0") -> 0 | X63: =IF(U63=$V$4,0,IF(U63=$W$4,0,IF(U63="-",0,IF(U63="Sin Ajuste",0,T63)))) -> 0 | Y63: =+V63*D63+W63*D63 -> 0 | Z63: =+E63*D63 -> 1373059.9 | AA63: =+Z63/$Z$3 -> 0.0074748804 | AB63: =+AB62+AA63 -> 0.5965284
A64: D-07-08-A01 | B64: 044270K05000 | C64: JGO. FUELLE | D64: 97727.413 | E64: 9 | F64: 9 | G64: =+F64-E64 -> 0 | H64: =+D64*G64 -> 0 | I64: SC | J64: SC | K64: - | L64: - | N64: =+SUM(L64:M64) -> 0 | O64: =-E64-N64+F64 -> 0 | P64: - | S64: =+R64-Q64 -> 0 | T64: =IF(G64=0,0,IF(P64="Recontar",S64,IF(P64="Ajustar",O64,IF(P64="Canje",G64)))) -> 0 | U64: - | V64: =IF(U64=$V$4,T64,"0") -> 0 | W64: =IF(U64=$W$4,T64,"0") -> 0 | X64: =IF(U64=$V$4,0,IF(U64=$W$4,0,IF(U64="-",0,IF(U64="Sin Ajuste",0,T64)))) -> 0 | Y64: =+V64*D64+W64*D64 -> 0 | Z64: =+E64*D64 -> 879546.72 | AA64: =+Z64/$Z$3 -> 0.0047882154 | AB64: =+AB63+AA64 -> 0.60131662
A65: D-07-09-A01 | B65: 044950K05000 | C65: JGO. ZAPATAS DE FRENO | D65: 224915.11 | E65: 55 | F65: =35+19 -> 54 | G65: =+F65-E65 -> -1 | H65: =+D65*G65 -> -224915.11 | I65: SC | J65: SC | K65: MAL UBICADA X1 STOCK OK. RECONTAR | L65: - | N65: =+SUM(L65:M65) -> 0 | O65: =-E65-N65+F65 -> -1 | P65: Recontar | Q65: 59 | R65: 59 | S65: =+R65-Q65 -> 0 | T65: 0 | U65: Sin Ajuste | V65: =IF(U65=$V$4,T65,"0") -> 0 | W65: =IF(U65=$W$4,T65,"0") -> 0 | X65: =IF(U65=$V$4,0,IF(U65=$W$4,0,IF(U65="-",0,IF(U65="Sin Ajuste",0,T65)))) -> 0 | Y65: =+V65*D65+W65*D65 -> 0 | Z65: =+E65*D65 -> 12370331 | AA65: =+Z65/$Z$3 -> 0.067343564 | AB65: =+AB64+AA65 -> 0.66866018
A66: D-07-09-D03 | B66: VAR-0372-00001 | C66: RULEMAN POLEA ACANALADA | D66: 2976.8148 | E66: 42 | F66: 42 | G66: =+F66-E66 -> 0 | H66: =+D66*G66 -> 0 | I66: SC | J66: SC | K66: - | L66: - | N66: =+SUM(L66:M66) -> 0 | O66: =-E66-N66+F66 -> 0 | P66: - | S66: =+R66-Q66 -> 0 | T66: =IF(G66=0,0,IF(P66="Recontar",S66,IF(P66="Ajustar",O66,IF(P66="Canje",G66)))) -> 0 | U66: - | V66: =IF(U66=$V$4,T66,"0") -> 0 | W66: =IF(U66=$W$4,T66,"0") -> 0 | X66: =IF(U66=$V$4,0,IF(U66=$W$4,0,IF(U66="-",0,IF(U66="Sin Ajuste",0,T66)))) -> 0 | Y66: =+V66*D66+W66*D66 -> 0 | Z66: =+E66*D66 -> 125026.22 | AA66: =+Z66/$Z$3 -> 0.00068063751 | AB66: =+AB65+AA66 -> 0.66934082
A67: D-07-11-F02 | B67: 904301203100 | C67: JTA.TAPON CARTER (AZUL) | D67: 1140.328 | E67: 1284 | F67: =1290+75 -> 1365 | G67: =+F67-E67 -> 81 | H67: =+D67*G67 -> 92366.568 | I67: SC | J67: SC | K67: VARIACION EN LA OPERATIVA DEL TALLER (ES EL DE MAS ALTA ROTACION) recomiendo contar y controlar con el stock virtual al momento de terminar. (RECONTAR) | L67: - | N67: =+SUM(L67:M67) -> 0 | O67: =-E67-N67+F67 -> 81 | P67: Recontar | Q67: 1623 | R67: 1610 | S67: =+R67-Q67 -> -13 | T67: =IF(G67=0,0,IF(P67="Recontar",S67,IF(P67="Ajustar",O67,IF(P67="Canje",G67)))) -> -13 | U67: Faltante | V67: =IF(U67=$V$4,T67,"0") -> -13 | W67: =IF(U67=$W$4,T67,"0") -> 0 | X67: =IF(U67=$V$4,0,IF(U67=$W$4,0,IF(U67="-",0,IF(U67="Sin Ajuste",0,T67)))) -> 0 | Y67: =+V67*D67+W67*D67 -> -14824.264 | Z67: =+E67*D67 -> 1464181.2 | AA67: =+Z67/$Z$3 -> 0.0079709408 | AB67: =+AB66+AA67 -> 0.67731176
A68: D-07-11-F03 | B68: 904301800800 | C68: JTA.TAPON DIF (aluminio) | D68: 1177.12 | E68: 1472 | F68: =1427+71 -> 1498 | G68: =+F68-E68 -> 26 | H68: =+D68*G68 -> 30605.12 | I68: SC | J68: SC | K68: VARIACION EN LA OPERATIVA DEL TALLER (ES EL DE MAS ALTA ROTACION) recomiendo contar y controlar con el stock virtual al momento de terminar. (RECONTAR) | L68: - | N68: =+SUM(L68:M68) -> 0 | O68: =-E68-N68+F68 -> 26 | P68: Recontar | Q68: 2082 | R68: 2008 | S68: =+R68-Q68 -> -74 | T68: =IF(G68=0,0,IF(P68="Recontar",S68,IF(P68="Ajustar",O68,IF(P68="Canje",G68)))) -> -74 | U68: Faltante | V68: =IF(U68=$V$4,T68,"0") -> -74 | W68: =IF(U68=$W$4,T68,"0") -> 0 | X68: =IF(U68=$V$4,0,IF(U68=$W$4,0,IF(U68="-",0,IF(U68="Sin Ajuste",0,T68)))) -> 0 | Y68: =+V68*D68+W68*D68 -> -87106.88 | Z68: =+E68*D68 -> 1732720.6 | AA68: =+Z68/$Z$3 -> 0.0094328585 | AB68: =+AB67+AA68 -> 0.68674462
A69: D-08-01-A01 | B69: 815510K26100 | C69: ACRILICO FARO TR. DER. KOITO | D69: 125850.53 | E69: 9 | F69: 10 | G69: =+F69-E69 -> 1 | H69: =+D69*G69 -> 125850.53 | I69: SC | J69: SC | K69: CRUZADO CON 815510K300 - | L69: - | N69: =+SUM(L69:M69) -> 0 | O69: =-E69-N69+F69 -> 1 | P69: Recontar | Q69: 9 | R69: 10 | S69: =+R69-Q69 -> 1 | T69: =IF(G69=0,0,IF(P69="Recontar",S69,IF(P69="Ajustar",O69,IF(P69="Canje",G69)))) -> 1 | U69: Sobrante | V69: =IF(U69=$V$4,T69,"0") -> 0 | W69: =IF(U69=$W$4,T69,"0") -> 1 | X69: =IF(U69=$V$4,0,IF(U69=$W$4,0,IF(U69="-",0,IF(U69="Sin Ajuste",0,T69)))) -> 0 | Y69: =+V69*D69+W69*D69 -> 125850.53 | Z69: =+E69*D69 -> 1132654.8 | AA69: =+Z69/$Z$3 -> 0.006166125 | AB69: =+AB68+AA69 -> 0.69291074
A70: D-08-05-A01 | B70: 435120K15000 | C70: DISCO DE FRENO DEL. | D70: 118017.05 | E70: 18 | F70: =10+8 -> 18 | G70: =+F70-E70 -> 0 | H70: =+D70*G70 -> 0 | I70: SC | J70: SC | K70: - | L70: - | N70: =+SUM(L70:M70) -> 0 | O70: =-E70-N70+F70 -> 0 | P70: - | S70: =+R70-Q70 -> 0 | T70: =IF(G70=0,0,IF(P70="Recontar",S70,IF(P70="Ajustar",O70,IF(P70="Canje",G70)))) -> 0 | U70: - | V70: =IF(U70=$V$4,T70,"0") -> 0 | W70: =IF(U70=$W$4,T70,"0") -> 0 | X70: =IF(U70=$V$4,0,IF(U70=$W$4,0,IF(U70="-",0,IF(U70="Sin Ajuste",0,T70)))) -> 0 | Y70: =+V70*D70+W70*D70 -> 0 | Z70: =+E70*D70 -> 2124306.8 | AA70: =+Z70/$Z$3 -> 0.011564637 | AB70: =+AB69+AA70 -> 0.70447538
A71: D-08-06-A01 | B71: 435120K08000 | C71: DISCO DE FRENO | D71: 113112.38 | E71: 6 | F71: 6 | G71: =+F71-E71 -> 0 | H71: =+D71*G71 -> 0 | I71: SC | J71: SC | K71: - | L71: - | N71: =+SUM(L71:M71) -> 0 | O71: =-E71-N71+F71 -> 0 | P71: - | S71: =+R71-Q71 -> 0 | T71: =IF(G71=0,0,IF(P71="Recontar",S71,IF(P71="Ajustar",O71,IF(P71="Canje",G71)))) -> 0 | U71: - | V71: =IF(U71=$V$4,T71,"0") -> 0 | W71: =IF(U71=$W$4,T71,"0") -> 0 | X71: =IF(U71=$V$4,0,IF(U71=$W$4,0,IF(U71="-",0,IF(U71="Sin Ajuste",0,T71)))) -> 0 | Y71: =+V71*D71+W71*D71 -> 0 | Z71: =+E71*D71 -> 678674.3 | AA71: =+Z71/$Z$3 -> 0.0036946745 | AB71: =+AB70+AA71 -> 0.70817005
A72: D-08-11-A02 | B72: 312040K11000 | C72: HORQUILLA EMBRAGUE | D72: 115831.74 | E72: 24 | F72: 24 | G72: =+F72-E72 -> 0 | H72: =+D72*G72 -> 0 | I72: SC | J72: SC | K72: - | L72: - | N72: =+SUM(L72:M72) -> 0 | O72: =-E72-N72+F72 -> 0 | P72: - | S72: =+R72-Q72 -> 0 | T72: =IF(G72=0,0,IF(P72="Recontar",S72,IF(P72="Ajustar",O72,IF(P72="Canje",G72)))) -> 0 | U72: - | V72: =IF(U72=$V$4,T72,"0") -> 0 | W72: =IF(U72=$W$4,T72,"0") -> 0 | X72: =IF(U72=$V$4,0,IF(U72=$W$4,0,IF(U72="-",0,IF(U72="Sin Ajuste",0,T72)))) -> 0 | Y72: =+V72*D72+W72*D72 -> 0 | Z72: =+E72*D72 -> 2779961.9 | AA72: =+Z72/$Z$3 -> 0.015133996 | AB72: =+AB71+AA72 -> 0.72330405
A73: D-08-11-E05 | B73: 909812002900 | C73: LAMPARA XENON COROLLA | D73: 186885.57 | E73: 3 | F73: 3 | G73: =+F73-E73 -> 0 | H73: =+D73*G73 -> 0 | I73: SC | J73: SC | K73: - | L73: - | N73: =+SUM(L73:M73) -> 0 | O73: =-E73-N73+F73 -> 0 | P73: - | S73: =+R73-Q73 -> 0 | T73: =IF(G73=0,0,IF(P73="Recontar",S73,IF(P73="Ajustar",O73,IF(P73="Canje",G73)))) -> 0 | U73: - | V73: =IF(U73=$V$4,T73,"0") -> 0 | W73: =IF(U73=$W$4,T73,"0") -> 0 | X73: =IF(U73=$V$4,0,IF(U73=$W$4,0,IF(U73="-",0,IF(U73="Sin Ajuste",0,T73)))) -> 0 | Y73: =+V73*D73+W73*D73 -> 0 | Z73: =+E73*D73 -> 560656.72 | AA73: =+Z73/$Z$3 -> 0.0030521917 | AB73: =+AB72+AA73 -> 0.72635624
A74: D-09-03-B01 | B74: 485318Z02100 | C74: SET AMORTIGUADOR RR RH | D74: 58221.282 | E74: 52 | F74: =41+13-2 -> 52 | G74: =+F74-E74 -> 0 | H74: =+D74*G74 -> 0 | I74: SC | J74: SC | K74: - | L74: - | N74: =+SUM(L74:M74) -> 0 | O74: =-E74-N74+F74 -> 0 | P74: - | S74: =+R74-Q74 -> 0 | T74: =IF(G74=0,0,IF(P74="Recontar",S74,IF(P74="Ajustar",O74,IF(P74="Canje",G74)))) -> 0 | U74: - | V74: =IF(U74=$V$4,T74,"0") -> 0 | W74: =IF(U74=$W$4,T74,"0") -> 0 | X74: =IF(U74=$V$4,0,IF(U74=$W$4,0,IF(U74="-",0,IF(U74="Sin Ajuste",0,T74)))) -> 0 | Y74: =+V74*D74+W74*D74 -> 0 | Z74: =+E74*D74 -> 3027506.7 | AA74: =+Z74/$Z$3 -> 0.016481619 | AB74: =+AB73+AA74 -> 0.74283786
A75: D-09-04-B01 | B75: 485410936100 | C75: SET AMORTIGUADOR RR LH | D75: 55651.554 | E75: 31 | F75: 31 | G75: =+F75-E75 -> 0 | H75: =+D75*G75 -> 0 | I75: SC | J75: SC | K75: - | L75: - | N75: =+SUM(L75:M75) -> 0 | O75: =-E75-N75+F75 -> 0 | P75: - | S75: =+R75-Q75 -> 0 | T75: =IF(G75=0,0,IF(P75="Recontar",S75,IF(P75="Ajustar",O75,IF(P75="Canje",G75)))) -> 0 | U75: - | V75: =IF(U75=$V$4,T75,"0") -> 0 | W75: =IF(U75=$W$4,T75,"0") -> 0 | X75: =IF(U75=$V$4,0,IF(U75=$W$4,0,IF(U75="-",0,IF(U75="Sin Ajuste",0,T75)))) -> 0 | Y75: =+V75*D75+W75*D75 -> 0 | Z75: =+E75*D75 -> 1725198.2 | AA75: =+Z75/$Z$3 -> 0.0093919065 | AB75: =+AB74+AA75 -> 0.75222977
A76: D-09-04-C01 | B76: 485100D39000 | C76: AMORTIGUADOR DEL. | D76: 129244.09 | E76: 19 | F76: 19 | G76: =+F76-E76 -> 0 | H76: =+D76*G76 -> 0 | I76: SC | J76: SC | K76: - | L76: - | N76: =+SUM(L76:M76) -> 0 | O76: =-E76-N76+F76 -> 0 | P76: - | S76: =+R76-Q76 -> 0 | T76: =IF(G76=0,0,IF(P76="Recontar",S76,IF(P76="Ajustar",O76,IF(P76="Canje",G76)))) -> 0 | U76: - | V76: =IF(U76=$V$4,T76,"0") -> 0 | W76: =IF(U76=$W$4,T76,"0") -> 0 | X76: =IF(U76=$V$4,0,IF(U76=$W$4,0,IF(U76="-",0,IF(U76="Sin Ajuste",0,T76)))) -> 0 | Y76: =+V76*D76+W76*D76 -> 0 | Z76: =+E76*D76 -> 2455637.7 | AA76: =+Z76/$Z$3 -> 0.013368388 | AB76: =+AB75+AA76 -> 0.76559816
A77: D-09-05-B01 | B77: 372300K05000 | C77: COJINETE CENT CARDAN | D77: 168228.65 | E77: 10 | F77: 10 | G77: =+F77-E77 -> 0 | H77: =+D77*G77 -> 0 | I77: SC | J77: SC | K77: - | L77: - | N77: =+SUM(L77:M77) -> 0 | O77: =-E77-N77+F77 -> 0 | P77: - | S77: =+R77-Q77 -> 0 | T77: =IF(G77=0,0,IF(P77="Recontar",S77,IF(P77="Ajustar",O77,IF(P77="Canje",G77)))) -> 0 | U77: - | V77: =IF(U77=$V$4,T77,"0") -> 0 | W77: =IF(U77=$W$4,T77,"0") -> 0 | X77: =IF(U77=$V$4,0,IF(U77=$W$4,0,IF(U77="-",0,IF(U77="Sin Ajuste",0,T77)))) -> 0 | Y77: =+V77*D77+W77*D77 -> 0 | Z77: =+E77*D77 -> 1682286.5 | AA77: =+Z77/$Z$3 -> 0.0091582971 | AB77: =+AB76+AA77 -> 0.77475645
A78: D-09-05-D01 | B78: 312307101100 | C78: RULEMAN EMPUJE | D78: 106612.47 | E78: 26 | F78: 25 | G78: =+F78-E78 -> -1 | H78: =+D78*G78 -> -106612.47 | I78: SC | J78: SC | K78: NO SE ENCUENTRA EL DESVIO AJUSTAR | L78: - | N78: =+SUM(L78:M78) -> 0 | O78: =-E78-N78+F78 -> -1 | P78: Ajustar | S78: =+R78-Q78 -> 0 | T78: =IF(G78=0,0,IF(P78="Recontar",S78,IF(P78="Ajustar",O78,IF(P78="Canje",G78)))) -> -1 | U78: Faltante | V78: =IF(U78=$V$4,T78,"0") -> -1 | W78: =IF(U78=$W$4,T78,"0") -> 0 | X78: =IF(U78=$V$4,0,IF(U78=$W$4,0,IF(U78="-",0,IF(U78="Sin Ajuste",0,T78)))) -> 0 | Y78: =+V78*D78+W78*D78 -> -106612.47 | Z78: =+E78*D78 -> 2771924.2 | AA78: =+Z78/$Z$3 -> 0.015090239 | AB78: =+AB77+AA78 -> 0.78984669
A79: D-09-06-A01 | B79: 044650K40100 | C79: JGO. PASTILLAS FRENO HX 2016 | D79: 145362.67 | E79: 71 | F79: =72-1 -> 71 | G79: =+F79-E79 -> 0 | H79: =+D79*G79 -> 0 | I79: SC | J79: SC | K79: - | L79: - | N79: =+SUM(L79:M79) -> 0 | O79: =-E79-N79+F79 -> 0 | P79: - | S79: =+R79-Q79 -> 0 | T79: =IF(G79=0,0,IF(P79="Recontar",S79,IF(P79="Ajustar",O79,IF(P79="Canje",G79)))) -> 0 | U79: - | V79: =IF(U79=$V$4,T79,"0") -> 0 | W79: =IF(U79=$W$4,T79,"0") -> 0 | X79: =IF(U79=$V$4,0,IF(U79=$W$4,0,IF(U79="-",0,IF(U79="Sin Ajuste",0,T79)))) -> 0 | Y79: =+V79*D79+W79*D79 -> 0 | Z79: =+E79*D79 -> 10320749 | AA79: =+Z79/$Z$3 -> 0.056185726 | AB79: =+AB78+AA79 -> 0.84603242
A80: D-09-06-F01 | B80: 044650230000 | C80: JGO.PAST.FRENO DEL. | D80: 160851.09 | E80: 7 | F80: 6 | G80: =+F80-E80 -> -1 | H80: =+D80*G80 -> -160851.09 | I80: SC | J80: SC | K80: NO SE ENCUENTRA EL DESVIO AJUSTAR | L80: - | N80: =+SUM(L80:M80) -> 0 | O80: =-E80-N80+F80 -> -1 | P80: Ajustar | S80: =+R80-Q80 -> 0 | T80: =IF(G80=0,0,IF(P80="Recontar",S80,IF(P80="Ajustar",O80,IF(P80="Canje",G80)))) -> -1 | U80: Faltante | V80: =IF(U80=$V$4,T80,"0") -> -1 | W80: =IF(U80=$W$4,T80,"0") -> 0 | X80: =IF(U80=$V$4,0,IF(U80=$W$4,0,IF(U80="-",0,IF(U80="Sin Ajuste",0,T80)))) -> 0 | Y80: =+V80*D80+W80*D80 -> -160851.09 | Z80: =+E80*D80 -> 1125957.6 | AA80: =+Z80/$Z$3 -> 0.0061296661 | AB80: =+AB79+AA80 -> 0.85216208
A81: D-09-07-A03 | B81: 044660230000 | C81: JGO. PASTILLAS FRENO RR COROLLA | D81: 102521.04 | E81: 20 | F81: 22 | G81: =+F81-E81 -> 2 | H81: =+D81*G81 -> 205042.08 | I81: SC | J81: SC | K81: FALTA CARGA REMITO R33-871005 STOCK OK | L81: - | N81: =+SUM(L81:M81) -> 0 | O81: =-E81-N81+F81 -> 2 | P81: Recontar | Q81: 26 | R81: 26 | S81: =+R81-Q81 -> 0 | T81: =IF(G81=0,0,IF(P81="Recontar",S81,IF(P81="Ajustar",O81,IF(P81="Canje",G81)))) -> 0 | U81: Sin Ajuste | V81: =IF(U81=$V$4,T81,"0") -> 0 | W81: =IF(U81=$W$4,T81,"0") -> 0 | X81: =IF(U81=$V$4,0,IF(U81=$W$4,0,IF(U81="-",0,IF(U81="Sin Ajuste",0,T81)))) -> 0 | Y81: =+V81*D81+W81*D81 -> 0 | Z81: =+E81*D81 -> 2050420.8 | AA81: =+Z81/$Z$3 -> 0.011162405 | AB81: =+AB80+AA81 -> 0.86332449
A82: D-09-07-B03 | B82: 044660225000 | C82: JGO.PAST.FRENO TRAS. | D82: 93275.756 | E82: 3 | F82: 3 | G82: =+F82-E82 -> 0 | H82: =+D82*G82 -> 0 | I82: SC | J82: SC | K82: - | L82: - | N82: =+SUM(L82:M82) -> 0 | O82: =-E82-N82+F82 -> 0 | P82: - | S82: =+R82-Q82 -> 0 | T82: =IF(G82=0,0,IF(P82="Recontar",S82,IF(P82="Ajustar",O82,IF(P82="Canje",G82)))) -> 0 | U82: - | V82: =IF(U82=$V$4,T82,"0") -> 0 | W82: =IF(U82=$W$4,T82,"0") -> 0 | X82: =IF(U82=$V$4,0,IF(U82=$W$4,0,IF(U82="-",0,IF(U82="Sin Ajuste",0,T82)))) -> 0 | Y82: =+V82*D82+W82*D82 -> 0 | Z82: =+E82*D82 -> 279827.27 | AA82: =+Z82/$Z$3 -> 0.0015233679 | AB82: =+AB81+AA82 -> 0.86484786
A83: D-09-07-C05 | B83: 044666014000 | C83: KIT PASTILLAS FRENO TR. | D83: 73381.224 | E83: 34 | F83: 36 | G83: =+F83-E83 -> 2 | H83: =+D83*G83 -> 146762.45 | I83: NC | J83: SC | K83: FALTA CARGA REMITO R33-871005 stock ok | L83: - | N83: =+SUM(L83:M83) -> 0 | O83: =-E83-N83+F83 -> 2 | P83: Recontar | Q83: 31 | R83: 31 | S83: =+R83-Q83 -> 0 | T83: =IF(G83=0,0,IF(P83="Recontar",S83,IF(P83="Ajustar",O83,IF(P83="Canje",G83)))) -> 0 | U83: Sin Ajuste | V83: =IF(U83=$V$4,T83,"0") -> 0 | W83: =IF(U83=$W$4,T83,"0") -> 0 | X83: =IF(U83=$V$4,0,IF(U83=$W$4,0,IF(U83="-",0,IF(U83="Sin Ajuste",0,T83)))) -> 0 | Y83: =+V83*D83+W83*D83 -> 0 | Z83: =+E83*D83 -> 2494961.6 | AA83: =+Z83/$Z$3 -> 0.013582466 | AB83: =+AB82+AA83 -> 0.87843032
A84: D-09-07-F01 | B84: 044650K30000 | C84: JGO.PASTILLA FRENO | D84: 126871.86 | E84: 16 | F84: 16 | G84: =+F84-E84 -> 0 | H84: =+D84*G84 -> 0 | I84: SC | J84: SC | K84: - | L84: - | N84: =+SUM(L84:M84) -> 0 | O84: =-E84-N84+F84 -> 0 | P84: - | S84: =+R84-Q84 -> 0 | T84: =IF(G84=0,0,IF(P84="Recontar",S84,IF(P84="Ajustar",O84,IF(P84="Canje",G84)))) -> 0 | U84: - | V84: =IF(U84=$V$4,T84,"0") -> 0 | W84: =IF(U84=$W$4,T84,"0") -> 0 | X84: =IF(U84=$V$4,0,IF(U84=$W$4,0,IF(U84="-",0,IF(U84="Sin Ajuste",0,T84)))) -> 0 | Y84: =+V84*D84+W84*D84 -> 0 | Z84: =+E84*D84 -> 2029949.8 | AA84: =+Z84/$Z$3 -> 0.011050962 | AB84: =+AB83+AA84 -> 0.88948129
A85: D-09-07-F02 | B85: 044650K28000 | C85: JGO. PAST. FRENO HX | D85: 155074.49 | E85: 45 | F85: 44 | G85: =+F85-E85 -> -1 | H85: =+D85*G85 -> -155074.49 | I85: SC | J85: SC | K85: NO SE ENCUENTRA EL DESVIO AJUSTAR | L85: - | N85: =+SUM(L85:M85) -> 0 | O85: =-E85-N85+F85 -> -1 | P85: Ajustar | S85: =+R85-Q85 -> 0 | T85: =IF(G85=0,0,IF(P85="Recontar",S85,IF(P85="Ajustar",O85,IF(P85="Canje",G85)))) -> -1 | U85: Faltante | V85: =IF(U85=$V$4,T85,"0") -> -1 | W85: =IF(U85=$W$4,T85,"0") -> 0 | X85: =IF(U85=$V$4,0,IF(U85=$W$4,0,IF(U85="-",0,IF(U85="Sin Ajuste",0,T85)))) -> 0 | Y85: =+V85*D85+W85*D85 -> -155074.49 | Z85: =+E85*D85 -> 6978351.9 | AA85: =+Z85/$Z$3 -> 0.037989855 | AB85: =+AB84+AA85 -> 0.92747114
A86: D-11-01-A02 | B86: 28800YZZWG00 | C86: BATERIA COROLLA / ETIOS | D86: 125718.85 | E86: 22 | F86: =21+1 -> 22 | G86: =+F86-E86 -> 0 | H86: =+D86*G86 -> 0 | I86: SC | J86: SC | K86: - | L86: - | N86: =+SUM(L86:M86) -> 0 | O86: =-E86-N86+F86 -> 0 | P86: - | S86: =+R86-Q86 -> 0 | T86: =IF(G86=0,0,IF(P86="Recontar",S86,IF(P86="Ajustar",O86,IF(P86="Canje",G86)))) -> 0 | U86: - | V86: =IF(U86=$V$4,T86,"0") -> 0 | W86: =IF(U86=$W$4,T86,"0") -> 0 | X86: =IF(U86=$V$4,0,IF(U86=$W$4,0,IF(U86="-",0,IF(U86="Sin Ajuste",0,T86)))) -> 0 | Y86: =+V86*D86+W86*D86 -> 0 | Z86: =+E86*D86 -> 2765814.7 | AA86: =+Z86/$Z$3 -> 0.015056979 | AB86: =+AB85+AA86 -> 0.94252812
A87: D-11-01-A04 | B87: 28800YZZUJ00 | C87: BATERIA LN3-HILUX(DIESEL) | D87: 190062.33 | E87: 21 | F87: =1+20 -> 21 | G87: =+F87-E87 -> 0 | H87: =+D87*G87 -> 0 | I87: SC | J87: SC | K87: - | L87: - | N87: =+SUM(L87:M87) -> 0 | O87: =-E87-N87+F87 -> 0 | P87: - | S87: =+R87-Q87 -> 0 | T87: =IF(G87=0,0,IF(P87="Recontar",S87,IF(P87="Ajustar",O87,IF(P87="Canje",G87)))) -> 0 | U87: - | V87: =IF(U87=$V$4,T87,"0") -> 0 | W87: =IF(U87=$W$4,T87,"0") -> 0 | X87: =IF(U87=$V$4,0,IF(U87=$W$4,0,IF(U87="-",0,IF(U87="Sin Ajuste",0,T87)))) -> 0 | Y87: =+V87*D87+W87*D87 -> 0 | Z87: =+E87*D87 -> 3991308.9 | AA87: =+Z87/$Z$3 -> 0.021728518 | AB87: =+AB86+AA87 -> 0.96425664
A88: D-11-01-A09 | B88: 08021LL02000 | C88: LIQ. LIMPIAPARABRISA | D88: 2821.427 | E88: 197 | F88: =10+276-96 -> 190 | G88: =+F88-E88 -> -7 | H88: =+D88*G88 -> -19749.989 | I88: SC | J88: SC | K88: Variacion en la operativa de taller de ese dia STOCK OK.(RECONTAR) | L88: - | N88: =+SUM(L88:M88) -> 0 | O88: =-E88-N88+F88 -> -7 | P88: Recontar | Q88: 334 | R88: =372-54+9+1+6 -> 334 | S88: =+R88-Q88 -> 0 | T88: =IF(G88=0,0,IF(P88="Recontar",S88,IF(P88="Ajustar",O88,IF(P88="Canje",G88)))) -> 0 | U88: Sin Ajuste | V88: =IF(U88=$V$4,T88,"0") -> 0 | W88: =IF(U88=$W$4,T88,"0") -> 0 | X88: =IF(U88=$V$4,0,IF(U88=$W$4,0,IF(U88="-",0,IF(U88="Sin Ajuste",0,T88)))) -> 0 | Y88: =+V88*D88+W88*D88 -> 0 | Z88: =+E88*D88 -> 555821.12 | AA88: =+Z88/$Z$3 -> 0.0030258669 | AB88: =+AB87+AA88 -> 0.9672825
A89: D-11-01-B14 | B89: 90916T203300 | C89: CORREA | D89: 54520.725 | E89: 38 | F89: 37 | G89: =+F89-E89 -> -1 | H89: =+D89*G89 -> -54520.725 | I89: SC | J89: SC | K89: ARTICULO X1 EN RESERVA STOCK OK. | L89: - | N89: =+SUM(L89:M89) -> 0 | O89: =-E89-N89+F89 -> -1 | P89: Recontar | Q89: 39 | R89: =31+8 -> 39 | S89: =+R89-Q89 -> 0 | T89: =IF(G89=0,0,IF(P89="Recontar",S89,IF(P89="Ajustar",O89,IF(P89="Canje",G89)))) -> 0 | U89: Sin Ajuste | V89: =IF(U89=$V$4,T89,"0") -> 0 | W89: =IF(U89=$W$4,T89,"0") -> 0 | X89: =IF(U89=$V$4,0,IF(U89=$W$4,0,IF(U89="-",0,IF(U89="Sin Ajuste",0,T89)))) -> 0 | Y89: =+V89*D89+W89*D89 -> 0 | Z89: =+E89*D89 -> 2071787.6 | AA89: =+Z89/$Z$3 -> 0.011278725 | AB89: =+AB88+AA89 -> 0.97856123
A90: D-11-01-B16 | B90: 135683901600 | C90: CORREA DISTRIBUCION | D90: 80369.086 | E90: 49 | F90: 51 | G90: =+F90-E90 -> 2 | H90: =+D90*G90 -> 160738.17 | I90: SC | J90: SC | K90: ARTICULO SOBRANTE X1 RECONTAR | L90: - | N90: =+SUM(L90:M90) -> 0 | O90: =-E90-N90+F90 -> 2 | P90: Recontar | Q90: 43 | R90: =28+14 -> 42 | S90: =+R90-Q90 -> -1 | T90: =IF(G90=0,0,IF(P90="Recontar",S90,IF(P90="Ajustar",O90,IF(P90="Canje",G90)))) -> -1 | U90: Faltante | V90: =IF(U90=$V$4,T90,"0") -> -1 | W90: =IF(U90=$W$4,T90,"0") -> 0 | X90: =IF(U90=$V$4,0,IF(U90=$W$4,0,IF(U90="-",0,IF(U90="Sin Ajuste",0,T90)))) -> 0 | Y90: =+V90*D90+W90*D90 -> -80369.086 | Z90: =+E90*D90 -> 3938085.2 | AA90: =+Z90/$Z$3 -> 0.021438771 | AB90: =+AB89+AA90 -> 1
C93: Inventario Rotativo 08.11.2024 - Autolux S.A. Salta
C94: Detalle | D94: Art. | E94: $ | F94: %
C95: Muestra | D95: =SUM(E5:E90) -> 5832 | E95: =+Z3 -> 1.8368988e+08 | F95: 1
C96: Sobrante | D96: =SUMIFS($G$5:$G$90,$G$5:$G$90,">0") -> 151 | E96: =SUMIFS($H$5:$H$90,$G$5:$G$90,">0") -> 5686929.9 | F96: =+E96/E95 -> 0.030959408
C97: Faltante | D97: =SUMIFS($G$5:$G$90,$G$5:$G$90,"<0") -> -82 | E97: =SUMIFS($H$5:$H$90,$G$5:$G$90,"<0") -> -3595831.8 | F97: =+E97/E95 -> -0.019575557
C98: Dif. Neta | D98: =SUBTOTAL(9,D96:D97) -> 69 | E98: =SUBTOTAL(9,E96:E97) -> 2091098.2 | F98: =SUBTOTAL(9,F96:F97) -> 0.011383851
C99: Dif Absoluta | D99: =+D96-D97 -> 233 | E99: =+E96-E97 -> 9282761.7 | F99: =+F96-F97 -> 0.050534966

Sheet 4.1
A1: =+Rotativo!A1 -> Autolux S.A. - Sucursal Salta
A2: =+Rotativo!A2 -> Control Integral de Depósito
A3: =+Rotativo!A3 -> Fecha: | B3: =+Rotativo!B3 -> 45604
B5: =+Rotativo!C93 -> Inventario Rotativo 08.11.2024 - Autolux S.A. Salta
B6: Cant. artic | C6: $ | D6: %
A7: Muestra | B7: =COUNT(Rotativo!D5:D90) -> 86 | C7: =+Rotativo!Z3 -> 1.8368988e+08 | D7: 1
A8: Faltantes | B8: =COUNTIFS(Rotativo!U5:U90,Rotativo!$V$4) -> 18 | C8: =SUMIFS(Rotativo!$Y$5:$Y$90,Rotativo!$U$5:$U$90,Rotativo!$V$4) -> -1715215.3 | D8: =+C8/C7 -> -0.00933756
A9: Sobrantes | B9: =COUNTIFS(Rotativo!U5:U90,Rotativo!$W$4) -> 6 | C9: =SUMIFS(Rotativo!$Y$5:$Y$90,Rotativo!$U$5:$U$90,Rotativo!$W$4) -> 474942.89 | D9: =+C9/C7 -> 0.0025855692
A10: Diferencia Neta | B10: =SUM(B8:B9) -> 24 | C10: =SUM(C8:C9) -> -1240272.4 | D10: =+C10/C7 -> -0.0067519908
A11: Diferencia Absoluta | B11: =+B8-B9 -> 12 | C11: =+-C8+C9 -> 2190158.2 | D11: =+C11/C7 -> 0.011923129
A17: Ajuste
A19: Fecha | B19: Nro. | C19: Cuenta | D19: Debe | E19: Haber | F19: Detalle
A20: =+B3 -> 45604 | B20: 1143100001 | C20: Repuestos Toyota en Stock | D20: =IF(C10<0,-C10,"0") -> 1240272.4 | E20: =IF(C10>0,C10,"") | F20: =CONCATENATE("Ajuste ",B5) -> Ajuste Inventario Rotativo 08.11.2024 - Autolux S.A. Salta
A21: =+A20 -> 45604 | B21: 6010500024 | C21: Mermas Inventarios | D21: =+-C8 -> 1715215.3 | F21: =+F20 -> Ajuste Inventario Rotativo 08.11.2024 - Autolux S.A. Salta
A22: =+A21 -> 45604 | B22: 6010500025 | C22: Sobrantes de Inventarios | E22: =C9 -> 474942.89 | F22: =+F21 -> Ajuste Inventario Rotativo 08.11.2024 - Autolux S.A. Salta

Sheet Hoja1
A1: Autolux S.A. - Sucursal Salta
A2: Control Integral de Depósito - Recuento
A3: Fecha: | B3: 45604 | E3: Inventario Rotativo | I3: Recuento
A4: Locación | B4: Artículo | C4: Descripción | D4: Cto.Rep. | E4: Stock | F4: Conteo | G4: Dif. | H4: Acción | I4: Stock | J4: Recuento
A5: A-01-A01 | B5: 10594001 | C5: 205/55 R16 91V Turanza ER300 | D5: 138147.13 | E5: -3 | F5: 1 | G5: 4 | H5: Recontar | I5: 21
A6: A-01-A03 | B6: 14199001 | C6: 265/60R18 110H - DUELER HT 684 II | D6: 217804.45 | E6: 15 | F6: 14 | G6: -1 | H6: Recontar | I6: 31
A7: B-02-05-C01 | B7: 15175001 | C7: 265/60R18 110T DUELER HT 684 II | D7: 219662.03 | E7: 1 | F7: 2 | G7: 1 | H7: Recontar | I7: 1
A8: ABI-02-A01 | B8: 0400720171C0 | C8: CENTRO VOLANTE (BLACK) | D8: 117012.5 | E8: 9 | F8: 14 | G8: 5 | H8: Recontar | I8: 19
A9: ABI-02-B01 | B9: 0400720171B0 | C9: CENTRO VOLANTE (DK.GRAY) | D9: 117012.5 | E9: 7 | F9: 18 | G9: 11 | H9: Recontar | I9: 15
A10: ABI-03-C01 | B10: 040040712200 | C10: KIT FFX CABLE ESPIRAL | D10: 148788.51 | E10: 4 | F10: 11 | G10: 7 | H10: Recontar | I10: 18
A11: ABI-03-D01 | B11: 040050591200 | C11: KIT PLACA SUCCION COMB. | D11: 59893.631 | E11: 11 | F11: 6 | G11: -5 | H11: Recontar | I11: 12
A12: B-06-11-A01 | B12: 426110KF7200 | C12: LLANTA 17 CHAPA 17X7.5 | D12: 151958.66 | E12: 18 | F12: 17 | G12: -1 | H12: Recontar | I12: 15
A13: B-06-11-A02 | B13: 426110KR8000 | C13: LLANTA CHAPA 17X6 | D13: 142247.43 | E13: 0 | F13: 1 | G13: 1 | H13: Recontar | I13: 15
A14: D-01-02-A01 | B14: 871390K08000 | C14: FILTRO A/A | D14: 14403.347 | E14: 302 | F14: 300 | G14: -2 | H14: Recontar | I14: 336
A15: D-01-02-B01 | B15: 871390K01000 | C15: FILTRO AIRE ACOND. | D15: 19677.231 | E15: 247 | F15: 246 | G15: -1 | H15: Recontar | I15: 243
A16: D-01-03-A01 | B16: 233900L07000 | C16: FILTRO COMBUSTIBLE | D16: 6541.969 | E16: -1 | F16: 0 | G16: 1 | H16: Recontar | I16: -1
... A40: D-11-01-B16 | B40: 135683901600 | C40: CORREA DISTRIBUCION | D40: 80369.086 | E40: 49 | F40: 51 | G40: 2 | H40: Recontar | I40: 43
